Workbook
Name _____TVL1: #REF!
Name _____TVL1: #REF!
Name _____TVL1: #REF!
Name _____TVL1: #REF!
Name _____TVL1: #REF!
Name ____TVL1: #REF!
Name ____TVL1: #REF!
Name ____TVL1: #REF!
Name ____TVL1: #REF!
Name ____TVL1: #REF!
Name ___TVL1: #REF!
Name ___TVL1: #REF!
Name ___TVL1: #REF!
Name ___TVL1: #REF!
Name ___TVL1: #REF!
Name __TVL1: #REF!
Name __TVL1: #REF!
Name __TVL1: #REF!
Name __TVL1: #REF!
Name __TVL1: #REF!
Name _TVL1: #REF!
Name _TVL1: #REF!
Name _TVL1: #REF!
Name _TVL1: #REF!
Name _TVL1: #REF!
Name A: {"ÿÿÿÿÿ"}
Name accessories: 0.2
Name D: {"ÿÿÿÿÿ"}
Name dau: #REF!,#REF!,#REF!,#REF!,#REF!
Name dau: #REF!,#REF!,#REF!,#REF!,#REF!
Name dau: #REF!,#REF!,#REF!,#REF!,#REF!
Name dau: #REF!,#REF!,#REF!,#REF!,#REF!
Name dau: #REF!,#REF!,#REF!,#REF!,#REF!
Name dgnckeoday: 10%
Name dgnclaptrunking: 6%
Name Document_array: {"ÿÿÿÿÿ"}
Name dongia: #REF!
Name dongia: #REF!
Name dongia: #REF!
Name dongia: #REF!
Name dongia: #REF!
Name hide: #REF!,#REF!,#REF!,#REF!,#REF!
Name hide: #REF!,#REF!,#REF!,#REF!,#REF!
Name hide: #REF!,#REF!,#REF!,#REF!,#REF!
Name hide: #REF!,#REF!,#REF!,#REF!,#REF!
Name hide: #REF!,#REF!,#REF!,#REF!,#REF!
Name hihe1: #REF!,#REF!,#REF!,#REF!,#REF!,#REF!,#REF!
Name hihe1: #REF!,#REF!,#REF!,#REF!,#REF!,#REF!,#REF!
Name hihe1: #REF!,#REF!,#REF!,#REF!,#REF!,#REF!,#REF!
Name hihe1: #REF!,#REF!,#REF!,#REF!,#REF!,#REF!,#REF!
Name hihe1: #REF!,#REF!,#REF!,#REF!,#REF!,#REF!,#REF!
Name HS: #REF!
Name HS: #REF!
Name HS: #REF!
Name HS: #REF!
Name HS: #REF!
Name HSlabor: 0.15
Name hsnc: 0.08
Name hsnc_bms: 10%
Name hstb: 1

Sheet 예산관리
E4: Ⅳ. 예산관리
F6: ■ | G6: 예산부서별 예산편성
H9: 연간예산편성(당초) | N9: 연간예산편성현황 (종합) | T9: 예산현황 조회 (월) | Z9: 예산현황 조회 (연간) | AF9: 예산조정신청 (등록) | AL9: 예산조정신청 (현황) | AR9: 예산조정신청 (편성)
H11: 적용연도 | K11: 2018 | O11: 예산부서 | R11: XXXXXX | U11: + | V11: 수출영업1-1팀 | AC11: 조회 | AF11: 저장 | AI11: * 천원단위 입력
H14: 예산부서 | Q14: 예산세목 | AB14: 월별 예산편성 현황
H15: PXXX | J15: 수출영업1-1팀 | N15: ▤ | Q15: 코드 | T15: 세목명 | AB15: 1월 | AE15: 2월 | AH15: 3월 | AK15: 4월 | AN15: 5월 | AQ15: 6월 | AT15: 7월 | AW15: 8월 | AZ15: 9월 | BC15: 10월 | BF15: 11월 | BI15: 12월 | BL15: 연간계
H16: XXXX | J16: 수출영업1-1팀 | P16: □ | Q16: XXXXX | T16: 조직관리비
H17: XXXX | J17: 수출영업1-2팀 | P17: □ | Q17: XXXXX | T17: 회의비식대
H18: XXXX | J18: 수출영업본부장 | P18: □ | Q18: XXXXX | T18: 국내출장숙박비
H19: XXXX | J19: 수출영업1부문장 | P19: □ | Q19: XXXXX | T19: 국내출장일비
H20: XXXX | J20: 수출영업2부문장 | P20: □ | Q20: XXXXX | T20: 국내출장기타경비
P21: □ | Q21: XXXXX | T21: 해외출장항공료
P22: □ | Q22: XXXXX | T22: 해외출장숙박비
P23: □ | Q23: XXXXX | T23: 해외출장일비
P24: □ | Q24: XXXXX | T24: 해외출장기타경비
G26: * 연간예산편성은 기중 마감이 진행되지 않은 달의 예산은 수정가능 (단, 마감이후 기간소급분 수정 불가)
G27: * Profit center 는 예산편성 대상부서 X
H30: 연간예산편성(당초) | N30: 연간예산편성현황 (종합) | T30: 예산현황 조회 (월) | Z30: 예산현황 조회 (연간) | AF30: 예산조정신청 (등록) | AL30: 예산조정신청 (현황) | AR30: 예산조정신청 (편성)
H32: 적용연도 | K32: 2018 | O32: 예산부서 | R32: XXXXXX | U32: + | V32: 수출영업1-1팀 | AC32: 조회 | AF32: 임의예산편성 저장
H35: 예산부서 | Q35: 예산세목 | Z35: 예산 구분 | AB35: 월별 예산편성 현황 (종합-조정분 반영)
H36: PXXX | J36: 수출영업1-1팀 | N36: ▤ | Q36: 코드 | T36: 세목명 | AB36: 1월 | AE36: 2월 | AH36: 3월 | AK36: 4월 | AN36: 5월 | AQ36: 6월 | AT36: 7월 | AW36: 8월 | AZ36: 9월 | BC36: 10월 | BF36: 11월 | BI36: 12월 | BL36: 연간계 | BO36: ▤
H37: XXXX | J37: 수출영업1-1팀 | P37: □ | Q37: XXXXX | T37: 조직관리비 | Z37: 당초
H38: XXXX | J38: 수출영업1-2팀 | Z38: 추가
H39: XXXX | J39: 수출영업본부장 | Z39: 임의
H40: XXXX | J40: 수출영업1부문장 | Z40: 소계
H41: XXXX | J41: 수출영업2부문장 | P41: □ | Q41: XXXXX | T41: 회의비식대 | Z41: 당초
Z42: 추가
Z43: 임의
Z44: 소계
P45: □ | Q45: XXXXX | T45: 국내출장숙박비 | Z45: 당초
Z46: 추가
Z47: 임의
Z48: 소계
G50: * 예산편성된 Data 만 조회/임의예산편성하는 메뉴임 (예산 잔액이월, 선집행 등 예산집행과 관련된 Data 제외)
G51: * 예산구분 정의
G52: ① 당초(예산) : 연간예산편성(당초) 메뉴에서 사업계획시 부서별/예산세목별/월별로 편성된 예산 (기중 수정은 연간 Total 금액내에서만 조정 가능)
G53: ② 추가(예산) : 현업 예산조정신청 및 승인 Process 를 통해 기중 추가예산 승인된 예산금액
G54: ③ 임의(예산) : 경영관리팀 담당자 임의로 특정목적을 위해 편성된 예산 → 임의예산을 '부서별-예산세목별-임의예산' 항목 월별 금액 입력후, '임의예산편성 저장' 시 해당 예산편성 반영 (단, 연간예산편성(당초) 와는 별개임)
F57: ■ | G57: 예산현황조회
H60: 연간예산편성(당초) | N60: 연간예산편성현황 (종합) | T60: 예산현황 조회 (월) | Z60: 예산현황 조회 (연간) | AF60: 예산조정신청 (등록) | AL60: 예산조정신청 (현황) | AR60: 예산조정신청 (편성)
H62: 조회년월 | K62: 2017-10 | O62: 예산부서 | R62: XXXXXX | U62: + | V62: 수출영업1-1팀 | AC62: 조회 | AF62: 저장 | AJ62: 조정신청
H65: 예산부서 | Q65: 예산세목 | AB65: 당월 예산현황 | BP65: 선집행 신청 가능잔액 (당월예산외) | BT65: 년간 예산현황
H66: PXXX | J66: 수출영업1-1팀 | N66: ▤ | P66: □ | AB66: 편성내역 | AN66: 신청현황 | AT66: 조정현황 | BC66: 집행실적 | BF66: 예산잔액 | BT66: 편성내역 | BZ66: 집행실적 | CF66: 잔존예산
H67: XXXX | J67: 수출영업1-1팀 | Q67: 코드 | T67: 세목명 | AB67: 당초예산 | AE67: 전월이월 | AH67: 선집행 | AK67: 가용예산 | AN67: 선집행 | AQ67: 추가 | AT67: 선집행 | AW67: 추가 | AZ67: 조정계 | BF67: 당월 잔액 | BI67: 차월 이월 | BL67: 소 계 | BT67: 당월누적 | BW67: 연간예산 | BZ67: 당월누적 | CC67: 집행율 | CF67: (금액) | CI67: 잔존월평균
H68: XXXX | J68: 수출영업1-2팀 | P68: ▣ | Q68: XXXXX | T68: 조직관리비
H69: XXXX | J69: 수출영업본부장 | P69: ▣ | Q69: XXXXX | T69: 회의비식대
H70: XXXX | J70: 수출영업1부문장 | P70: □ | Q70: XXXXX | T70: 협의회
H71: XXXX | J71: 수출영업2부문장 | P71: □ | Q71: XXXXX | T71: 국내출장교통비
P72: □ | Q72: XXXXX | T72: 국내출장숙박비
P73: □ | Q73: XXXXX | T73: 국내출장일비
P74: □ | Q74: XXXXX | T74: 국내출장기타경비
P75: □ | Q75: XXXXX | T75: 해외출장항공료
P76: □ | Q76: XXXXX | T76: 해외출장숙박비 | AB76: 1200000 | AE76: 50000 | AH76: -200000 | AK76: =AB76+AE76+AH76 -> 1050000 | AN76: (50,000) | AQ76: (100,000) | AZ76: =AT76+AW76 -> 0 | BC76: 1200000 | BF76: =AK76+AZ76-BC76 -> -150000 | BL76: =BF76+BI76 -> -150000 | BT76: 6000000 | BW76: 5000000 | BZ76: 5500000 | CC76: =BZ76/BW76 -> 1.1 | CF76: =BT76-BZ76 -> 500000 | CI76: =CF76/2 -> 250000
P77: □ | Q77: XXXXX | T77: 해외출장일비
P78: □ | Q78: XXXXX | T78: 해외출장기타경비
H80: 당월 계정별 비용집행현황
I82: 실제 집행전표 현황 표기
H91: 연간예산편성(당초) | N91: 연간예산편성현황 (종합) | T91: 예산현황 조회 (월) | Z91: 예산현황 조회 (연간) | AF91: 예산조정신청 (등록) | AL91: 예산조정신청 (현황) | AR91: 예산조정신청 (편성)
H93: 조회연도 | K93: 2017 | O93: 예산부서 | R93: XXXXXX | U93: + | V93: 수출영업1-1팀 | AC93: 조회 | AF93: 저장 | AJ93: 조정신청
H95: 예산세목 | V95: 당월 예산현황 | BI95: 년간 예산현황
T96: 월별 | V96: 편성내역 | AH96: 신청현황 | AN96: 조정현황 | AW96: 집행실적 | AZ96: 예산잔액 | BI96: 편성내역 | BO96: 집행실적 | BU96: 잔존예산
H97: 코드 | K97: 세목명 | V97: 당초예산 | Y97: 전월이월 | AB97: 선집행 | AE97: 가용예산 | AH97: 선집행 | AK97: 추가 | AN97: 선집행 | AQ97: 추가 | AT97: 조정계 | AZ97: 당월 잔액 | BC97: 차월 이월 | BF97: 소 계 | BI97: 연간예산 | BL97: 당월누적 | BO97: 당월누적 | BR97: 집행율 | BU97: (금액) | BX97: 잔존월평균
H98: XXXXX | K98: 조직관리비 | T98: 1월 | BC98: 1000
H99: XXXXX | K99: 회의비식대 | T99: 2월 | Y99: 1000
H100: XXXXX | K100: 협의회 | T100: :
H101: XXXXX | K101: 국내출장교통비 | T101: 11월
H102: XXXXX | K102: 국내출장숙박비 | T102: 12월
H104: 계정별 비용집행현황
I107: 실제 집행전표 현황 표기
G112: * 경영기획팀 담당자는 '임의조정' 필드에 대한 수기예산편성 가능
F115: ■ | G115: 예산조정신청
G117: - 예산조정 유형
H119: ① (예산) 선집행 : 연간 혹은 예산세목 설정시 '선집행 대상기간' 내 편성된 예산잔액 기준, 비용 선집행 → 기안상신 불필요 (단, 조정신청 진행)
H120: ② 예산추가 : 연간 편성예산外 추가로 요청해 편성되는 예산 → 기안상신 必
G122: [현업담당자용]
H124: 연간예산편성(당초) | N124: 연간예산편성현황 (종합) | T124: 예산현황 조회 (월) | Z124: 예산현황 조회 (연간) | AF124: 예산조정신청 (등록) | AL124: 예산조정신청 (현황) | AR124: 예산조정신청 (편성)
AZ126: 예산조정 신청서 | BH126: 결제1 | BJ126: 결제2 | BL126: 결제3
H127: 신청년월 | K127: 2017-10 | AI127: 신규 | AL127: 저장 | AO127: 기안작성 | BA127: 1234-12456-가-12 | BH127: 합의1 | BJ127: 합의2 | BL127: 합의3
H129: 신청코드 | K129: XXXXX-171101-01 | P129: 담당자 | S129: XXXXXX | V129: + | W129: 홍길동 | Z129: ZZ사업부 | BA129: 제목 : 홍 길동 인도네시아 출장비 예산조정요청의 건
H131: 예산부서 | K131: XXXXXX | N131: + | O131: ZZ사업부 | BA131: 조정신청대상계정별 월 : 가용예산, 집행실적, 예산잔액
BA132: 예산조정신청 유형 및 신청액 (요청계정별 한정승인 가능)
H133: (+)행추가 | K133: (-)행삭제 | BA133: [예산조정신청 사유]
H135: □ | I135: No | K135: 예산세목 | V135: 당월예산 잔액 | Z135: 선집행 가능 예산잔액 (당월제외) | AD135: 조정유형 | AH135: 신청금액 | AL135: 신청사유요약 | BA135: ZZ사업부 인도네시아 생산컨펌 위한 ....
K136: 코드 | O136: 세목명 | BA136: 당월 XXX 사유로 가용예산 대비 비용초과 됨.
H137: □ | I137: 01 | K137: XXXXX | N137: + | O137: 해외출장숙박비 | V137: 0 | Z137: 100000 | AD137: 선집행 | AG137: ▼ | AH137: 50000 | AL137: 홍 길동 인도네시아 생산지원 (숙박비 초과) | BA137: 참조문서 | BD137: 출장사전신고서
H138: □ | I138: 02 | K138: XXXXX | N138: + | O138: 해외출장일비 | V138: 0 | Z138: 0 | AD138: 예산추가 | AG138: ▼ | AH138: 100000 | AL138: 홍 길동 인도네시아 생산지원 (일비 부족) | BA138: 첨부파일 | BD138: 출장비 집행현황
V139: =V137+V138 -> 0 | Z139: =Z137+Z138 -> 100000 | AH139: =AH137+AH138 -> 150000
G141: * 신청코드의 필요여부는 경영정보팀에서 판단요망.
H144: 연간예산편성(당초) | N144: 연간예산편성현황 (종합) | T144: 예산현황 조회 (월) | Z144: 예산현황 조회 (연간) | AF144: 예산조정신청 (등록) | AL144: 예산조정신청 (현황) | AR144: 예산조정신청 (편성)
H146: 조회기간 | K146: 2017-10-01 | N146: - | O146: 2017-10-31 | R146: 담당자 | U146: XXXXXX | X146: + | Y146: 홍길동 | AB146: ZZ사업부 | AH146: 예산부서 | AK146: XXXXXX | AN146: + | AO146: ZZ사업부
H148: 신청유형 | K148: 예산추가 | N148: ▼ | P148: 승인현황 | S148: 승인 | V148: ▼ | Y148: 신청코드 | AB148: XXXXX-171101-01 | AS148: 조회
H150: 상신일자 | K150: 신청코드 | Q150: No | S150: 예산세목 | AD150: 신청유형 | AG150: 신청금액 | AK150: 승인 현황 | AN150: 승인 유형 | AQ150: 기안문서번호
S151: 코드 | W151: 세목명
H152: 2017-10-31 | K152: XXXXX-171101-01 | Q152: 001 | S152: XXXXX | W152: 해외출장숙박비 | AD152: 선집행 | AG152: 50000 | AK152: 승인 | AN152: 선집행 | AQ152: 1234-12456-가-12
H153: 2017-10-31 | K153: XXXXX-171101-01 | Q153: 001 | S153: XXXXX | W153: 해외출장일비 | AD153: 예산추가 | AG153: 100000 | AK153: 대체승인 | AN153: 선집행 | AQ153: 1234-12456-가-12
H154: 2017-10-31 | K154: XXXXX-171101-01 | Q154: 001 | S154: XXXXX | W154: 해외출장일비 | AD154: 예산추가 | AG154: 100000 | AK154: 반려 | AN154: 반려 | AQ154: 1234-12456-가-12
H155: 2017-10-31 | K155: XXXXX-171101-02 | Q155: 001 | S155: XXXXX | W155: 해외출장일비 | AD155: 선집행 | AG155: 100000 | AK155: 진행중 | AN155: - | AQ155: 1234-12456-가-14
G157: * 기안문서번호 클릭시, 해당 GW내 기안조회 가능토록 개발요망
G158: * 마감월 이후, 소급 예산신청 불가
G160: [예산담당자용]
...

Sheet 최초안
G2: *** 생산사전원가 세부정보 Tab 필요, 니트 Artwork / 쉐이드밴드 컨펌과정 및 코멘트 필요, 스웨터팀 진척율 시트참고, 팬츠팀 업체스케쥴 시트 참고
G3: *** 예상사전원가, 생산사전원가 입력일 정보 필요, 각 TAB 별 진행 History comments 입력기능 필요
G4: *** 제약사항 : 등록방법, 등록기준, 등록Depth, 등록범위, 용어개념화 등 체계화 미흡 (사전 BPR 작업 필요)
G6: 스타일정보
H8: Style no. | L8: 차수 | N8: File no. | R8: 스케치 | T8: 시즌 | W8: 브랜드 | AD8: COLOR | AG8: 기획수량 | AK8: 담당자
W10: 상위 | Y10: 하위 | AA10: 복종 | AK10: Design | AN10: MD | AQ10: 소싱 | AT10: Fabric
G11: □ | H11: MSZ5TS1001 | L11: A | N11: TO19TT7001 | R11: [+] | T11: SP | W11: TT | Y11: MS | AA11: JUMPER | AD11: 5 | AF11: [+] | AG11: 1500 | AJ11: [+] | AK11: O OO | AN11: O OO | AQ11: O OO | AT11: O OO
G12: □ | R12: [+] | AF12: [+] | AJ12: [+]
G13: □ | R13: [+] | AF13: [+] | AJ13: [+]
G14: □ | R14: [+] | AF14: [+] | AJ14: [+]
S15: ↑ | T15: 제품이미지 | AF15: ↑ | AG15: 세부컬러 | AJ15: ↑ | AK15: 칼라/사이즈별 수량정보
L17: 소싱정보
H19: Style no. | L19: 차수 | N19: 소싱팀 | Q19: 소싱형태 | U19: 원산지/무역정보 | AE19: 소싱업체 | AM19: 작지정보 | AS19: 납기일 (In-DC)
U21: 원산지 | X21: HS Code | AB21: 무역협정 | AE21: 결제업체 | AI21: 봉제공장 | AM21: 수취일 | AP21: 확정일
G22: □ | H22: MSZ5TS1001 | L22: A | N22: 니트1팀 | Q22: 임가공 | U22: 미얀마 | X22: 6109.10.1000 | AB22: GSP | AE22: SHINSUNG Int'l | AI22: SSTS#1 | AM22: 2018-06-14 | AP22: 2018-07-11 | AS22: 43419 | AV22: [+]
G23: □ | AV23: [+]
G24: □ | AV24: [+]
G25: □ | AV25: [+]
G26: * 작지정보 별도표기 여부 문의 | AS26: ↑ | AT26: 최근기준 | AV26: ↑ | AW26: 납기일 변경 History
Q28: 단가정보
H30: Style no. | L30: 차수 | N30: 기획수량 | Q30: PCS당 | AV30: Amount (기획수량 기준) | BG30: PCS당
Q31: Retail Price | W31: 사전원가 | AI31: 사후원가 (입고평균) | AL31: 생산 배수 | BG31: FOB (USD)
Q32: 예상 | T32: 확정 | W32: MD협의 | Z32: 예상 | AC32: 생산(최초) | AF32: 생산(최종) | AL32: MD협의 | AN32: 예상 | AP32: 사전(초) | AR32: 사전(종) | AT32: 사후 | AV32: Retail Price | AY32: 사전COGM | BB32: 사후COGM | BG32: 예상 | BJ32: 확정
G33: □ | H33: MSZ5TS1001 | L33: A | N33: 1500 | Q33: 199900 | T33: 199000 | W33: 50000 | Z33: 49000 | AC33: 49200 | AF33: 48000 | AI33: 48500 | AL33: =IF($T33<>0,($T33/1.1)/W33,($Q33/1.1)/W33) -> 3.6181818 | AN33: =IF($T33<>0,($T33/1.1)/Z33,($Q33/1.1)/Z33) -> 3.6920223 | AP33: =IF($T33<>0,($T33/1.1)/AC33,($Q33/1.1)/AC33) -> 3.677014 | AR33: =IF($T33<>0,($T33/1.1)/AF33,($Q33/1.1)/AF33) -> 3.7689394 | AT33: =IF(AI33=0,0,IF($T33<>0,($T33/1.1)/AI33,($Q33/1.1)/AI33)) -> 3.7300843 | AV33: =IF($T33<>0,$N33*T33,$N33*Q33) -> 298500000 | AY33: =IF($AF33<>0,$N33*AF33,$N33*Z33) -> 72000000 | BB33: =IF($AI33=0,0,AI33*N33) -> 72750000
G34: □
G35: □
G36: □
G37: * 입고원가 (셔츠팀 기준 DDP Price) 는 입고종결처리전 현업에서 별도 정확한 산출없이 추정 불가. 따라서, 시스템 기준 입고원가 끌어와야 함 | BG37: ↑ 시스템 등록정보 있는지 확인필요
G38: * PCS당 사전원가 USD기준정보 필요한지 여부 체크
G39: * 빨강색 사후원가 관련 필드 삭제 or 별도조회 여부 체크
W40: 자재정보
H42: Style no. | L42: 차수 | O42: 원자재 | BT42: 부자재 | CE42: 원자재
O43: SPEC | AE43: 거래처 | AL43: 원단발주 | AU43: 제검사 | BI43: 원단입고 | BR43: SHADE BAND | BT43: 원단발주 | CE43: 요척
O44: 혼용율 | V44: DESCRIPTION | AE44: 업체명 | AI44: CO | AL44: 접수일 | AO44: 발주일 | AR44: 납기일 | AU44: BT cfm | AY44: 원단 cfm | BC44: APP YDS | BF44: KC/이화학 | BI44: 운송유형 | BL44: ETD | BO44: ETA | BT44: 발주일 | BW44: ETD | BZ44: ETA | CE44: 개발 | CG44: 공장
G45: □ | H45: MSZ5TS1001 | L45: A | N45: ▣ | O45: 49%WOOL 49%POLYESTER 2%POLYURETHANE | V45: 2/90*1/50PU 280G/M 49%WOOL 49%POLYESTER 2%POLYURETHANE 57" | AE45: SINO(AOYANG) | AI45: 중국 | AL45: 2018-08-01 | AO45: 2018-08-04 | AR45: 2018-09-01 | AU45: 2018-09-08 | AX45: [+] | AY45: 2018-09-08 | BB45: [+] | BC45: 2018-09-09 | BF45: 인열 불합격 | BI45: VESSEL | BL45: 2018-09-08 | BO45: 2018-09-09 | BR45: [+] | BT45: 2018-08-04 | BW45: 2018-09-01 | BZ45: 2018-09-01
G46: □ | AX46: [+] | BB46: [+] | BR46: [+]
G47: □ | AX47: [+] | BB47: [+] | BR47: [+]
G48: □ | AX48: [+] | BB48: [+] | BR48: [+]
G49: * 원단 Main 한 종류만 정보를 표기해도 무방한지 체크 | N49: ↑스타일 자재정보등록 조회 | V49: ↑ | W49: Body (Main) 기준으로 조회 | BI49: ↑ 시스템 등록정보 유무 확인필요 | BT49: ↑ 시스템 등록정보 유무 확인필요 | CE49: ↑ 현재 Tab 필요여부 문의
G50: * 요척합의일 필요한지 문의 | BI50: ↑ 원단 분할선적시 처리 방법 문의
AB51: 생산정보
H53: Style no. | L53: 차수 | N53: SAMPLE | AG53: Production
N54: ART WORK | P54: APP | W54: FPP | AD54: 수납 | AG54: Cutting (일자) | AJ54: Sewing | AP54: 생산수량 | AY54: QA Report
P55: 접수일 | T55: 승인일 | W55: 접수일 | AA55: 승인일 | AD55: 승인일 | AJ55: 시작일 | AM55: 종료일 | AP55: 기획수량 | AS55: 누적생산 | AV55: Balance
G56: □ | H56: MSZ5TS1001 | L56: A | N56: [+] | P56: 2018-09-08 | S56: [+] | T56: 2018-09-08 | W56: 2018-09-08 | Z56: [+] | AA56: 2018-09-08 | AD56: 2018-09-08 | AJ56: 2018-09-15 | AM56: 2018-09-30 | AP56: 1500 | AS56: 500 | AV56: =AS56-AP56 -> -1000 | AY56: [+]
G57: □ | N57: [+] | S57: [+] | Z57: [+] | AY57: [+]
G58: □ | N58: [+] | S58: [+] | Z58: [+] | AY58: [+]
G59: □ | N59: [+] | S59: [+] | Z59: [+] | AY59: [+]
AS60: ↑ | AT60: 차후 생산실적 연동 | AY60: ↑ | AZ60: QA시스템 연동
AG62: 선적/입고정보
H64: Style no. | L64: 차수 | N64: Shipment | AA64: In-DC
N65: Schedule | W65: 선적수량 | Z65: ▣ | AA65: 일고일 | AH65: 입고수량 | AR65: 누 적 입고금액 (Retail P.기준) | AU65: 입고원가 | AZ65: 생산배수
N66: 운송유형 | Q66: ETD | T66: ETA | AA66: 예정일 | AD66: 1차 입고 | AG66: ▣ | AH66: 기획수량 | AK66: 입고누적 | AO66: Balance | AU66: 누적 | AX66: PCS당 | AZ66: 사전 | BB66: 사후 | BD66: GAP
G67: □ | H67: MSZ5TS1001 | L67: A | N67: VESSEL | Q67: 2018-09-08 | T67: 2018-09-08 | W67: 5000 | Z67: [+] | AA67: 2018-09-08 | AD67: 2018-09-08 | AG67: [+] | AH67: 1500 | AK67: 500 | AN67: [+] | AO67: =AH67-AK67 -> 1000 | AR67: 99500000 | AU67: =AI33*AK67 -> 24250000 | AX67: =AU67/AK67 -> 48500 | AZ67: =AR33 -> 3.7689394 | BB67: =(T33/1.1)/AX67 -> 3.7300843 | BD67: =BB67/AZ67-1 -> -0.010309278
G68: □ | Z68: [+] | AG68: [+] | AN68: [+]
G69: □ | Z69: [+] | AG69: [+] | AN69: [+]
G70: □ | Z70: [+] | AG70: [+] | AN70: [+]
N71: ↑ | O71: 1차 선적분 기준 Display (2차분 부터 [+] 눌러 조회) | AD71: ↑ | AE71: 1차 선적분 기준 Display (2차분 부터 [+] 눌러 조회) | AN71: ↑ | AO71: 분할입고 내역 조회 | AZ71: ↑ 사전대비 사후 배수로 보는지 문의

Sheet 제품유형분류
B3: 카테고리(전산) | D3: 카테고리 | F3: 대품종 | H3: 품종 | J3: 프로그램
B5: 01_KNIT | D5: Bags | F5: SET-UP | H5: BOTTOM | J5: 5-Pocket Pants
B6: 02_SHIRTS | D6: Beach Wear | F6: 가죽&FUR | H6: Short 스커트 | J6: 5-Pocket Shorts
B7: 03_SWEATER | D7: Belt | F7: 기타 | H7: TOP | J7: 7L-Shirts
B8: 04_PANTS | D8: Cardigan | F8: 니트 셔츠 | H8: Turtle | J8: 7L-Tees
B9: 05_DENIM | D9: Coat | F9: 데님 | H9: T-에리 | J9: Active Cardigan
B10: 06_OUTER | D10: Collar Tees | F10: 사파리 | H10: VEST | J10: Active Collar Tees
B11: 07_DRESS/SKIRTS | D11: Cooling Tees | F11: 소품 | H11: V-넥 | J11: Active Hoodie
B12: 08_UNDER | D12: Dress Shirts | F12: 수트 | H12: 가방 | J12: Active Hoodie Cardigan
B13: 09_SUITS | D13: Glove | F13: 스웨터 | H13: 가죽사파리 | J13: Active MTM
B14: 10_ACC/ETC | D14: Hat/Cap | F14: 스커트 | H14: 가죽자켓 | J14: Active Shorts
D15: HomeWear | F15: 언더웨어 | H15: 가죽점퍼 | J15: Active Sweat Pants
D16: Hoodie Cardigan | F16: 우븐 셔츠 | H16: 기타 | J16: Active Tanks
D17: Hoodies | F17: 원피스 | H17: 니트반바지 | J17: Active Tees
D18: InnerWear | F18: 자켓 | H18: 니트팬츠 | J18: Active Vest
D19: Jacket | F19: 점퍼 | H19: 다운점퍼 | J19: A-Line One-Piece
D20: Jeans | F20: 조끼 | H20: 더블재킷 | J20: A-Line Skirt
D21: Jumper | F21: 코트 | H21: 더블코트 | J21: Back Pack
D22: Jumpsuit | F22: 팬츠 | H22: 데님반바지 | J22: Band Pants
D23: Leather/Fur Jacket | H23: 데님셔츠 | J23: Banding Shorts
D24: Leggings | H24: 데님스커트 | J24: Basic Jeans
D25: MTM | H25: 데님자켓 | J25: Basic Tanks
D26: Muffler | H26: 데님팬츠 | J26: Basic Tees
D27: Neck-Tie | H27: 드레스셔츠 | J27: Beach Bottom
D28: One-Piece | H28: 라운드 | J28: Beach Outer
D29: Other Accessories | H29: 라운드(V넥 등) | J29: Beach Top
D30: Other UnderWear | H30: 라운지 반바지 | J30: Belt
D31: Shirts | H31: 라운지 원피스 | J31: Blazer
D32: Shoes | H32: 라운지 후드집업 | J32: Blouse
D33: Shorts | H33: 라운지상의 | J33: BOA Cardigan
D34: Skirts | H34: 라운지하의 | J34: BOA Hoodie Cardigan
... D47: Woven Pants | H47: 셔츠형 | J47: Check Suit Vest
H48: 수트조끼 | J48: Chino Pants
H49: 수트팬츠 | J49: Chino Shorts
H50: 스커트 | J50: Collabo-Tees
H51: 시계 | J51: Cool-Air
H52: 신발 | J52: Corduroy Pants
H53: 싱글재킷 | J53: Corduroy Shirts
H54: 싱글코트 | J54: Denim Jacket
H55: 양말 | J55: Denim Jeggings
H56: 언더웨어 셋업 | J56: Denim Shirts
H57: 오픈형(CARDIGAN) | J57: Denim Shorts
H58: 오픈형티(맨투맨 등) | J58: Dobby Shirts
H59: 원피스 | J59: Down Vest
... H79: 후드티 | J79: Jacket-Like Shirts
J80: Jacket-Type Jumper
J81: Jersey Collar Tees
J82: Jumpsuit
J83: Knit Leggings
J84: Knit Vest
J85: Leather Jacket
J86: Leather Mustang
J87: Leggings Shorts
J88: Light Down Vest
J89: Light Padding Vest
J90: Light Weight Jumper
J91: Linen Shirts
... J206: Woven Vest

Sheet 팀별관리양식
C4: 아우터팀 | E4: 제품기획 | P4: 작지 완성도 | R4: 오더 관리 | AF4: FABRIC | AT4: PRODUCTIOIN | BE4: SHIPMENT SCHEDULE | BK4: 입고 정보 | BM4: 주차별 입고 예상 스케줄
E5: NO | F5: 생산팀 | G5: 생산담당자 | H5: SEASON | I5: LINE | J5: ITEM | K5: STYLE NO | L5: 생산차수 | M5: 구분 | N5: COLOR | O5: Q'TY | P5: 작지 수취일 | Q5: 퀄러티확정일 | R5: 납기 | S5: 원가정보 | Z5: 거래형태 | AA5: 생산처 | AB5: 생산국 | AC5: 공장명/업체명 | AD5: 혼용률 | AE5: 원단구분 (우븐/니트) | AF5: DESCRIPTION | AG5: 업체 | AH5: FAB CO | AI5: 원단발주서 | AM5: BT | AN5: 원단컨펌 | AO5: APP YDS | AP5: KC/이화학 TEST(유/무) | AR5: 원단입고 | AT5: APP | AW5: FPP | AY5: PLAN | AZ5: CUTTING | BA5: SEWING | BC5: FINAL INSPECTION REPORT | BD5: 수납 | BE5: ETD | BF5: ETA | BG5: SHIP MODE | BH5: Q'TY | BI5: 예상 IN-DC | BJ5: REMARK | BK5: 1차 입고일자 | BL5: 입고 누적수량 | BM5: 1차 입고 | BO5: 2차 입고 | BQ5: 3차 입고 | BS5: 4차 입고 | BU5: 잔량 입고
S6: 사사전원가 | T6: 사전원가 | U6: 예상판매가(원) | V6: 결정판매가(원) | W6: 생산원가합 | X6: 판매가합 | Y6: 실배수 (V-) | AI6: 접수일 | AJ6: 발주일 | AK6: 납기 | AL6: 최종납기 | AM6: CFM | AN6: CFM | AQ6: ETD (최초선적) | AR6: ETA | AS6: SHIP MODE | AT6: 1차 QC접수 | AU6: 2차 QC접수 | AV6: CFM | AW6: FPP 접수 | AX6: CFM | AY6: 투입계획 | AZ6: 실제일자 | BA6: START (실제일자) | BB6: FININSH (실제일자) | BD6: CFM | BM6: 예정 일자 | BN6: 예상 수량 | BO6: 예정 일자 | BP6: 예상 수량 | BQ6: 예정 일자 | BR6: 예상 수량 | BS6: 예정 일자 | BT6: 예상 수량 | BU6: 예정 일자 | BV6: 예상 수량
E7: 1 | F7: 아우터팀 | G7: 유승모 | H7: 봄 | I7: AB | J7: JUMPER | K7: ABZ1JP1101 | L7: A | N7: 2 | O7: 2500 | P7: 43265 | R7: 43442 | S7: 36800 | U7: 199900 | W7: 92000000 | X7: 499750000 | Y7: 4.9382411 | Z7: 임가공 | AA7: 아우터팀 | AB7: 미얀마 | AC7: SSTS#1 | AD7: 100%POLYESTER | AE7: 우븐 | AF7: P50D DTY * P50D DTY 168*114 WR TPU LAMI 100%POLYESTER 55" | AG7: 예진 | AH7: 국내 | AI7: 43269 | AJ7: 43269 | AK7: 43340 | AL7: 43342 | AM7: 43288 | AN7: 43306 | AO7: 43308 | AP7: 인열 불합격 | AQ7: 43342 | AR7: 43363 | AS7: VESSEL | AT7: 43322 | AU7: 43339 | AV7: 43341
C9: 정장팀 | E9: 제품기획 | P9: 작지 완성도 | R9: 오더 관리 | AF9: FABRIC | AT9: PRODUCTIOIN | BE9: SHIPMENT SCHEDULE | BK9: 입고 정보 | BM9: 주차별 입고 예상 스케줄
E10: NO | F10: 생산팀 | G10: 생산담당자 | H10: SEASON | I10: LINE | J10: ITEM | K10: STYLE NO | L10: 생산차수 | M10: 구분 | N10: COLOR | O10: Q'TY | P10: 작지 수취일 | Q10: 퀄러티확정일 | R10: 납기 | S10: 원가정보 | Z10: 거래형태 | AA10: 생산처 | AB10: 생산국 | AC10: 공장명/업체명 | AD10: 혼용률 | AE10: 원단구분 (우븐/니트) | AF10: DESCRIPTION | AG10: 업체 | AH10: FAB CO | AI10: 원단발주서 | AM10: BT | AN10: 원단컨펌 | AO10: APP YDS | AP10: KC/이화학 TEST(유/무) | AR10: 원단입고 | AT10: APP | AW10: FPP | AY10: PLAN | AZ10: CUTTING | BA10: SEWING | BC10: FINAL INSPECTION REPORT | BD10: 수납 | BE10: ETD | BF10: ETA | BG10: SHIP MODE | BH10: Q'TY | BI10: 예상 IN-DC | BJ10: REMARK | BK10: 1차 입고일자 | BL10: 입고 누적수량 | BM10: 1차 입고 | BO10: 2차 입고 | BQ10: 3차 입고 | BS10: 4차 입고 | BU10: 잔량 입고
S11: 사사전원가 | T11: 사전원가 | U11: 예상판매가(원) | V11: 결정판매가(원) | W11: 생산원가합 | X11: 판매가합 | Y11: 실배수 (V-) | AI11: 접수일 | AJ11: 발주일 | AK11: 납기 | AL11: 최종납기 | AM11: CFM | AN11: CFM | AQ11: ETD (최초선적) | AR11: ETA | AS11: SHIP MODE | AT11: 1차 QC접수 | AU11: 2차 QC접수 | AV11: CFM | AW11: FPP 접수 | AX11: CFM | AY11: 투입계획 | AZ11: 실제일자 | BA11: START (실제일자) | BB11: FININSH (실제일자) | BD11: CFM | BM11: 예정 일자 | BN11: 예상 수량 | BO11: 예정 일자 | BP11: 예상 수량 | BQ11: 예정 일자 | BR11: 예상 수량 | BS11: 예정 일자 | BT11: 예상 수량 | BU11: 예정 일자 | BV11: 예상 수량 | BW11: 요척합의
E12: 1 | F12: 정장팀 | G12: 손지선 | H12: 사계절 | I12: AB | J12: SUIT상 | K12: ABZ5SB1201 | L12: A | M12: SOLID | N12: 2 | O12: 8500 | P12: 43292 | Q12: 43266 | R12: 43419 | S12: 37524.4 | U12: 199000 | W12: 318957400 | X12: 1691500000 | Y12: 4.8211055 | Z12: CMT | AA12: 정장팀 | AB12: 베트남 | AC12: 블루컴퍼니 | AD12: 49%WOOL 49%POLYESTER 2%POLYURETHANE | AE12: 우븐 | AF12: 2/90*1/50PU 280G/M 49%WOOL 49%POLYESTER 2%POLYURETHANE 57" | AG12: SINO(AOYANG) | AH12: 중국 | AI12: 43259 | AJ12: 43259 | AK12: 43358
E13: 2 | F13: 정장팀 | G13: 손지선 | H13: 사계절 | I13: AB | J13: SUIT하 | K13: ABZ5SP1201 | L13: A | M13: SOLID | N13: 2 | O13: 10625 | P13: 43292 | Q13: 43266 | R13: 43419 | S13: 19369.65 | U13: 99000 | W13: 2.0580253e+08 | X13: 1051875000 | Y13: 4.6464443 | Z13: CMT | AA13: 정장팀 | AB13: 베트남 | AC13: 블루컴퍼니 | AD13: 49%WOOL 49%POLYESTER 2%POLYURETHANE | AE13: 우븐 | AF13: 2/90*1/50PU 280G/M 49%WOOL 49%POLYESTER 2%POLYURETHANE 57" | AG13: SINO(AOYANG) | AH13: 중국 | AI13: 43259 | AJ13: 43259 | AK13: 43358
C16: 팬츠팀 | S16: 오더 진행 | V16: 생산원가 | AC16: 부자재 | AE16: 원단/부자재 현황
E17: BRAND | F17: 품번 | G17: 차수 | H17: 복종 | I17: 파일번호 | J17: 담당 디자이너 | K17: DESCRIPTION | L17: W/S | M17: ORDER QTY | N17: COL QTY | O17: COL | P17: 작지 접수 | Q17: 가먼트 납기(INDC) | R17: Ex Fac | S17: 생산형태 | T17: 생산처 | U17: FAC. | V17: 사사전원가 | W17: 사전원가 | X17: 예판가 | Y17: 확정 판매가 | Z17: 사전원가 합 | AA17: 생산 원가 합 | AB17: MU | AC17: ACC 발주일 | AD17: ACC 선적일 | AE17: 원단납기 | AF17: 원단 요청 납기 | AG17: 원단업체 | AH17: 원단SPEC | AI17: 원단가 | AJ17: BT | AK17: MAIN FABRIC CFM | AL17: 원단 REPROT | AM17: ETD FAB | AN17: QC | AO17: FPP | AP17: APPROVED FPP 발송 일 | AQ17: 재단 시작일 | AR17: 봉제 투입일 | AS17: 봉제 완료일 | AT17: INLINE & GARMENT TEST | AU17: SHIPPING SAMPLE | AV17: ETD | AW17: ETA | AX17: INDC | AY17: 비고
E18: TOPTEN | F18: MSZ1PP2002 | G18: A | H18: 1PP | J18: 김정은 | K18: W)CTN SEMI WIDE CASUAL | M18: 2300 | O18: BE | P18: 43278 | Q18: 43467 | S18: 완사입 | T18: 베트남 | U18: 나인 | V18: 10000 | X18: 39900 | Z18: 23000000 | AB18: 3.6272727 | AE18: 43308 | AF18: 43363 | AG18: 나인 | AH18: 나인)VJSS-16798 7*7 68*68 57/58" 373GSM | AM18: 0 | AN18: 7/27 OK | AO18: 0
C20: 니트팀 | E20: ORDER ISSUE | M20: 스타일 정보 | AC20: DETAIL DESCRIPTION | AI20: ARTWORK | AK20: 발주 | AM20: QC | AR20: 생산진행 | BC20: 원가정보 | BJ20: CMPH | BO20: BT CFM | BP20: EMB | BQ20: PRINT | BR20: F/SO
M21: 63 | P21: 224 | Q21: 800300 | AW21: 날짜값만입력 | BC21: 21100 | BD21: 0 | BE21: 83600 | BF21: 0 | BG21: 1227500000 | BH21: 4327500000 | BI21: 3.204962
E22: NO | F22: 디자이너 | G22: 담당자 | H22: 작지수령 | I22: 작지확정 | J22: 시즌 | K22: 브랜드 | L22: ORDER구분 | M22: SKETCH | N22: ST NO | O22: FILE NO. | P22: COL | Q22: Q'TY | R22: 최종납기 | S22: 납기변경내역 | T22: 1ST IN | U22: 1ST Q'TY | V22: 2ST IN | W22: 2ST Q'TY | X22: 3ST IN | Y22: 3ST Q'TY | Z22: 생산국 | AA22: 생산처 | AB22: REMARK | AC22: F.담당 | AD22: F.MILL | AE22: FBR DESC. | AF22: 제품 혼용율 | AG22: GARMENT DESC | AH22: HS CODE | AI22: 나염 | AJ22: 자수 | AK22: 원단발주 | AL22: 부자재발주 | AM22: QC1 | AN22: QC2 | AO22: QC3 | AP22: QC CFM | AQ22: REMARK | AR22: FPP발송 | AS22: FPP접수 | AT22: FPP CFM | AU22: REMARK | AV22: 요척합의 | AW22: FAB ETD | AX22: 원단세부 | AY22: 투입 | AZ22: 종결 | BA22: REMARK | BB22: TOP | BC22: 사사전원가 | BD22: 사전원가 | BE22: 예판가 | BF22: 결판가 | BG22: 원가합 | BH22: 판가합 | BI22: 배수 | BJ22: CM(P) | BK22: H | BL22: P | BM22: PH2 | BN22: FOB
E23: 1 | F23: 홍나영 | G23: 조하나 | H23: 43278 | I23: 43278 | J23: 사계절(SS) | K23: TT | L23: 메인 | M23: 1 | N23: MSZ5TS3901A | O23: TO19TT6007 | P23: 8 | Q23: 30000 | R23: 43480 | S23: 0 | T23: 0 | U23: 0 | V23: 0 | W23: 0 | X23: 0 | Y23: 0 | Z23: 미얀마 | AA23: MYM | AB23: 임가공 | AC23: 김용옥 | AD23: 국내임가공 | AE23: CM26'S/1 SINGLE JERSEY WITH COMPACT + ENZYME (175G) | AF23: C100 | AG23: MEN'S T-SHIRTS | AH23: 6109.10.1000 | AI23: X | AJ23: X | AK23: 43278 | AL23: 43298 | AM23: 43298 | AN23: 0 | AO23: 0 | AP23: 43298 | AQ23: 0 | AR23: 0 | AS23: 0 | AT23: 0 | AU23: 0 | AV23: 0 | AW23: 43359 | AX23: SOL 9/16 30% (8040), 9/23 30% (8040), 9/30 40% (13920) MEL 10/7 100% (3200) | AY23: 43427 | AZ23: 43452 | BA23: 37~38 | BB23: 0 | BC23: 3307 | BD23: 0 | BE23: 15900 | BF23: 0 | BG23: 99210000 | BH23: 477000000 | BI23: 4.3708937 | BJ23: 0.48 | BK23: 0.06 | BL23: 0.09 | BM23: 0.01 | BN23: 0
C30: 스웨터팀 | E30: 순번 | F30: 시즌 | G30: 브랜드 | H30: STYLE# | I30: 차수 | J30: PCS | K30: 업체 | L30: 실입고수량 | M30: QUALITY | N30: LAST BT | O30: BT | P30: 원사발주 | Q30: YARN ETA | R30: 1ST QC | S30: 2ND QC | T30: 3RD QC | U30: APP | V30: LINE | W30: FPP | X30: TOP | Y30: INSPECTION | Z30: ETD | AA30: ETA | AB30: IN-DC | AC30: 2nd DELI | AD30: 협의 납기 | AE30: STATUS | AF30: 최초기획납기 | AG30: 거래형태 | AH30: 생산국 | AI30: 혼용율 | AJ30: 실제혼용율 | AK30: 번수 | AL30: GG | AM30: PLY | AN30: 중량 | AO30: ASSORT | AP30: 예상원가 | AQ30: 예상판가 | AR30: FOB PRICE | AS30: ETD+45 | AT30: AMOUNT | AU30: FACTORY | AV30: DETAIL YARN SPEC | AW30: 입고율 | AX30: 기획원가 합 | AY30: 기획판가 합
E31: 1 | F31: SP | G31: OLZEN | H31: ZOZ1ER1101 | I31: A | J31: 1800 | K31: SANTEX | M31: 43271 | N31: 43283 | O31: 43304 | P31: 43307 | Q31: 43315 | U31: 43300 | V31: 43330 | W31: 43337 | X31: 43427 | Z31: 43434 | AA31: 43439 | AB31: 43441 | AE31: ZOZER002 | AF31: 43446 | AG31: 직LC | AH31: 중국 | AI31: W=100 (COMPACT) | AK31: 30'S/2 | AL31: 12 | AM31: 1 | AN31: 309 | AP31: 19000 | AQ31: 128000 | AT31: 0 | AV31: 30'S/2 12GG 1PLY | AW31: 0 | AX31: 34200000 | AY31: 230400000
AK34: 이 항목들이 TRIM 관련 정보인지 여부 | CV34: 이해불가 | DS34: 이해불가
K35: 작업지시서 워크시트 수령일 | L35: 작업지시서 확정일 | M35: 공장출하일 | N35: 납기일 | Q35: 수량 | R35: 수량 | S35: 수량 | T35: 수량 | U35: 수량 | V35: 수량 | W35: 수량 | X35: 수량 | Y35: 수량 | Z35: 원산지 | AA35: 생산형태 | AB35: 봉제공장 | AD35: 원산지증명 | AF35: 요척 | AG35: YDS당 단가 | AH35: PCS당 원자재 원가 | AI35: 원단 사용 차수 | AK35: 안감 | AL35: 봉사 | AM35: 단추 | AN35: 라벨 | AO35: 기타부자재 | AP35: 팩킹자재 | AQ35: PCS당 부자재 원가 | AV35: 팩킹 핸들링 차지 | AW35: PCS당 CMP 원가 | BC35: 에이션 마진율 | BM35: MD 확정 가격 | BN35: MD 확정 Amt | BO35: MD M/up | BP35: 원단제조업체 | BQ35: 발주일 | BR35: 원단납기일 | BU35: 자재선적 수단 | BV35: 부자재 ETD | BW35: 부자재 ETA | BX35: 생산일정 | BY35: 시직,BT 검사납기 | BZ35: 시직,BT 디자인 1차제출일 | CA35: 1차 컨펌 | CB35: 시직,BT 디자인 2차 제출일 | CC35: 2차 컨펌 | CD35: 시직,BT 디자인 3차 제출일 | CE35: 3차 컨펌 | CF35: 시직,BT 디자인 4차 제출일 | CG35: 4차 컨펌 | CH35: 원단 1차생산분 제출일 | CI35: 원단 1차 컨펌 | CJ35: 원단 2차생산분 제출일 | CK35: 원단 2차 컨펌 | CL35: 원단 3차생산분 제출일 | CM35: 원단 3차 컨펌 | CN35: 샘플야대지 수령일 | CO35: 샘플야대지 디자이너 승인일 | CV35: 승인 원부자재 송부일 | CW35: 원단선적예상일 | CY35: 원단 1차선적예상일 | DG35: 원단 선적수량 | DJ35: 공장요척 | DL35: 요척합의서(공장에서 소싱팀) | DM35: 재단수량 | DR35: 선적샘플 수령일 | ED35: 사전원가 등록일 | EE35: 물류납기 1차 | EF35: 물류납기 2차 | EG35: 물류납기 3차 | EH35: 물류납기 4차 | EI35: 물류입고 총수량 | EL35: 부족수량 비율
C36: 셔츠팀 | E36: No | F36: SLV | G36: FAB PTTN | H36: St. | I36: STYLE NO | K36: W/S RCVD | L36: W/S FIXED DATE | M36: EX-FTY DUE | N36: IN DC DUE DATE | O36: COL | P36: PATTERN / COL | T36: ASSORT | Y36: Q'TY | Z36: GMT ORIGIN | AA36: TYPE OF PRODUCE | AB36: GMT FACTORY (MFG) | AC36: HS CODE | AD36: C/O (PAPER) | AE36: FABRIC DESCRIPTION | AF36: Shell Y.Y | AG36: FABRIC U/P | AH36: FABRIC TOTAL AMT | AI36: CONTRAST (1) | AJ36: CONTRAST (2) | AK36: INTER LINING | AL36: THREAD | AM36: BTTN | AN36: LABEL TAG | AO36: OTHERS | AP36: PACK | AQ36: TRIM TOTAL AMT | AR36: C.M | AS36: G/Wash | AT36: EMB | AU36: Print / Others | AV36: PH (1+2) | AW36: CMP TOTAL AMT | AX36: FOB PRICE | AY36: FOB for EX INFO | AZ36: FREIGHT | BA36: IMPORT TARIFF 5% | BB36: AIR CHARGE | BC36: FOR A.tion (9.44%) | BD36: DDP PRICE | BE36: DDP PRICE (KOR) | BF36: DDP PRICE (E) | BG36: DDP AMOUNT | BH36: RETAIL PRICE (E) | BI36: RETAIL PRICE | BJ36: RETAIL AMOUNT | BK36: M/U (-V) | BL36: M/U (+V) | BM36: MD CFMD PRICE | BN36: MD CFMD AMT | BO36: MD M/U (+V) | BP36: FABRIC ORIGIN /MILL | BQ36: FABRIC ORDERED DATE | BR36: DELIVERY DATE by Fabric team | BS36: FABRIC ETD | BT36: FABRIC ETA | BU36: FABRIC SHIP MODE | BV36: TRIM ETD | BW36: TRIM ETA | BX36: PERIOD of Production | BY36: H/L OR B/T DUE DATE | BZ36: H/L OR B/T SUBMIT | CA36: 1ST CFM | CB36: H/L OR B/T SUBMIT 2ND | CC36: 2ND CFM | CD36: 3RD | CE36: 3RD CFM | CF36: 4TH | CG36: 4TH CFM | CH36: LOT SUBMIT 1ST | CI36: 1ST CFM | CJ36: LOT SUBMIT 2ND | CK36: 2ND CFM | CL36: LOT SUBMIT 3RD | CM36: 3RD CFM | CN36: S/Y RCVD | CO36: QC APPROVAL DUE DATE | CP36: S/D 1st Q.C | CQ36: 1st Q.C RCVD | CR36: S/D 2nd QC | CS36: 2nd QC RCVD | CT36: S/D 3rd QC | CU36: 3rd QC RCVD | CV36: APPROVAL FINAL PACKAGE SENDING DATE | CW36: FABRIC ETD DUE DATE | CX36: FABRIC ORDER Q'TY | CY36: ETD FABRIC 1ST | CZ36: ETA FABRIC 1ST | DA36: ETD FABRIC 2ND | DB36: ETA FABRIC 2ND | DC36: ETD FABRIC 3RD | DD36: ETA FABRIC 3RD | DE36: ETD FABRIC 4TH | DF36: ETA FABRIC 4TH | DG36: FABRIC SHIPPED TOTAL | DH36: FABRIC BALANCE | DI36: BALANCE RATING | DJ36: FACTORY Y.Y | DK36: BALANCE | DL36: Y.Y AGREEMENT COMMENT | DM36: CUT Q'TY | DN36: CUT BALANCE | DO36: CUT RATING | DP36: FABRIC USAGE | DQ36: FABRIC BALANCE | DR36: SHIPMENT SAMPLE RCVD | DS36: ETD RGN 1st | DT36: ETA PSN 1st | DU36: ETD RGN 2nd | DV36: ETA PSN 2nd | DW36: ETD RGN 3rd | DX36: ETA PSN 3rd | DY36: ETD RGN 4th | DZ36: ETA PSN 4th | EA36: SHPD SUM | EB36: SHIP BAL (CUT) | EC36: SHPD RATING | ED36: ESP-Pre COSTING input date | EE36: INDC 1st | EF36: INDC 2nd | EG36: INDC 3rd | EH36: INDC 4th | EI36: INDC TOTAL | EJ36: INDC BALANCE | EK36: INDC AMOUNT | EL36: RATE SHORTAGE OVERAGE | EM36: SHORTAGE COMMENT
E37: 1 | F37: L | G37: SOLID | H37: BLZ1WD1001A | I37: BLZ1WD1001 | J37: A | K37: 43277 | L37: 43286 | M37: 43465 | N37: 43470 | O37: 3 | R37: <90> | S37: <95> | T37: <100> | U37: <105> | V37: <110> | X37: sub | Y37: 8500 | Z37: 미얀마 | AA37: 임가공 | AB37: SSTS#3 | AC37: 6205.20.0000 | AD37: GSP CO | AE37: COTTON 61 POLYESTER 34 POLYURETHANE 5 | AF37: 1.6423529 | AG37: 2.2566372 | AH37: 3.7061947 | AK37: 0.35 | AL37: 0.066371681 | AM37: 0.13274336 | AN37: 0.23893805 | AO37: 0.022123894 | AP37: 0.145 | AQ37: 0.95517699 | AR37: 1.87 | AV37: 0.18 | AW37: 2.05 | AX37: 6.7113717 | AY37: 6.9613717 | AZ37: 0.16778429 | BB37: 0 | BD37: 6.879156 | BE37: 7773.4462 | BF37: 7888 | BG37: 66074293 | BH37: 74000 | BI37: 74000 | BJ37: 629000000 | BK37: 9.5195873 | BL37: 8.6541702 | BM37: 7902 | BN37: 67167000 | BO37: 8.5133798 | BP37: KOREA | BQ37: 43263 | BR37: 43419 | BS37: 43419 | BT37: 43429 | BU37: AIR | BV37: 43290 | BW37: 43320 | BX37: 26 | BY37: 43330 | BZ37: 43278 | CA37: 0 | CB37: 43286 | CC37: 0 | CD37: 43290 | CE37: 43293 | CF37: 0 | CG37: 0 | CH37: 43299 | CI37: 43307 | CJ37: 0 | CK37: 0 | CL37: 0 | CM37: 0 | CN37: 43299 | CO37: 43415 | CP37: 43290 | CQ37: 43300 | CR37: 0 | CS37: 0 | CT37: 0 | CU37: 0 | CV37: 43307 | CW37: 43390 | CX37: 13960 | CY37: 43313 | CZ37: 43314 | DG37: 14047.5 | DH37: 87.5 | DI37: 0.0062679083 | DJ37: 43322 | DM37: 0 | DO37: 0.98094118 | DP37: 0 | DS37: 0 | DT37: 0 | DU37: 0 | DV37: 0 | DW37: 0 | DX37: 0 | DY37: 0 | DZ37: 0 | EA37: 0 | EC37: 0 | ED37: 0 | EE37: 0 | EF37: 0 | EG37: 0 | EH37: 0 | EI37: 0 | EJ37: -8500 | EK37: 0
H38: SEMI WIDE | I38: TY19AZ0001 | L38: 아소트전달 | O38: BK | P38: SOLID | T38: 800 | X38: 800 | AE38: CM40*P100D/PU40 148*84 50" TWILL | AF38: 1.65 | AG38: 2.2566372 | AH38: 3.7234513 | AK38: 395.5 | AL38: 75 | AM38: 150 | AN38: 270 | AO38: 25 | AP38: 163.85 | AQ38: 1079.35 | AR38: 2113.1 | AV38: 203.4 | AX38: 7583.85 | BB38: 0 | BH38: 8.6541702 | BP38: 은성 | BV38: 단추 7/9,7/16 | BZ38: 43278 | CA38: 6/29재 | CB38: 43286 | CC38: 43286 | CH38: 43305 | CI38: 43307 | CN38: 43304 | CX38: 1320 | CY38: 1360.25 | DG38: 1360.25 | DH38: 40.25 | DI38: 0.030492424 | DK38: 0 | DL38: W50.5" | DM38: 818 | DN38: 18 | DO38: 0.0225 | DP38: 1349.7 | DQ38: -10.55 | EA38: 0 | EB38: -818 | EC38: -1 | EI38: 0 | EJ38: -800
O39: BL | P39: SOLID | T39: 1200 | X39: 1200 | AF39: 1.65 | AG39: 2.2566372 | AH39: 3.7234513 | BZ39: 43278 | CA39: 6/29재 | CB39: 43286 | CC39: 7/5재 | CD39: 43290 | CE39: 43293 | CH39: 43306 | CI39: 43307 | CN39: 43304 | CX39: 1980 | CY39: 2026.75 | DG39: 2026.75 | DH39: 46.75 | DI39: 0.023611111 | DK39: 0 | DL39: W50.5" | DM39: 1214 | DN39: 14 | DO39: 0.011666667 | DP39: 2003.1 | DQ39: -23.65 | EA39: 0 | EB39: -1214 | EC39: -1 | EI39: 0 | EJ39: -1200
O40: WT | P40: SOLID | T40: 6500 | X40: 6500 | AF40: 1.64 | AG40: 2.2566372 | AH40: 3.700885 | BZ40: 43278 | CA40: 43280 | CH40: 43299 | CI40: 43301 | CN40: 43299 | CX40: 10660 | CZ40: 10660.5 | DG40: 10660.5 | DH40: 0.5 | DI40: 4.6904315e-05 | DK40: -0.03 | DL40: W49.75" | DM40: 6306 | DN40: -194 | DO40: -0.029846154 | DP40: 10531.02 | DQ40: -129.48 | EA40: 0 | EB40: -6306 | EC40: -1 | EI40: 0 | EJ40: -6500

Sheet 소싱관리팀집계양식
C5: 구분키 | D5: 부서 | E5: 스타일번호 | F5: 기획수량 | G5: 제조원가 | H5: 판매가 | I5: 생산형태 | J5: 생산국 | K5: 생산처 | L5: 납기 | M5: 원단CFM | N5: APP | O5: FPP | P5: CUTTING | Q5: ETD | R5: 입고 | S5: SEASON

Sheet 관리현황집계
L3: 아우터팀 | M3: 정장팀 | N3: 셔츠팀 | O3: 팬츠팀 | P3: 니트팀 | Q3: 스웨터팀
F4: 스타일정보 | G4: Style no.
G5: File no.
G6: 스케치 (Image)
G7: 생산차수
G8: 시즌
G9: 브랜드
G10: 브랜드라인
G11: 복종(ITEM)
G12: COLOR
H13: 칼라수량 합계관리
H14: 칼러수량 개별관리
I15: SOLID
I16: STRIPE
G17: 기획수량
H18: 총수량 관리
H19: 사이즈별 수량 관리
H20: 사이즈/칼라별 수량 관리
G21: *누적입고수량
G22: 담당 디자이너
F24: 소싱정보 | G24: 소싱팀
G25: 소싱담당자
G26: 소싱형태
G27: 소싱처
G28: 소싱국가(원산지)
H29: 원산지
H30: HS CODE
H31: 대상 무역협정
G32: 소싱업체정보
H33: 결제업체
H34: 봉제공장
F36: 단가정보 | G36: PCS당
H37: Retail Price
I38: 예상
I39: 확정
H40: COGM
I41: 예상사전원가
I42: 생산사전원가
J43: 최초
J44: 최종
B45: * 이 정보 목적이 무엇인지? | H45: FOB단가 (셔츠)
I46: 예상
I47: 확정
H48: DDP단가 (셔츠)
I49: 예상
J50: 원화환산
I51: 확정
J52: 원화환산
B53: * 이 정보 목적이 무엇인지? 예상원가로 MD 협의하는 것 아닌지 | H53: MD확정원가
G54: Amount
H55: Retail Price
H56: COGM
G57: Production M/up (-V)
F59: 자재정보 | G59: Material
H60: 원자재
I61: 자재구분 (우븐/니트)
I62: 혼용율
I63: (표준)원단명 (DESCRIPTION)
I64: 거래처
J65: 업체명
J66: 업체국가
I67: 요척정보
J68: 요척
K69: 개발요척
K70: 공장요척
J71: 요척합의
I72: * 단가 (셔츠)
J73: YDS당
J74: PCS당
I75: * CONTRAST (셔츠)
J76: (1)
J77: (2)
H78: ART WORK (니트)
I79: 나염
I80: 자수
H81: 부자재
I82: 자재구분
I83: 자재명
I84: 거래처
J85: 업체명
J86: 업체국가
I87: * 부자재 정보 (TRIM - 셔츠)
H88: * 기타 제조원가 정보
F90: 소싱일정 | G90: 관리일정
H91: 작지수취일
H92: 작지확정일 (셔츠)
H93: 퀄러티확정 (정장/아우터)
H94: 제품납기일
G95: 자재일정
H96: 원자재
I97: 원단발주
J98: 발주서접수일
J99: 발주일
I100: 원단납기일
I101: 원단선적일
J102: 1차
K103: ETD
K104: ETA
J105: 2차
K106: ETD
...

Sheet 고려사항
E2: 마감용 Garment 입출고 수불장에 제품대체 해 넣을 수 있는 Logic 넣어야 함 (경영관리팀 향후 과제)
E4: 원단 Spread 시, Length 처리 필드 재정의 필요
D11: *** | E11: 공장요척 및 실요척 구하는 기준 문의 필요
E13: Function별 Set-up 진행계획 수립 필요
E15: 회계용 Ledger 기준 Closing 여부 매월 점검하면서 선적완료 파일에 대한 잔존 원단, 재단물, Garment 관리 Process 마련 필요
E17: 법인별 필수 Report 나 현황물 체크해야 함
E19: 근태기준 BEP 산출 Logic 필요
E21: 부자재 YOKO Material W/H 입출고 기준으로 별도 등록 및 현황 자료 필요

Sheet Cover
AP9: PMS 개발요청서
AP12: (Production Management System)
AP20: 경영기획실
AP22: 2021. 5. 31

Sheet Process
C3: ■ PMS (Production Management System) Process MAP
D6: Process | K6: Material Warehouse | AB6: Cutting | BY6: Sewing | EP6: EXIM | FA6: Garment Stock Warehouse
D8: Depot (수불거점)
D12: Menu & Process
D32: INDEX | K32: * 공통 기초자료 : 생산지표 산정기준 Function별 인원현황, 근무시간, 급여지급내역 | CO32: * 기초자료 : Line별 생산현황, 공장별 공정별 입출고현황, Defect현황 | EP32: * 기초자료 : 제품별 출고현황

Sheet Master
E3: ■ 주요 Master 체계
F5: 1. Organization of Accounting Standards (Nicaragua 예시 - ISTMO, UDN)
F37: 2. IN-OUT Depot & Transaction
I39: IN-OUT Type | P39: Class1 | W39: Class2 | AD39: Class3 | AK39: Depot / Transaction | BC39: 발생여부
I41: Transfer | P41: In-bound | W41: Material W/H | AE41: (N/A) | AL41: Material W/H | AS41: : Material Warehouse | BC41: IN-OUT
W43: Cutting | AE43: (N/A-통합재단) | AL43: C.Fabric W/H | AS43: : Cutting Fabric Warehouse | BC43: IN-OUT
AL44: Spreading & Cutting | BC44: IN-OUT
AL45: C.Bundle W/H | AS45: : Cutting Bundle Warehouse | BC45: IN-OUT
AL46: :
AE47: Factory 1 | AL47: Fac1-C.Fabric W/H | BC47: IN-OUT
AE48: (공장별 재단) | AL48: Fac1-Spreading & Cutting | BC48: IN-OUT
AL49: Fac1-C.Bundle W/H | BC49: IN-OUT
W51: Sewing | AE51: (N/A-단일공장) | AL51: S.Bundle W/H | AS51: : Sewing Bundle Warehouse | BC51: IN-OUT
AL52: Sewing Line | BC52: IN-OUT
AL53: Garment Stock W/H | AS53: : Garment Stock Warehouse | BC53: IN-OUT
AL54: :
AE55: Factory 1 | AL55: Fac1-S.Bundle W/H | BC55: IN-OUT
AL56: Fac1-Sewing Line | BC56: IN-OUT
AL57: Fac1-Garment Stock W/H | BC57: IN-OUT
P61: Out-bound | W61: Sub-contract | AE61: (N/A) | AL61: (외주봉제업체) | AS61: * 업체별 개별등록
AE65: Print | AL65: (부속가공업체) | AS65: * 업체별 개별등록
W66: Sub-processing | AE66: EMB | AL66: (부속가공업체) | AS66: * 업체별 개별등록
AE67: Washing | AL67: (부속가공업체) | AS67: * 업체별 개별등록
I70: Managing | P70: (N/A) | AL70: Net-IN | AS70: * Material W/H 입고 전용 Transaction | BC70: IN
AL72: Sales | AS72: * 자재 및 제품 판매 | BC72: OUT
AL73: Trans SPEC | AS73: * 자재 SPEC (File/Style 변경) 변경 | BC73: IN-OUT
AL74: Trans Location | AS74: * 자재 Location 변경 | BC74: -
AL75: Sample | AS75: * 샘플사용 | BC75: IN-OUT
AL76: Split | AS76: * 하나의 Roll 원단을 2개 이상의 Roll 로 분할 | BC76: IN-OUT
AL77: Disposal | AS77: * 폐기 | BC77: OUT
AL78: Loss | AS78: * 분실/도난 등 | BC78: OUT
AL79: Adjusted | AS79: * 기타 재고조정 | BC79: IN-OUT
F82: 3. 생산관리 INDEX 기초Data 집계용 Function Master
G84: : HR 자료와 생산실적 Data 연계 집계 필요
I86: Class1 | P86: Class2 | W86: Function | AE86: Remark
I88: Sewing Factory | P88: Sewing Line | X88: Line Manager | AE88: * Sewing Line | BF88: 인원, 근무시간, 인건비
I89: (봉제공장) | P89: (생산라인) | X89: Technician | AE89: : 순수 Line / 법인내 공장별 생산성 측정을 위한 기준
X90: Odd-job
P92: Prod. Support | X92: Material W/H | AE92: * Production Support
P93: (생산지원) | X93: Cutting | AE93: - 법인별 공장운영 특성에 따라 통합체계 상이함 원인, 공장별 생산성 측정 Data 로 부적합
X94: Finishing | AE94: Prod. Support 기초Data 는 각 법인 전체를 기준으로 생산성지표 관리해야 함
X95: Mechanic | AE95: Ex. 통합재단, 통합완성반, 통합공무 등
X96: QA/QC | AE96: - 특정 법인 생산지원 조직의 경우, Main Office 소속 불구, 본사 생산관리Data 는 생산지원 별도 분류&집계
X97: Factory Office
X98: Sample
I100: Main Office | P100: (N/A) | X100: Personnel / General Affair | AE100: * Main Office 내 구성Function 외 추가 Function 필요시, 마스터 추가 등록 진행
I101: (법인공통) | P101: (N/A) | X101: Accounting
P102: (N/A) | X102: EXIM
I104: 영업지사 | X104: (회계기준 예산부서로 구분)

Sheet 1.M.WH
E2: Ⅰ. MATERIAL WAREHOUSE
F4: ※ System Menu 구성
G6: ◆ Material Warehouse | O6: □ | P6: Material W/H IN - Plan Reg. (Fabric) | AA6: : 자재창고 입고계획 등록
O7: □ | P7: Material W/H IN - Reg. (Fabric) | AA7: : 자재창고 입고 등록 (바코드 및 수기등록)
O8: □ | P8: Material W/H - Trans Location Reg. | AA8: : 자재창고 Location 변경 등록
O9: □ | P9: Material W/H - Trans SPEC Reg. | AA9: : 자재창고 자재 SPEC 변경 등록 (File/Style Info.)
O10: □ | P10: Material W/H - Split Reg. | AA10: : 자재창고 Roll 분리 등록 (1 Roll → XX Roll)
O11: □ | P11: Material W/H OUT - Reg. (Fabric) | AA11: : 자재창고 출고 등록
O12: □ | P12: Fabric Inspection - Reg. | AA12: : 원단 품질검사 등록 (Next Step)
O14: (R) | P14: Material W/H IN-OUT Ledger | AA14: : 월별 자재창고 입출고 현황 (for Accounting)
O15: (R) | P15: Material W/H IN-OUT Status | AA15: : 기간별 자재창고 입출고 현황 (Lot 단위)
O16: (R) | P16: Material W/H Stock Status (by Present) | AA16: : 현재기준 자재창고 재고 현황 (재고수량 및 Location)
O17: (R) | P17: Fabric Inspection Status | AA17: : 원단 품질검사 현황 (Next Step)
O19: ※ 주의사항 : 출고후, 일일 업무마감 전 출고내역 Target Depot 측 입고처리 완료여부 확인 必
F22: 1-1. Material W/H IN - Plan Reg. (Fabric)
G24: : IN-OUT Depot & Transaction - Managing 중, Net-IN (Material W/H IN 전용 Transaction) 입고등록 전, 사전 필수등록 사항
I27: M. W/H IN - Plan Reg | P27: Status
I29: Shipping Status Search | O29: (팝업창)
I31: - Container info.
I32: From | N32: Supplier | S32: TRANSPORT | W32: Container no. | AB32: Con. Size | AE32: ETD | AI32: ETA
I33: KOREA | N33: XXXXXXXXXX | S33: VESSEL | W33: XXXXXXXXXX | AB33: XXX | AE33: YYYY-MM-DD | AI33: YYYY-MM-DD
I35: - Item infomation by Container
I37: ■ | J37: Order | U37: Item | AM37: Status
J38: File no. | N38: Style no. | R38: Part | U38: CODE | X38: Name | AC38: Description | AJ38: Color | AM38: UNIT | AO38: Length | AR38: Weight | AU38: ▤
I39: V | J39: TN19GB8044 | N39: 12345 | R39: BODY | U39: XXXXXXXX | X39: XXXXXXXX | AC39: XXXXXXXXXXXXXXXXX | AJ39: BLK | AM39: YDS | AO39: 200 | AR39: 200
I40: □ | J40: TN19GB8044 | N40: 12345 | R40: BODY | U40: XXXXXXXX | X40: XXXXXXXX | AC40: XXXXXXXXXXXXXXXXX | AJ40: BLK | AM40: KGS | AO40: 100 | AR40: 200
I41: □ | J41: TN19GB8044 | N41: 12345 | R41: BODY | U41: XXXXXXXX | X41: XXXXXXXX | AC41: XXXXXXXXXXXXXXXXX | AJ41: BLK | AM41: LBS | AO41: 100 | AR41: 200
I44: [ Material W/H IN - Plan Reg. (Barcode Creation) ] | AF44: Save & Barcode create | AL44: Delete
I46: (+)Add | L46: (+) COPY & ADD | P46: (-)Del | S46: □ | T46: Select all | AG46: Plan no. | AJ46: XXXXXXXXXX
I48: ■ | J48: Bulk Reg. | Y48: Gross Qty | AH48: Barcode
J49: Lot no. | M49: Roll no. | P49: UNIT | S49: Qty | V49: Width | Y49: UNIT | AB49: Length | AE49: Weight | AN49: ▤
I50: □ | J50: XXX1 | M50: 1 | P50: Roll | R50: ▼ | S50: 1 | V50: 66 | Y50: YDS | AA50: ▼ | AB50: 60 | AE50: - | AH50: XXXXXXXXXXXXXXXXX
I51: □ | J51: XXX2 | M51: 2 | P51: Roll | R51: ▼ | S51: 1 | V51: 66 | Y51: YDS | AA51: ▼ | AB51: 40 | AE51: - | AH51: XXXXXXXXXXXXXXXXX
I52: □ | J52: XXX3 | M52: 3 | P52: Roll | R52: ▼ | S52: 1 | V52: 66 | Y52: YDS | AA52: ▼ | AB52: 100 | AE52: - | AH52: XXXXXXXXXXXXXXXXX
Q55: Total | S55: =S52+S51+S50 -> 3 | AB55: =AB52+AB51+AB50 -> 200 | AE55: -
J57: * 상단 W/H IN Plan Reg. (Barcode Creation) 의 Status 수치와 상기 등록된 Gross Qty 수량 상이할 시, 저장 불가
J60: Shipping Status Search
K62: Destination | O62: NICARAGUA | S62: ▼ | T62: From | W62: - | AA62: ▼ | AM62: Query | AP62: Apply | AT62: ← 이미 Plan 등록 완료된 Container 는 'Apply' 버튼 클릭해도 적용되면 안됨
K64: Transport | O64: VESSEL | S64: ▼ | T64: ETA | W64: YYYY-MM-DD | AA64: ▤ | AB64: ~ | AC64: YYYY-MM-DD | AG64: ▤
K66: Container no. | O66: XXXXXXXXXX | T66: B/L no. | W66: XXXXXXXXXX | AB66: File no. | AE66: XXXXXXXXXX
K68: □ | L68: Includes data already processed
K70: - Container info.
K71: ■ | L71: Plan | N71: From | S71: Supplier | X71: TRANSPORT | AB71: Container no. | AG71: Con. Size | AJ71: ETD | AN71: ETA
K72: V | L72: N | N72: KOREA | S72: XXXXXXXXXX | X72: VESSEL | AB72: XXXXXXXXXX | AG72: XXX | AJ72: YYYY-MM-DD | AN72: YYYY-MM-DD | AR72: ▤
K73: □ | L73: N | N73: KOREA | S73: XXXXXXXXXX | X73: VESSEL | AB73: XXXXXXXXXX | AG73: XXX | AJ73: YYYY-MM-DD | AN73: YYYY-MM-DD
K74: □ | L74: N | N74: HONDURAS | S74: XXXXXXXXXX | X74: TRUCKING | AB74: XXXXXXXXXX | AG74: XXX | AJ74: YYYY-MM-DD | AN74: YYYY-MM-DD
I79: M. W/H IN - Plan Reg | O79: Status
I81: Reg Date | M81: ▼ | O81: YYYY-MM-DD | S81: ▤ | T81: ~ | U81: YYYY-MM-DD | Y81: ▤ | Z81: ← Drop down 메뉴의 기한조회 기준은 Reg Date, ETA | CA81: Query | CD81: B. Print
I83: From | K83: - | O83: ▼ | P83: Container no. | T83: XXXXXXXXXX | Y83: B/L no. | AB83: XXXXXXXXXX | AG83: File no. | AJ83: XXXXXXXXXX | AO83: + | AP83: Style no. | AS83: XXXXXXXXXX | AX83: Plan no. | BA83: XXXXXXXXXX
I85: ■ | J85: Plan no. | N85: ETA | R85: Order | AC85: Item | AU85: Status | BC85: Bulk Info. | BR85: Gross Qty | BZ85: Barcode
R86: File no. | V86: Style no. | Z86: Part | AC86: CODE | AF86: Name | AK86: Description | AR86: Color | AU86: UNIT | AW86: Length | AZ86: Weight | BC86: Lot no | BF86: Roll no | BI86: UNIT | BL86: Qty | BO86: Width | BR86: UNIT | BT86: Length | BW86: Weight | CF86: ▤
I87: □ | J87: XXXXXXXXXX | N87: YYYY-MM-DD | R87: TN19GB8044 | V87: 12345 | Z87: BODY | AC87: XXXXXXXX | AF87: XXXXXXXX | AK87: XXXXXXXXXXXXXXXXX | AR87: BLK | AU87: YDS | AW87: 100 | AZ87: 200 | BC87: XXX1 | BF87: 1 | BI87: Roll | BL87: 1 | BO87: 66 | BR87: YDS | BT87: 60 | BW87: - | BZ87: XXXXXXXXXXXXXXXXX
I88: □ | J88: XXXXXXXXXX | N88: YYYY-MM-DD | R88: TN19GB8044 | V88: 12345 | Z88: BODY | AC88: XXXXXXXX | AF88: XXXXXXXX | AK88: XXXXXXXXXXXXXXXXX | AR88: BLK | AU88: YDS | AW88: 100 | AZ88: 200 | BC88: XXX2 | BF88: 2 | BI88: Roll | BL88: 1 | BO88: 66 | BR88: YDS | BT88: 40 | BW88: - | BZ88: XXXXXXXXXXXXXXXXX
I89: □ | J89: XXXXXXXXXX | N89: YYYY-MM-DD | R89: TN19GB8044 | V89: 12345 | Z89: BODY | AC89: XXXXXXXX | AF89: XXXXXXXX | AK89: XXXXXXXXXXXXXXXXX | AR89: BLK | AU89: YDS | AW89: 100 | AZ89: 200 | BC89: XXX3 | BF89: 3 | BI89: Roll | BL89: 1 | BO89: 66 | BR89: YDS | BT89: 100 | BW89: - | BZ89: XXXXXXXXXXXXXXXXX
BJ92: Total | BL92: =BL89+BL88+BL87 -> 3 | BT92: =BT89+BT88+BT87 -> 200 | BW92: -
I95: * Plan no. 더블클릭시, M. W/H IN - Plan Reg. 화면으로 이동
H96: : Container 및 기타 등록정보에 대한 필드 필요시, 임의 해당 필드추가 OK
F99: 1-2. Material W/H IN - Reg. (Fabric)
H101: ※ Depot & Transaction
J104: IN-OUT TYPE
J106: ■ Transfer | O106: : | Q106: 이론상 IN-OUT Depot Master 에 등록된 모든 Depot 를 Source 로 한, 입고처리 가능 (단, Depot별 관리SPEC 필드 동일 전제)
K107: (거점이동 입고)
J108: ■ Managing | O108: : | Q108: 이론상 IN-OUT Transaction Master 등록된 모든 TR 에 대한, 입고처리 가능 (단, Depot별 관리SPEC 필드 동일 전제)
K109: (회계/관리목적 입출고처리) | Q109: 단, 'Net-IN' 은 해외 혹은 Local 에서 최초 자재입고에 대한 입고처리 등록이므로 Material W/H IN 에서만 나타나는 TR 형태임
Q110: * Managing 은 대부분 회계적인 Transaction 혹은 관리적 목적에 기반해 발생하는 처리 유형
I115: M. W/H IN - Reg | O115: M. W/H IN - Reg. (Manual) | W115: Status
I117: W/H IN Date | N117: YYYY-MM-DD | R117: ▤ | S117: □ | T117: Date Modify | X117: □ | Y117: Excl. already processed 'IN' | AW117: Query | AZ117: Save | BC117: Delete
I119: Depot | N119: Material W/H | R119: + | T119: Source Depot | Y119: Net-IN | AC119: + | AD119: ← Net-IN 외 Master 'IN-OUT Depot & Transaction' 정보 참조
I121: [ Query connditions ]
I123: Plan reg Date | M123: ▼ | N123: YYYY-MM-DD | R123: ▤ | S123: ~ | T123: YYYY-MM-DD | X123: ▤ | Y123: ← 조회기간 Drop down 메뉴 기준은 Plan reg Date, ETA, Out reg date
I125: File no. | L125: XXXXXXXXXX | P125: + | Q125: Style no. | T125: XXXXXXXXXX | Z125: Plan no. (Out reg no.) | AF125: XXXXXXXXXX
I127: [ W/H IN - Request ]
I129: ■ | J129: IN Y/N | L129: Plan no. (OUT Reg no.) | P129: Plan Reg date (OUT Reg date) | T129: ETA | X129: Source Depot (Transaction) | AC129: Order | AN129: Item | BF129: Bulk Info. | BU129: Gross Qty | CC129: Barcode
AC130: File no. | AG130: Style no. | AK130: Part | AN130: CODE | AQ130: Name | AV130: Description | BC130: Color | BF130: Lot no | BI130: Roll no | BL130: Unit | BO130: Qty | BR130: Width | BU130: UNIT | BW130: Length | BZ130: Weight | CI130: ▤
I131: □ | J131: N | L131: XXXXXXXXXX | P131: YYYY-MM-DD | T131: YYYY-MM-DD | X131: Net-IN | AC131: TN19GB8044 | AG131: 12345 | AK131: BODY | AN131: XXXXXXXX | AQ131: XXXXXXXX | AV131: XXXXXXXXXXXXXXXXX | BC131: BLK | BF131: XXX1 | BI131: 1 | BL131: Roll | BO131: 1 | BR131: 66 | BU131: YDS | BW131: 60 | BZ131: - | CC131: XXXXXXXXXXXXXXXXX
I132: □ | J132: N | L132: XXXXXXXXXX | P132: YYYY-MM-DD | T132: YYYY-MM-DD | X132: Net-IN | AC132: TN19GB8044 | AG132: 12345 | AK132: BODY | AN132: XXXXXXXX | AQ132: XXXXXXXX | AV132: XXXXXXXXXXXXXXXXX | BC132: BLK | BF132: XXX2 | BI132: 2 | BL132: Roll | BO132: 1 | BR132: 66 | BU132: YDS | BW132: 40 | BZ132: - | CC132: XXXXXXXXXXXXXXXXX
I133: □ | J133: N | L133: XXXXXXXXXX | P133: YYYY-MM-DD | T133: YYYY-MM-DD | X133: Net-IN | AC133: TN19GB8044 | AG133: 12345 | AK133: BODY | AN133: XXXXXXXX | AQ133: XXXXXXXX | AV133: XXXXXXXXXXXXXXXXX | BC133: BLK | BF133: XXX3 | BI133: 3 | BL133: Roll | BO133: 1 | BR133: 66 | BU133: YDS | BW133: 100 | BZ133: - | CC133: XXXXXXXXXXXXXXXXX
BM136: Total | BO136: =BO133+BO132+BO131 -> 3 | BW136: =BW133+BW132+BW131 -> 200 | BZ136: -
I139: W/H Location | M139: (L.Zone) | P139: ▼ | Q139: P01 | T139: ▼ | U139: L01-C01 | X139: ▼ | Y139: Apply | AB139: ◎ | AC139: Selection only | AG139: ○ | AH139: All | AJ139: Barcode | AM139: XXXXXXXXXXXXXXXXX
I141: ↑ 법인별 관리수준 고려, 諸W/H Location 은 3단계 Depth 로 구성 (Location Zone - Class 1 - Class 2) | AM141: ↑ W/H IN - Request 테이블에 조회된 내용을 기준으로, 대상 바코드 스캔하여 Material W/H IN - Reg 테이블로 보낼 수 있도록 하기 위한 목적. 단, 사전 WH Location 입력 필수
I144: [ Material W/H IN - Reg. ] | P144: (-)Del Row | U144: IN Reg No. | X144: XXXXXXXXXX
I146: ■ | J146: Plan no. (OUT Reg no.) | N146: Source Depot (Transaction) | R146: Target Depot | V146: W/H Location | AH146: Order | AS146: Item | BK146: Bulk IN | BZ146: Gross Qty | CH146: Barcode
V147: Zone | Z147: Class 1 | AD147: Class 2 | AH147: File no. | AL147: Style no. | AP147: Part | AS147: CODE | AV147: Name | BA147: Description | BH147: Color | BK147: Lot no | BN147: Roll no | BQ147: Unit | BT147: Q'ty | BW147: Width | BZ147: UNIT | CB147: Length | CE147: Weight | CN147: ▤
I148: □ | J148: XXXXXXXXXX | N148: Net-IN | R148: Material W/H | V148: (L.Zone) | Z148: P01 | AD148: L01-C01 | AH148: TN19GB8044 | AL148: 12345 | AP148: BODY | AS148: XXXXXXXX | AV148: XXXXXXXX | BA148: XXXXXXXXXXXXXXXXX | BH148: BLK | BK148: XXX1 | BN148: 1 | BQ148: Roll | BT148: 1 | BW148: 66 | BZ148: YDS | CB148: 60 | CE148: - | CH148: XXXXXXXXXXXXXXXXX
I149: □ | J149: XXXXXXXXXX | N149: Net-IN | R149: Material W/H | V149: (L.Zone) | Z149: P01 | AD149: L01-C01 | AH149: TN19GB8044 | AL149: 12345 | AP149: BODY | AS149: XXXXXXXX | AV149: XXXXXXXX | BA149: XXXXXXXXXXXXXXXXX | BH149: BLK | BK149: XXX1 | BN149: 2 | BQ149: Roll | BT149: 1 | BW149: 66 | BZ149: YDS | CB149: 50 | CE149: - | CH149: XXXXXXXXXXXXXXXXX
BP152: Total : | BT152: =BT148+BT149 -> 2 | CB152: =CB149+CB148 -> 110 | CE152: -
I154: * 주의 : Scan 후, 반드시 Save 버튼으로 저장시켜야 함
I158: M. W/H IN - Reg | O158: M. W/H IN - Reg. (Manual) | W158: Status
I160: W/H IN Date | N160: YYYY-MM-DD | R160: ▤ | S160: □ | T160: Date Modify | AR160: Save | AU160: Delete | AX160: Upload | BB160: Barcode Print
I162: Depot | N162: Material W/H | R162: + | T162: Source Depot | Y162: (Sub-contract) | AC162: + | AD162: ← Managing type transaction 등록 가능 | AR162: ↑ 하기 Contents 등록후, 저장시 Barcode 자동부여 필요
I164: W/H Location | N164: (L.Zone) | Q164: ▼ | R164: P01 | U164: ▼ | V164: L01-C01 | Y164: ▼
I166: [ Material W/H IN - Reg. ]
I168: Add | K168: Copy & Add | O168: Del | AB168: IN Reg No. | AE168: XXXXXXXXXX
I170: ■ | J170: Source Depot (Transaction) | N170: Target Depot | R170: W/H Location | AD170: Order | AP170: Item | BH170: Bulk IN | BW170: Gross Qty | CE170: Barcode
R171: Zone | V171: Class 1 | Z171: Class 2 | AD171: File no. | AH171: Style no. | AM171: Part | AP171: CODE | AS171: Name | AX171: Description | BE171: Color | BH171: Lot no | BK171: Roll no | BN171: UNIT | BQ171: Q'ty | BT171: Width | BW171: UNIT | BY171: Length | CB171: Weight
I172: □ | J172: (Sub-contract) | N172: Material W/H | R172: (L.Zone) | U172: ▼ | V172: P01 | Y172: ▼ | Z172: L01-C01 | AC172: ▼ | AD172: TN19GB8044 | AH172: 12345 | AL172: + | AM172: BODY | AP172: XXXXXXXX | AS172: XXXXXXXX | AW172: + | AX172: XXXXXXXXXXXXXXXXX | BE172: BLK | BH172: XXX1 | BK172: 1 | BN172: Roll | BP172: ▼ | BQ172: 1 | BT172: 66 | BW172: YDS | BY172: 60 | CB172: - | CE172: XXXXXXXXXX
I173: □ | J173: (Sub-contract) | N173: Material W/H | R173: (L.Zone) | U173: ▼ | V173: P01 | Y173: ▼ | Z173: L01-C01 | AC173: ▼ | AD173: TN19GB8044 | AH173: 12345 | AL173: + | AM173: BODY | AP173: XXXXXXXX | AS173: XXXXXXXX | AW173: + | AX173: XXXXXXXXXXXXXXXXX | BE173: BLK | BH173: XXX1 | BK173: 1 | BN173: Roll | BP173: ▼ | BQ173: 1 | BT173: 66 | BW173: YDS | BY173: 50 | CB173: - | CE173: XXXXXXXXXX
BN176: Total : | BQ176: =BQ172+BQ173 -> 2 | BY176: =BY173+BY172 -> 110 | CB176: -
I182: M. W/H IN - Reg | O182: M. W/H IN - Reg. (Manual) | W182: Status
I184: W/H IN Date | M184: YYYY-MM-DD | Q184: ▤ | R184: ~ | S184: YYYY-MM-DD | W184: ▤ | Z184: Depot | AC184: Material W/H | AI184: ▼ | AZ184: Query | BC184: Excel | BG184: Barcode Print | BK184: ← Barcode 재출력 목적
...

Sheet 2.Cutting
E2: Ⅱ. Spreading & Cutting
F4: ※ System Menu 구성
H6: ◆ Spreading & Cutting | P6: ◆ Cutting Fabric W/H | X6: □ | Y6: C.Fabric W/H IN - Reg. | AO6: : 재단반 원단창고 입고 등록
P7: (C.Fabric W/H) | X7: □ | Y7: C.Fabric W/H - Trans Location Reg. | AO7: : 재단반 원단창고 Location 변경 등록
X8: □ | Y8: C.Fabric W/H - Trans SPEC Reg. | AO8: : 재단반 원단창고 자재 SPEC 변경 등록 (File/Style/Color/Yds Info.)
X9: □ | Y9: C.Fabric W/H - Trans Split Reg. | AO9: : 재단반 원단창고 자재 Split 등록
X10: □ | Y10: C.Fabric W/H OUT - Reg. | AO10: : 재단반 원단창고 출고 등록
X12: (R) | Y12: C.Fabric W/H - IN-OUT Ledger | AO12: : 월별 재단반 원단창고 입출고 현황 (for Accounting)
X13: (R) | Y13: C.Fabric W/H - IN-OUT Status | AO13: : 기간별/누적 재단반 원단창고 입출고 현황
X14: (R) | Y14: C.Fabric W/H - Stock Status (by Present) | AO14: : 현재기준 재단반 원단창고 재고현황 (재고수량 및 Location)
P16: ◆ Spreading & Cutting | X16: □ | Y16: Sub-processing Plan - Reg (by C. Part) | AO16: : File-Style 재단 부위별 부속가공 계획 등록
X17: □ | Y17: Size Ratio by Marker - Reg. | AO17: : Marker Spec 등록
X18: □ | Y18: Spreading & Cutting - Reg. | AO18: : 연단&재단 실적 등록 (Incl.연단실적)
X19: □ | Y19: Sewing Process - Reg. (for Process tag printing) | AO19: : 파일/스타일별 공정등록 (옵션항목)
X20: □ | Y20: Bundle PKG - Reg. | AO20: : Bundle PKG 코드생성
X21: □ | Y21: C. Bundle PKG Setting - Reg. (PKG & IN - Reg.) | AO21: : Bundle PKG 내 Bundle 구성 등록 (옵션항목 : 동시 C.Bundle W/H IN 가능)
X23: (R) | Y23: Cutting Report | AO23: : 기간별 오더대비 재단물 상세현황
P25: ◆ Cutting Bundle W/H | X25: ▶ | Y25: Cutting Bundle IN-OUT
P26: (C.Bundle W/H) | X26: □ | Y26: C.Bundle W/H IN - Reg. (from Cutting) | AK26: (Garment 기준) | AO26: : 재단물 창고 입고 등록 (from 재단반)
X27: □ | Y27: C.Bundle W/H IN - Reg. | AK27: (Garment 기준) | AO27: : 재단물 창고 입고 등록 (재단반 外)
X28: □ | Y28: C.Bundle W/H - Trans Location Reg. | AK28: (Garment 기준) | AO28: : 재단물 창고 Location 변경 등록
X29: □ | Y29: C.Bundle W/H - Trans SPEC Reg. | AK29: (Garment 기준) | AO29: : 재단물 창고 자재 SPEC 변경 등록 (File/Style/color/Qty Info.)
X30: □ | Y30: C.Bundle W/H - Trans Split Reg. | AK30: (Garment 기준) | AO30: : 재단물 창고 자재 Split 등록
X31: □ | Y31: C.Bundle W/H OUT - Reg. | AK31: (Garment 기준) | AO31: : 재단물 창고 출고 등록
X33: (R) | Y33: C.Bundle W/H - IN-OUT Ledger | AK33: (Garment 기준) | AO33: : 월별 재단물 창고 입출고 현황 (for Accounting)
X34: (R) | Y34: C.Bundle W/H - IN-OUT Status | AK34: (Garment 기준) | AO34: : 기간별/누적 재단물 창고 입출고 현황
X35: (R) | Y35: C.Bundle W/H - Stock Status (by Present) | AK35: (Garment 기준) | AO35: : 현재기준 재단물 창고 재고 현황 (수량 및 Location)
X37: ▶ | Y37: Sub-processing IN-OUT
Y38: □ | Z38: Sub-Processing OUT - Reg. | AK38: (Parts 기준) | AO38: : 재단물 부속가공 출고 등록
Y39: □ | Z39: Sub-Processing Return OUT - Reg. | AK39: (Parts 기준) | AO39: : 재단물 부속가공 재출고 등록
Y40: □ | Z40: Sub-Processing IN - Reg. | AK40: (Parts 기준) | AO40: : 재단물 부속가공 입고 등록
X42: (R) | Y42: Sub-processing IN-OUT Status | AO42: : 재단물 부속가공 입출고 현황
F45: 2-1. C.Fabric W/H (Cutting - Fabric Warehouse)
G47: 2-1-1. C.Fabric W/H IN - Reg.
J50: C.Fabric W/H IN - Reg. | Q50: Status
J52: W/H IN Date | N52: YYYY-MM-DD | R52: ▤ | S52: □ | T52: Date Modify | X52: Depot | AA52: C. Fabric W/H | AG52: + | AX52: Query | BA52: SAVE | BD52: Delete
J54: [ W/H IN - Request Search ]
J56: Req. Date | M56: YYYY-MM-DD | Q56: ▤ | R56: ~ | S56: YYYY-MM-DD | W56: ▤ | X56: □ | Y56: Excl. already processed 'IN' | AG56: Source Depot | AK56: Material W/H | AQ56: +
J58: Buyer | M58: XXXXXXXXXX | Q58: ▤ | R58: File no | U58: XXXXXXXXXX | Y58: + | Z58: Style no | AC58: XXXXXXXXXX | AG58: + | AH58: Lot no | AK58: XXXXXXXXXX | AP58: OUT Reg. no | AT58: XXXXXXXXXX | AY58: Barcode | BB58: XXXXXXXXXX
J60: ■ | K60: IN Y/N | M60: OUT Reg Date | Q60: OUT Reg. no | U60: Source Depot | Y60: Order | AJ60: Item | BB60: Bulk Info. | BQ60: Gross Qty | BY60: Barcode
Y61: File no. | AC61: Style no. | AG61: Part | AJ61: CODE | AM61: Name | AR61: Description | AY61: Color | BB61: Lot no | BE61: Roll no | BH61: Unit | BK61: Qty | BN61: Width | BQ61: UNIT | BS61: Length | BV61: Weight | CE61: ▤
J62: □ | K62: N | M62: YY-MM-DD | Q62: XXXXXXXX | U62: Material W/H | Y62: TN19GB8044 | AC62: 12345 | AG62: BODY | AJ62: XXXXXXXX | AM62: XXXXXXXX | AR62: XXXXXXXXXXXXXXXXX | AY62: BLK | BB62: XXX1 | BE62: 1 | BH62: Roll | BK62: 1 | BN62: 66 | BQ62: YDS | BS62: 15 | BV62: 0 | BY62: XXXXXXXXXXXXXXXXX
J63: □ | K63: N | M63: YY-MM-DD | Q63: XXXXXXXX | U63: Material W/H | Y63: TN19GB8044 | AC63: 12345 | AG63: BODY | AJ63: XXXXXXXX | AM63: XXXXXXXX | AR63: XXXXXXXXXXXXXXXXX | AY63: BLK | BB63: XXX1 | BE63: 2 | BH63: Roll | BK63: 1 | BN63: 66 | BQ63: YDS | BS63: 20 | BV63: 0 | BY63: XXXXXXXXXXXXXXXXX
BE66: Total : | BI66: Bulk | BK66: 2 | BP66: Gross YDS | BS66: =BS63+BS62 -> 35 | BV66: =BV63+BV62 -> 0
J69: W/H Location | N69: (L.Zone) | Q69: ▼ | R69: P01 | U69: ▼ | V69: L01-C01 | Y69: ▼ | Z69: Apply | AC69: ◎ | AD69: Selection only | AH69: ○ | AI69: All | AK69: Barcode | AN69: XXXXXXXXXXXXXXXXX
AN71: ↑ W/H IN - Request 테이블에 조회된 내용을 기준으로, 대상 바코드 스캔하여 Material W/H IN - Reg 테이블로 보낼 수 있도록 하기 위한 목적. 단, 사전 WH Location 입력 필수
J73: [ W/H IN - Reg ] | O73: (-)Del Row | T73: IN Reg. no | X73: XXXXXXXXXX
J75: ■ | K75: OUT Reg. no | O75: Source Depot | S75: W/H Location | AB75: Order | AM75: Item | BE75: Lot no | BH75: Roll no | BK75: Bulk IN | BT75: Gross Qty | CB75: Barcode
S76: Zone | V76: Class 1 | Y76: Class 2 | AB76: File no. | AF76: Style no. | AJ76: Part | AM76: CODE | AP76: Name | AU76: Description | BB76: Color | BK76: Unit | BN76: Qty | BQ76: Width | BT76: UNIT | BV76: Length | BY76: Weight
J77: □ | K77: XXXXXXXX | O77: Material W/H | S77: (L.Zone) | V77: P01 | Y77: L01-C01 | AB77: TN19GB8044 | AF77: 12345 | AJ77: BODY | AM77: XXXXXXXX | AP77: XXXXXXXX | AU77: XXXXXXXXXXXXXXXXX | BB77: BLK | BE77: XXX1 | BH77: XX | BK77: Roll | BN77: 1 | BQ77: 66 | BT77: YDS | BV77: 15 | BY77: 0 | CB77: XXXXXXXXXXXXXXXXX
J78: □ | K78: XXXXXXXX | O78: Material W/H | S78: (L.Zone) | V78: P01 | Y78: L01-C01 | AB78: TN19GB8044 | AF78: 12345 | AJ78: BODY | AM78: XXXXXXXX | AP78: XXXXXXXX | AU78: XXXXXXXXXXXXXXXXX | BB78: BLK | BE78: XXX1 | BH78: XX | BK78: Roll | BN78: 1 | BQ78: 66 | BT78: YDS | BV78: 20 | BY78: 0 | CB78: XXXXXXXXXXXXXXXXX
BI81: Total : | BL81: Bulk | BN81: =BN77+BN78 -> 2 | BS81: Gross YDS | BV81: =BV78+BV77 -> 35 | BY81: =BY78+BY77 -> 0
J87: C.Fabric W/H IN - Reg. | Q87: Status
J89: W/H IN Date | O89: YYYY-MM-DD | S89: ▤ | T89: ~ | U89: YYYY-MM-DD | Y89: ▤ | AA89: Depot | AD89: C. Fabric W/H | AJ89: ▼ | CK89: Query | CN89: Excel
J91: Source Depot / TR | O91: (Depot or Transaction) | U91: ▼ | W91: W/H Location | AA91: (L.Zone) | AD91: ▼ | AE91: P01 | AH91: ▼ | AI91: L01-C01 | AL91: ▼
J93: Buyer | O93: XXXXXXXXXX | T93: File no. | W93: XXXXXXXXXX | AB93: + | AC93: Style no. | AF93: XXXXXXXXXX | AJ93: + | AK93: Lot no. | AN93: XXXXXXXXXX | AS93: IN Reg No. | AV93: XXXXXXXXXX | BA93: OUT Reg No. | BE93: XXXXXXXXXX | BJ93: Barcode | BM93: XXXXXXXXXX
J95: ■ | K95: IN Reg. no | O95: W/H IN Date | S95: Source Depot (Transaction) | W95: Depot (Present) | AA95: W/H Location | AJ95: Order | AU95: Item | BL95: Lot no | BO95: Roll no | BR95: Bulk IN | CA95: Gross Qty | CI95: OUT Reg. no | CM95: Barcode
AA96: Zone | AD96: Class 1 | AG96: Class 2 | AJ96: File no. | AN96: Style no. | AR96: Part | AU96: CODE | AX96: Name | BC96: Description | BI96: Color | BR96: Unit | BU96: Qty | BX96: Width | CA96: UNIT | CC96: Length | CF96: Weight
J97: □ | K97: XXXXXXXX | O97: YYYY-MM-DD | S97: Material W/H | W97: C.Fabric W/H | AA97: (L.Zone) | AD97: P01 | AG97: L01-C01 | AJ97: TN19GB8044 | AN97: 12345 | AR97: BODY | AU97: XXXXXXXX | AX97: XXXXXXXX | BC97: XXXXXXXXXXXXXXX | BI97: BLK | BL97: XXX1 | BO97: XX | BR97: Roll | BU97: 1 | BX97: 66 | CA97: YDS | CC97: 15 | CF97: 0 | CI97: XXXXXXXX | CM97: XXXXXXXX
J98: □ | K98: XXXXXXXX | O98: YYYY-MM-DD | S98: Material W/H | W98: C.Fabric W/H | AA98: (L.Zone) | AD98: P01 | AG98: L01-C01 | AJ98: TN19GB8044 | AN98: 12345 | AR98: BODY | AU98: XXXXXXXX | AX98: XXXXXXXX | BC98: XXXXXXXXXXXXXXX | BI98: BLK | BL98: XXX1 | BO98: XX | BR98: Roll | BU98: 1 | BX98: 66 | CA98: YDS | CC98: 20 | CF98: 0 | CI98: XXXXXXXX | CM98: XXXXXXXX
J101: * Row 더블클릭시, C.Fabric W/H IN - Reg 화면으로 전환 (for INPUT 수정&삭제) | BP101: Total : | BS101: Bulk | BU101: =BU97+BU98 -> 2 | BZ101: Gross YDS | CC101: =CC98+CC97 -> 35 | CF101: =CF98+CF97 -> 0
G106: 2-1-2. C.Fabric W/H - Trans Location Reg.
J109: C.Fabric W/H - Trans Location Reg. | S109: Status
J111: Reg Date | M111: YYYY-MM-DD | R111: ▤ | S111: □ | T111: Date Modify | W111: Depot | AA111: C. Fabric W/H | AG111: + | AV111: Query | AY111: Save | BB111: Delete
J113: File no. | M113: XXXXXXXXXX | R113: + | S113: Style no. | V113: XXXXXXXXXX | AA113: + | AC113: W/H Location | AG113: (L.Zone) | AJ113: ▼ | AK113: P01 | AN113: ▼ | AO113: L01-C01 | AR113: ▼
J115: [ Query details ]
J117: ■ | K117: Depot | P117: W/H Location | AB117: Order | AM117: Item | BE117: Bulk Info. | BT117: Gross Qty | CB117: Barcode
P118: Zone | T118: Class 1 | X118: Class 2 | AB118: File no. | AF118: Style no. | AJ118: Part | AM118: CODE | AP118: Name | AU118: Description | BB118: Color | BE118: Lot no | BH118: Roll no | BK118: UNIT | BN118: Qty | BQ118: Width | BT118: UNIT | BV118: Length | BY118: Weight
J119: V | K119: C. Fabric W/H | P119: (L.Zone) | T119: P01 | X119: L01-C01 | AB119: TN19GB8044 | AF119: 12345 | AJ119: BODY | AM119: XXXXXXXX | AP119: XXXXXXXX | AU119: XXXXXXXXXXXXXXXXX | BB119: BLK | BE119: XXX1 | BH119: 1 | BK119: Roll | BN119: 1 | BQ119: 66 | BT119: YDS | BV119: 60 | BY119: - | CB119: XXXXXXXXXXXXXXXXX | CH119: ▤
J120: V | K120: C. Fabric W/H | P120: (L.Zone) | T120: P01 | X120: L01-C01 | AB120: TN19GB8044 | AF120: 12345 | AJ120: BODY | AM120: XXXXXXXX | AP120: XXXXXXXX | AU120: XXXXXXXXXXXXXXXXX | BB120: BLK | BE120: XXX2 | BH120: 2 | BK120: Roll | BN120: 1 | BQ120: 66 | BT120: YDS | BV120: 40 | BY120: - | CB120: XXXXXXXXXXXXXXXXX
J121: □ | K121: C. Fabric W/H | P121: (L.Zone) | T121: P01 | X121: L01-C01 | AB121: TN19GB8044 | AF121: 12345 | AJ121: BODY | AM121: XXXXXXXX | AP121: XXXXXXXX | AU121: XXXXXXXXXXXXXXXXX | BB121: BLK | BE121: XXX3 | BH121: 3 | BK121: Roll | BN121: 1 | BQ121: 66 | BT121: YDS | BV121: 100 | BY121: - | CB121: XXXXXXXXXXXXXXXXX
BL124: Total | BN124: =BN121+BN120+BN119 -> 3 | BV124: =BV121+BV120+BV119 -> 200 | BY124: -
J128: Trans Location | N128: (L.Zone) | Q128: ▼ | R128: P01 | U128: ▼ | V128: L01-C02 | Y128: ▼ | Z128: Add & Apply | AF128: Barcode | AI128: XXXXXXXXXXXXXXXXX
AI129: ↑ 조건 입력후 조회할 수도 있으나 변경대상 바코드 스캔하여 Trans Location - Reg 테이블로 보낼 수 있도록 하기 위한 목적. 단, 사전 Trans Location 입력 필수
J132: [ Trans Location - Reg. ] | P132: Del | U132: Reg No. | X132: XXXXXXXXXX
J134: ■ | K134: Depot | P134: W/H Location | AB134: Order | AM134: Item | BE134: Bulk Info. | BT134: Gross Qty | CB134: Barcode
P135: Zone | T135: Class 1 | X135: Class 2 | AB135: File no. | AF135: Style no. | AJ135: Part | AM135: CODE | AP135: Name | AU135: Description | BB135: Color | BE135: Lot no | BH135: Roll no | BK135: UNIT | BN135: Qty | BQ135: Width | BT135: UNIT | BV135: Length | BY135: Weight
J136: □ | K136: C. Fabric W/H | P136: (L.Zone) | T136: P01 | X136: L01-C02 | AB136: TN19GB8044 | AF136: 12345 | AJ136: BODY | AM136: XXXXXXXX | AP136: XXXXXXXX | AU136: XXXXXXXXXXXXXXXXX | BB136: BLK | BE136: XXX1 | BH136: 1 | BK136: Roll | BN136: 1 | BQ136: 66 | BT136: YDS | BV136: 60 | BY136: 0 | CB136: XXXXXXXXXXXXXXXXX | CH136: ▤
J137: □ | K137: C. Fabric W/H | P137: (L.Zone) | T137: P01 | X137: L01-C02 | AB137: TN19GB8044 | AF137: 12345 | AJ137: BODY | AM137: XXXXXXXX | AP137: XXXXXXXX | AU137: XXXXXXXXXXXXXXXXX | BB137: BLK | BE137: XXX1 | BH137: 1 | BK137: Roll | BN137: 1 | BQ137: 66 | BT137: YDS | BV137: 50 | BY137: 0 | CB137: XXXXXXXXXXXXXXXXX
BJ140: Total : | BN140: =BN136+BN137 -> 2 | BT140: YDS | BV140: =BV136+BV137 -> 110 | BY140: =BY136+BY137 -> 0
J146: C.Fabric W/H - Trans Location Reg. | T146: Status
J148: Reg Date | M148: YYYY-MM-DD | Q148: ▤ | R148: ~ | S148: YYYY-MM-DD | W148: ▤ | Y148: Depot | AB148: C. Fabric W/H | AH148: + | CO148: Query | CR148: Excel
J150: Buyer | M150: XXXXXXXXXX | S150: File no. | U150: XXXXXXXXXX | Z150: + | AA150: Style no. | AD150: XXXXXXXXXX | AH150: + | AI150: Lot no. | AL150: XXXXXXXXXX | AQ150: Barcode | AT150: XXXXXXXXXX | AY150: Reg no. | BB150: XXXXXXXXXX
J152: ■ | K152: Reg no. | O152: Reg Date | S152: Depot | Y152: Before | AH152: After | AQ152: Order | BB152: Item | BT152: Bulk Info. | CI152: Gross Qty | CQ152: Barcode
Y153: Zone | AB153: Class 1 | AE153: Class 2 | AH153: Zone | AK153: Class 1 | AN153: Class 2 | AQ153: File no. | AU153: Style no. | AY153: Part | BB153: CODE | BE153: Name | BJ153: Description | BQ153: Color | BT153: Lot no | BW153: Roll no | BZ153: UNIT | CC153: Qty | CF153: Width | CI153: UNIT | CK153: Length | CN153: Weight
J154: □ | K154: XXXXXXXX | O154: YYYY-MM-DD | S154: C. Fabric W/H | Y154: (L.Zone) | AB154: P01 | AE154: L01-C01 | AH154: (L.Zone) | AK154: P01 | AN154: L01-C02 | AQ154: TN19GB8044 | AU154: 12345 | AY154: BODY | BB154: XXXXXXXX | BE154: XXXXXXXX | BJ154: XXXXXXXXXXXXXXXXX | BQ154: BLK | BT154: XXX1 | BW154: 1 | BZ154: Roll | CC154: 1 | CF154: 66 | CI154: YDS | CK154: 60 | CN154: 0 | CQ154: XXXXXXXX
J155: □ | K155: XXXXXXXX | O155: YYYY-MM-DD | S155: C. Fabric W/H | Y155: (L.Zone) | AB155: P01 | AE155: L01-C01 | AH155: (L.Zone) | AK155: P01 | AN155: L01-C02 | AQ155: TN19GB8044 | AU155: 12345 | AY155: BODY | BB155: XXXXXXXX | BE155: XXXXXXXX | BJ155: XXXXXXXXXXXXXXXXX | BQ155: BLK | BT155: XXX1 | BW155: 1 | BZ155: Roll | CC155: 1 | CF155: 66 | CI155: YDS | CK155: 50 | CN155: 0 | CQ155: XXXXXXXX
BY158: Total : | CC158: =CC154+CC155 -> 2 | CI158: YDS | CK158: =CK154+CK155 -> 110 | CN158: =CN154+CN155 -> 0
J161: * Trans Location 정보는 입출고현황의 입출고 내역(수량)에 표현하지 않음
G164: 2-1-3. C.Fabric W/H - Trans SPEC Reg.
J167: C.Fabric W/H - Trans SPEC Reg. | T167: Status
J169: Reg Date | N169: YYYY-MM-DD | S169: ▤ | T169: □ | U169: Date Modify | X169: Depot | AB169: C. Fabric W/H | AH169: + | AJ169: Barcode | AM169: XXXXXXXXXXXXXXXXX | AW169: Query | AZ169: Save | BC169: Delete | BG169: Barcode Print
J171: W/H Location | N171: (L.Zone) | Q171: ▼ | R171: P01 | U171: ▼ | V171: L01-C01 | Y171: ▼ | AZ171: ↑ Save 시 바코드 신규생성
J173: File no. | N173: XXXXXXXXXX | S173: + | T173: Style no. | W173: XXXXXXXXXX | AB173: +
J175: [ Query details ]
J177: ■ | K177: Depot | P177: W/H Location | AB177: Order | AM177: Item | BE177: Bulk Info. | BT177: Gross Qty | CB177: Barcode
P178: Zone | T178: Class 1 | X178: Class 2 | AB178: File no. | AF178: Style no. | AJ178: Part | AM178: CODE | AP178: Name | AU178: Description | BB178: Color | BE178: Lot no | BH178: Roll no | BK178: UNIT | BN178: Qty | BQ178: Width | BT178: UNIT | BV178: Length | BY178: Weight
J179: V | K179: C. Fabric W/H | P179: (L.Zone) | T179: P01 | X179: L01-C01 | AB179: TN19GB8044 | AF179: 12345 | AJ179: BODY | AM179: XXXXXXXX | AP179: XXXXXXXX | AU179: XXXXXXXXXXXXXXXXX | BB179: BLK | BE179: XXX1 | BH179: 1 | BK179: Roll | BN179: 1 | BQ179: 66 | BT179: YDS | BV179: 60 | BY179: - | CB179: XXXXXXXXXXXXXXXXX | CH179: ▤
J180: V | K180: C. Fabric W/H | P180: (L.Zone) | T180: P01 | X180: L01-C01 | AB180: TN19GB8044 | AF180: 12345 | AJ180: BODY | AM180: XXXXXXXX | AP180: XXXXXXXX | AU180: XXXXXXXXXXXXXXXXX | BB180: BLK | BE180: XXX2 | BH180: 2 | BK180: Roll | BN180: 1 | BQ180: 66 | BT180: YDS | BV180: 40 | BY180: - | CB180: XXXXXXXXXXXXXXXXX
J181: □ | K181: C. Fabric W/H | P181: (L.Zone) | T181: P01 | X181: L01-C01 | AB181: TN19GB8044 | AF181: 12345 | AJ181: BODY | AM181: XXXXXXXX | AP181: XXXXXXXX | AU181: XXXXXXXXXXXXXXXXX | BB181: BLK | BE181: XXX3 | BH181: 3 | BK181: Roll | BN181: 1 | BQ181: 66 | BT181: YDS | BV181: 100 | BY181: - | CB181: XXXXXXXXXXXXXXXXX
...

Sheet 3.Sewing
E3: Ⅲ. Sewing Line
F5: ※ System Menu 구성
H7: ◆ Sewing Line | O7: ◆ Sewing Bundle W/H | Y7: □ | Z7: S.Bundle W/H IN - Reg. | AM7: : 봉제라인 재단물 창고 입고 등록
O8: (S.Bundle W/H) | Y8: □ | Z8: S.Bundle W/H - Trans Location Reg. | AM8: : 봉제라인 재단물 창고 Location 변경 등록
Y9: □ | Z9: S.Bundle W/H - Trans SPEC Reg. | AM9: : 봉제라인 재단물 창고 재단물 SPEC 변경등록 (File/Style/Color, Bundle PKG, Bundle)
Y10: □ | Z10: S.Bundle W/H - Trans Split Reg. | AM10: : 봉제라인 재단물 창고 재단물 Split 등록
Y11: □ | Z11: S.Bundle W/H OUT - Reg. | AM11: : 봉제라인 재단물 창고 출고 등록
Y13: (R) | Z13: S.Bundle W/H IN-OUT Ledger (by Month) | AM13: : 월별 봉제라인 재단물 창고 입출고 현황 (for Accounting)
Y14: (R) | Z14: S.Bundle W/H IN-OUT Status (by Period) | AM14: : 기간별 봉제라인 재단물 창고 입출고 현황
Y15: (R) | Z15: S.Bundle W/H - Stock Status (Location) | AM15: : 시점별 봉제라인 재단물 창고 재고 현황 (Location)
O17: ◆ Production Management | Y17: ▶ | Z17: Sewing Line Management
Y18: □ | Z18: Production Scedule Management | AM18: : 라인별 생산계획 등록 (대쉬보드 연계)
Y19: □ | Z19: Production Status by line (Monitoring) | AM19: : 시간대별/라인별 생산현황 모니터링
Y20: □ | Z20: Hourly Sewing Record - Reg. (by Line) | AM20: : 시간대별/라인별 생산실적 등록
Y21: □ | Z21: Daily Sewing Record - Reg. (by Line) | AM21: : 일일 라인별 생산실적 등록
Y22: □ | Z22: Line Defect - Reg. | AM22: : 봉제중/후 완전 or 수선가능 불량 등록
Y24: (R) | Z24: Production Report by period (Q'ty) | AM24: : 수량 기준 기간별 생산현황 리포트
Y25: (R) | Z25: Production Report by period (Amt) | AM25: : 금액 기준 기간별 생산현황 리포트
Y26: (R) | Z26: Production Status (Overall) | AM26: : 세부 생산현황 리포트
Y27: (R) | Z27: Production Status by Process | AM27: : 법인 공정별 생산현황 리포트
Y29: ▶ | Z29: Semi Product IN-OUT
Y30: □ | Z30: Semi Product OUT - Reg. | AM30: : 반제품 부속가공 출고 등록
Y31: □ | Z31: Semi Product Return OUT - Reg. | AM31: : 반제품 부속가공 재출고 등록
Y32: □ | Z32: Semi Product IN - Reg. | AM32: : 반제품 부속가공 입고 등록
Y34: (R) | Z34: Semi Product IN-OUT Status | AM34: : 반제품 (부속가공) 입출고 현황
F38: 3-1. Sewing Bundle W/H
I40: [주의] Sewing Bundle W/H 에서는 부속가공 위한 입출고 불가
G42: 3-1-1. S.Bundle W/H IN - Reg.
I44: [주의] In-bound 내 재단물이 아닌 외부봉제업체 작업중 정책변경으로 재단물 입고시, 재단반에서만 재단물 수기 입고처리 가능
J47: S.Bundle W/H IN - Reg. | T47: Status
J49: W/H IN Date | N49: YYYY-MM-DD | R49: ▤ | S49: □ | T49: Date Modify | X49: Depot | AA49: S.Bundle W/H | AG49: + | AY49: Query | BB49: SAVE | BE49: Delete
J52: [ Request Search ]
J54: Source Depot | N54: C.Bundle W/H | T54: + | U54: □ | V54: Incl. data 'IN' already processed
J56: OUT Date | N56: YYYY-MM-DD | R56: ▤ | S56: ~ | T56: YYYY-MM-DD | X56: ▤ | AC56: OUT Reg no. | AG56: XXXXXXXXXX
J58: File no | N58: XXXXXXXXXX | R58: + | T58: Style no | W58: XXXXXXXXXX | AA58: + | AC58: Style Color | AG58: XXXXXXXXXX | AK58: ▼ | AL58: Bundle no. | AP58: XXXXXXXXXX
J60: [ Query details ]
J62: ■ | K62: IN Y/N | M62: OUT Reg. no | Q62: OUT Date | U62: Source Depot | Z62: B.PKG Barcode | AD62: Bundle no. | AH62: Bundle Barcode | AL62: Order | AX62: SIZE | AZ62: Q'ty
AL63: File no. | AP63: Style no. | AS63: Style Color | AZ63: (PCS) | BC63: ▤
J64: V | K64: N | M64: XXXXXXXX | Q64: YYYY-MM-DD | U64: C.Bundle W/H | Z64: AXXXXXXXX1 | AD64: XXXXXXXXX1 | AH64: XXXXXXXX | AL64: TN18TK7043 | AP64: 241657 | AS64: BCVC13(PL106) | AX64: 18M | AZ64: 14
J65: V | K65: N | M65: XXXXXXXX | Q65: YYYY-MM-DD | U65: C.Bundle W/H | Z65: AXXXXXXXX1 | AD65: XXXXXXXXX2 | AH65: XXXXXXXX | AL65: TN18TK7043 | AP65: 241657 | AS65: BCVC13(PL106) | AX65: 4T | AZ65: 14
J66: □ | K66: N | M66: XXXXXXXX | Q66: YYYY-MM-DD | U66: C.Bundle W/H | Z66: AXXXXXXXX1 | AD66: XXXXXXXXX3 | AH66: XXXXXXXX | AL66: TN18TK7043 | AP66: 241657 | AS66: BCVC13(PL106) | AX66: 4T | AZ66: 14
W69: Counting | Z69: 1 | AD69: 3 | AX69: Total | AZ69: =AZ66+AZ64 -> 28
J72: W/H Location | N72: (L.Zone) | Q72: ▼ | R72: P01 | U72: ▼ | V72: L01-C01 | Y72: ▼ | Z72: Apply | AD72: Barcode | AG72: XXXXXXXXXXXXXXXXX | AM72: ← Bundle PKG Barcode & Bundle Barcode 둘다 스캔 가능. 반드시 W/H Location 정보 입력해야 스캔 가능
J75: [ S.Bundle W/H IN - Reg. ] | Q75: Del Row | AO75: W/H IN no. | AS75: XXXXXXXXXX
J77: ■ | K77: W/H IN Date | O77: Source Depot | T77: Target Depot | Y77: B.PKG Barcode | AC77: Bundle no. | AG77: Order | AS77: SIZE | AV77: Q'ty | AY77: W/H Location
AG78: File no. | AK78: Style no. | AN78: Style Color | AV78: (PCS) | AY78: Zone | BB78: Class 1 | BE78: Class 2 | BH78: ▤
J79: □ | K79: YYYY-MM-DD | O79: C.Bundle W/H | T79: S.Bundle W/H | Y79: AXXXXXXXX1 | AC79: XXXXXXXXX1 | AG79: TN18TK7043 | AK79: 241657 | AN79: BCVC13(PL106) | AS79: 18M | AV79: 14 | AY79: (L.Zone) | BB79: P01 | BE79: L01-C01
J80: □ | K80: YYYY-MM-DD | O80: C.Bundle W/H | T80: S.Bundle W/H | Y80: AXXXXXXXX1 | AC80: XXXXXXXXX2 | AG80: TN18TK7043 | AK80: 241657 | AN80: BCVC13(PL106) | AS80: 4T | AV80: 14 | AY80: (L.Zone) | BB80: P01 | BE80: L01-C01
V83: Counting | Y83: 1 | AC83: 2 | AS83: Total | AV83: =AV80+AV79 -> 28
J86: * 주의 : 출고측 입고요청 정보와 실물 차이 발생시, 동일 입고요청건에 대해 전체 입고처리 불가. 따라서 이동중 분실 혹은 오기의 경우, 해당 출고정보 재수정 필요 (해당 부족분은 보고후 Loss 등 처리)
J90: S.Bundle W/H IN - Reg. | T90: Status
J92: W/H IN Date | N92: YYYY-MM-DD | R92: ▤ | S92: ~ | T92: YYYY-MM-DD | X92: ▤ | AA92: Depot | AD92: S.Bundle W/H | AJ92: ▼ | AL92: Source Depot | AP92: C.Bundle W/H | AV92: + | BF92: Query | BI92: Excel
J94: File no | N94: XXXXXXXXXX | R94: + | S94: Style no | V94: XXXXXXXXXX | Z94: + | AA94: Style Color | AD94: XXXXXXXXXX | AH94: ▼ | AJ94: B.PKG Barcode | AN94: XXXXXXXXX1 | AT94: Bundle no. | AW94: XXXXXXXXX1
J96: W/H Location | N96: (L.Zone) | Q96: ▼ | R96: P01 | U96: ▼ | V96: L01-C01 | Y96: ▼ | Z96: W/H IN Reg no. | AD96: XXXXXXXXXX
J98: ■ | K98: W/H IN Date | O98: W/H IN Reg no. | S98: Source Depot | X98: Target Depot | AC98: B.PKG Barcode | AG98: Bundle no. | AK98: Order | AW98: SIZE | AY98: Q'ty | BB98: W/H Location
AK99: File no. | AO99: Style no. | AR99: Style Color | AY99: (PCS) | BB99: Zone | BE99: Class 1 | BH99: Class 2 | BK99: ▤
J100: □ | K100: YYYY-MM-DD | O100: XXXXXXXXX | S100: C.Bundle W/H | X100: S.Bundle W/H | AC100: AXXXXXXXX1 | AG100: XXXXXXXXX1 | AK100: TN18TK7043 | AO100: 241657 | AR100: BCVC13(PL106) | AW100: 18M | AY100: 10 | BB100: (L.Zone) | BE100: P01 | BH100: L01-C01
J101: □ | K101: YYYY-MM-DD | O101: XXXXXXXXX | S101: C.Bundle W/H | X101: S.Bundle W/H | AC101: AXXXXXXXX1 | AG101: XXXXXXXXX2 | AK101: TN18TK7043 | AO101: 241657 | AR101: BCVC13(PL106) | AW101: 4T | AY101: 12 | BB101: (L.Zone) | BE101: P01 | BH101: L01-C01
Z104: Counting | AC104: 1 | AG104: 2 | AV104: Total | AY104: =AY101+AY100 -> 22
G110: 3-1-2. S.Bundle W/H - Trans Location Reg.
I113: S.Bundle W/H - Trans Location Reg. | R113: Status
I115: Reg Date | M115: YYYY-MM-DD | R115: ▤ | S115: □ | T115: Date Modify | W115: Depot | AA115: S.Bundle W/H | AG115: + | AS115: Query | AV115: Save | AY115: Delete
I117: W/H Location | M117: (L.Zone) | P117: ▼ | Q117: P01 | T117: ▼ | U117: L01-C01 | X117: ▼
I119: File no. | M119: XXXXXXXXXX | R119: + | S119: Style no. | V119: XXXXXXXXXX | AA119: + | AB119: Style Color | AE119: XXXXXXXXXX | AI119: ▼
I121: B. PKG Barcode | M121: XXXXXXXXX1 | S121: Bundle no. | V121: XXXXXXXXX1
I123: [ Query details ]
I125: ■ | J125: B.PKG Barcode | O125: Bundle no. | T125: Depot | Z125: W/H Location | AI125: Order | AU125: Size | AX125: Q'ty (PCS)
Z126: Zone | AC126: Class 1 | AF126: Class 2 | AI126: File no. | AM126: Style no. | AP126: Style Color
I127: V | J127: XXXXXXXXXX1 | O127: XXXXXX18M-01 | T127: S.Bundle W/H | Z127: (L.Zone) | AC127: P01 | AF127: L01-C01 | AI127: TN19GB8044 | AM127: 12345 | AP127: BCVC13(PL106) | AU127: 18M (ITG) | AX127: 12 | BA127: ▤
I128: V | J128: XXXXXXXXXX1 | O128: XXXXXX18M-02 | T128: S.Bundle W/H | Z128: (L.Zone) | AC128: P01 | AF128: L01-C01 | AI128: TN19GB8044 | AM128: 12345 | AP128: BCVC13(PL106) | AU128: 18M (ITG) | AX128: 14
I129: □ | J129: XXXXXXXXXX1 | O129: XXXXXX18M-02 | T129: S.Bundle W/H | Z129: (L.Zone) | AC129: P01 | AF129: L01-C01 | AI129: TN19GB8044 | AM129: 12345 | AP129: BCVC13(PL106) | AU129: 4T (ITG) | AX129: 20
AU132: Total : | AX132: =AX128+AX129+AX127 -> 46
I136: Trans Location | M136: (L.Zone) | P136: ▼ | Q136: P01 | T136: ▼ | U136: L01-C02 | X136: ▼ | Y136: Apply | AC136: Barcode | AF136: XXXXXXXXXXXXXXXXX | AL136: ← Bundle PKG Barcode & Bundle Barcode 둘다 스캔 가능. 반드시 Trans Location 정보 입력해야 스캔 가능
I139: [ Trans Location - Reg. ] | O139: Del Row | AG139: Reg No. | AJ139: XXXXXXXXXX
I141: ■ | J141: B.PKG Barcode | O141: Bundle no. | T141: Depot | Y141: W/H Location | AI141: Order | AU141: Size | AX141: Q'ty (PCS)
Y142: Zone | AB142: Class 1 | AE142: Class 2 | AI142: File no. | AM142: Style no. | AP142: Style Color
I143: □ | J143: XXXXXXXXXX1 | O143: XXXXXX18M-01 | T143: S.Bundle W/H | Y143: (L.Zone) | AB143: P01 | AE143: L01-C02 | AI143: TN19GB8044 | AM143: 12345 | AP143: BCVC13(PL106) | AU143: 18M (ITG) | AX143: 12 | BA143: ▤
I144: □ | J144: XXXXXXXXXX1 | O144: XXXXXX18M-02 | T144: S.Bundle W/H | Y144: (L.Zone) | AB144: P01 | AE144: L01-C02 | AI144: TN19GB8044 | AM144: 12345 | AP144: BCVC13(PL106) | AU144: 18M (ITG) | AX144: 14
AU147: Total : | AX147: =AX143+AX144 -> 26
I153: S.Bundle W/H - Trans Location Reg. | R153: Status
I155: Reg Date | L155: YYYY-MM-DD | P155: ▤ | Q155: ~ | R155: YYYY-MM-DD | V155: ▤ | X155: Depot | AA155: S.Bundle W/H | AG155: + | AI155: W/H Location | AM155: (L.Zone) | AP155: ▼ | AQ155: P01 | AT155: ▼ | AU155: L01-C01 | AX155: ▼ | BH155: Query | BK155: Excel
I157: Buyer | L157: XXXXXXXXXX | R157: File no. | V157: XXXXXXXXXX | AA157: + | AB157: Style no. | AE157: XXXXXXXXXX | AJ157: + | AK157: Style Color | AN157: XXXXXXXXXX | AR157: ▼ | AT157: B. PKG Barcode | AX157: XXXXXXXXX1 | BD157: Bundle no. | BG157: XXXXXXXXX1
I159: ■ | J159: Reg no. | N159: B.PKG Barcode | S159: Bundle no. | X159: Depot | AC159: Before | AL159: After | AU159: Order | BG159: Size | BJ159: Q'ty (PCS)
AC160: Zone | AF160: Class 1 | AI160: Class 2 | AL160: Zone | AO160: Class 1 | AR160: Class 2 | AU160: File no. | AY160: Style no. | BB160: Style Color
I161: □ | J161: XXXXXXXX | N161: XXXXXXXXXX1 | S161: XXXXXX18M-01 | X161: S.Bundle W/H | AC161: (L.Zone) | AF161: P01 | AI161: L01-C01 | AL161: (L.Zone) | AO161: P01 | AR161: L01-C02 | AU161: TN19GB8044 | AY161: 12345 | BB161: BCVC13(PL106) | BG161: 18M (ITG) | BJ161: 12 | BM161: ▤
I162: □ | J162: XXXXXXXX | N162: XXXXXXXXXX1 | S162: XXXXXX18M-02 | X162: S.Bundle W/H | AC162: (L.Zone) | AF162: P01 | AI162: L01-C01 | AL162: (L.Zone) | AO162: P01 | AR162: L01-C02 | AU162: TN19GB8044 | AY162: 12345 | BB162: BCVC13(PL106) | BG162: 18M (ITG) | BJ162: 14
BG165: Total : | BJ165: =BJ161+BJ162 -> 26
I168: * Trans Location 정보는 입출고현황의 입출고 내역에 표현하지 않음
G171: 3-1-3. S.Bundle W/H - Trans SPEC Reg.
J174: S.Bundle W/H - Trans SPEC Reg. | T174: Status
J176: Reg Date | N176: YYYY-MM-DD | S176: ▤ | T176: □ | U176: Date Modify | Y176: Barcode | AB176: XXXXXXXXXXXXXXXXX | AL176: Query | AO176: Save | AR176: Delete | AV176: Bundle Barcode Print
J178: Depot | N178: S.Bundle W/H | S178: + | T178: W/H Location | X178: (L.Zone) | AA178: ▼ | AB178: P01 | AE178: ▼ | AF178: L01-C01 | AI178: ▼ | AO178: ↑ Save 시 Bundle no. 와 Bundle Barcode 신규 생성
J180: File no. | N180: XXXXXXXXXX | S180: + | T180: Style no. | X180: XXXXXXXXXX | AB180: + | AC180: Style Color | AF180: XXXXXXXXXX | AJ180: ▼
J182: B. PKG Barcode | N182: XXXXXXXXX1 | T182: Bundle no. | X182: XXXXXXXXX1
J184: [ Query details ] | N184: * [주의] Trans SPEC 변경은 Color & Size 동일한 Bundle 선택시 다중 선택 가능하나, Color & Size 다를시 다중 선택 불가
J186: ■ | K186: Depot | P186: B.PKG Barcode | U186: Bundle no. | Z186: W/H Location | AI186: Order | AU186: Size | AX186: Q'ty (PCS)
Z187: Zone | AC187: Class 1 | AF187: Class 2 | AI187: File no. | AM187: Style no. | AP187: Style Color
J188: V | K188: S.Bundle W/H | P188: XXXXXXXXXX1 | U188: XXXXXX18M-01 | Z188: (L.Zone) | AC188: P01 | AF188: L01-C01 | AI188: TN19GB8044 | AM188: 12345 | AP188: BCVC13(PL106) | AU188: 18M (ITG) | AX188: 12 | BA188: ▤
J189: V | K189: S.Bundle W/H | P189: XXXXXXXXXX1 | U189: XXXXXX18M-02 | Z189: (L.Zone) | AC189: P01 | AF189: L01-C01 | AI189: TN19GB8044 | AM189: 12345 | AP189: BCVC13(PL106) | AU189: 18M (ITG) | AX189: 14
J190: □ | K190: S.Bundle W/H | P190: XXXXXXXXXX1 | U190: XXXXXX18M-02 | Z190: (L.Zone) | AC190: P01 | AF190: L01-C01 | AI190: TN19GB8044 | AM190: 12345 | AP190: BCVC13(PL106) | AU190: 4T (ITG) | AX190: 20
...

Sheet 3-1.Prod.Plan
D3: 3-2-1. Production Scedule Management
G5: : 당 메뉴는 ESP2 (수출관리시스템) 과 연동 필수
H7: ※ [ESP2] Order Schedule Management
Y10: Order -Reg.
M11: Order Status
K13: Buyer | Q13: OSHKOSH | Z13: + | AC13: Initial reg. | AJ13: YYYY-MM-DD | AR13: Last update | AY13: YYYY-MM-DD | BW13: New | CC13: Delete | CI13: Save | CO13: Print
K16: Reg no. | Q16: TOK-XXXXXXXX | AC16: Prod.D. | AH16: SHWE LIN PAN | AQ16: + | AT16: Order Status | BC16: Fixed | BL16: ▼ | BO16: Person in charge | BZ16: (Eng Name) | CK16: #(Phone Number)
K19: File no. | Q19: TY20OK0011 | AC19: PO no. | AH19: 193897 | AT19: FOB | AX19: @ PCS | BC19: 3.4
K23: Garment Sketch | X23: + | Z23: - | AC23: Style no. | AR23: Delivery / Order Q'ty | BO23: Prod. Schedule | BZ23: - Request - | CK23: - Prod. Plan -
AC26: (Style no.) | AN26: + | AR26: YYYY-MM-DD | BC26: (Order Q'ty) | BK26: + | BO26: Cutting | BZ26: YYYY-MM-DD | CK26: YYYY-MM-DD
AC29: 1J056810 | AN29: - | AR29: 43869 | BC29: 117 | BK29: - | BO29: Sewing | BZ29: YYYY-MM-DD | CK29: YYYY-MM-DD
AC31: 2J056810 | AN31: - | AR31: 43870 | BC31: 890 | BK31: -
AC33: 3J056810 | AN33: - | AR33: 43871 | BC33: 13362 | BK33: -
AN35: - | AR35: 43875 | BC35: 12416 | BK35: -
AN37: - | AR37: 43876 | BC37: 8592 | BK37: -
AN39: - | AR39: 43877 | BC39: 23382 | BK39: -
AN41: - | AR41: 43880 | BC41: 10123 | BK41: -
K43: Garment Description | AN43: - | AR43: 43880 | BC43: 10123 | BK43: -
K45: Full Runnina Leqqings | AR45: Total | BC45: =BC31+BC33+BC35+BC37+BC39+BC41+BC43+BC43 -> 89011
K48: Remark
K59: * Person in charge (영업담당자) 의 경우, 현지화 대비 영문을 Default 로 등록 (한글사용 지양 필요 - 향후 ESP2 전반적인 수정 필요)
K60: * 기 등록된 오더를 Delete 할 경우, Order Status 에 Delete 로 표현될 뿐, 등록된 내역에 대한 삭제 불용
M63: Order Status
AB64: Order - Reg.
K66: Date | Q66: Initial Reg. date | Z66: ▼ | AC66: YYYY-MM-DD | AL66: ▤ | AN66: ~ | AP66: YYYY-MM-DD | AY66: ▤ | BB66: □ | BD66: Excl. closing File | EH66: Query | EN66: Excel | ET66: Delete
K68: Buyer | Q68: OSHKOSH | Z68: + | AC68: Prod.Depot | AI68: SHWE LIN PAN | AR68: + | AU68: File no. | AZ68: XXXXXXXXXX | BI68: + | BL68: Reg no. | BQ68: TOK-XXXXXXXX | CC68: Person in charge | CM68: (Eng Name) | CY68: Order Status | DF68: Fixed | DM68: ▼
K70: Feedback | R70: Prod. Schedule | AA70: □ | AC70: Fixed | AG70: □ | AI70: not Fixed | AQ70: Update Check | AZ70: □ | BB70: check | BF70: □ | BH70: uncheck
K72: ■ | M72: Reg no. | W72: Sketch | AB72: Person in charge | AK72: Reg Date & Feedback | BG72: Order Info | EH72: Prod. Plan
AK73: Initial | AT73: C | AV73: Last update | BE73: C | BG73: Buyer | BP73: File no. | BY73: PO no. | CH73: Status | CO73: Order Q'ty | CX73: @FOB | DG73: Delivery (1st) | DP73: Delivery (F) | DY73: Factory | EH73: Cutting | EQ73: Sewing
K74: □ | M74: TOK-XXXXXXX1 | AB74: Kevin | AK74: YYYY-MM-DD | AT74: V | AV74: YYYY-MM-DD | BE74: □ | BG74: OSHKOSH | BP74: TY20OK0011 | BY74: 1J056810 | CH74: Fixed | CO74: 89011 | CX74: 3.4 | DG74: 43869 | DP74: 43880 | DY74: SHWE LIN PAN | EH74: 43869 | EQ74: 43880
K75: □ | M75: TOK-XXXXXXX2 | AB75: Kevin | AK75: YYYY-MM-DD | AT75: V | AV75: - | BE75: □ | BG75: OSHKOSH | BP75: TY20OK0012 | BY75: 1J056811 | CH75: Fixed | CO75: 89011 | CX75: 3.4 | DG75: 43869 | DP75: 43880 | DY75: SHWE LIN PAN | EH75: 43869 | EQ75: 43880
K76: □ | M76: TOK-XXXXXXX3 | AB76: Kevin | AK76: YYYY-MM-DD | AT76: □ | AV76: - | BE76: □ | BG76: OSHKOSH | BP76: TY20OK0013 | BY76: 1J056812 | CH76: Not fixed | CO76: 89011 | CX76: 3.4 | DG76: 43869 | DP76: 43880 | DY76: SHWE LIN PAN | EH76: - | EQ76: -
K77: □ | M77: TOK-XXXXXXX4 | AB77: Kevin | AK77: YYYY-MM-DD | AT77: □ | AV77: - | BE77: □ | BG77: OSHKOSH | BP77: - | BY77: 1J056813 | CH77: Delete | CO77: 89011 | CX77: 3.4 | DG77: 43869 | DP77: 43880 | DY77: SHWE LIN PAN | EH77: - | EQ77: -
K79: * File no. 생성전 오더등록 Case 및 File no. 생성후 Overwrite 위해 Reg no. 별도 관리 필요
K80: * Feedback 은 영업에서 등록한 오더에 대한 라인계획 수립 여부 및 오더정보 Update 시 해당 내역 인지하고 조정반영 했는지 여부 회신 관리용
K81: * 기 등록된 오더를 삭제시 (오더캔슬 또는 별도 신규등록 등 원인), Order Status 에 Delete 로 표현될 뿐, 등록된 오더내역 삭제 불가
H85: ※ [PMS 영역]
G89: Production Schedule
E92: Schedule | R92: Schedule - Reg
AQ93: Prod.Depot | AX93: SHWE LIN PAN | BG93: ▼ | BI93: Queyr date | BP93: YYYY-MM-DD | BX93: - | BY93: YYYY-MM-DD | CH93: □ Excl. sketch | DS93: Query | DY93: Excel | EE93: Print | EK93: Save
CQ94: Last update : 2020.02.25
F95: Query date | N95: Delivery | T95: ▼ | W95: YYYY-MM-DD | AE95: - | AF95: YYYY-MM-DD
AX96: Jan | CC96: Feb | DF96: Mar | EK96: Apr
AX97: W | AY97: T | AZ97: F | BA97: S | BB97: S | BC97: M | BD97: T | BE97: W | BF97: T | BG97: F | BH97: S | BI97: S | BJ97: M | BK97: T | BL97: W | BM97: T | BN97: F | BO97: S | BP97: S | BQ97: M | BR97: T | BS97: W | BT97: T | BU97: F | BV97: S | BW97: S | BX97: M | BY97: T | BZ97: W | CA97: T | CB97: F | CC97: S | CD97: S | CE97: M | CF97: T | CG97: W | CH97: T | CI97: F | CJ97: S | CK97: S | CL97: M | CM97: T | CN97: W | CO97: T | CP97: F | CQ97: S | CR97: S | CS97: M | CT97: T | CU97: W | CV97: T | CW97: F | CX97: S | CY97: S | CZ97: M | DA97: T | DB97: W | DC97: T | DD97: F | DE97: S | DF97: S | DG97: M | DH97: T | DI97: W | DJ97: T | DK97: F | DL97: S | DM97: S | DN97: M | DO97: T | DP97: W | DQ97: T | DR97: F | DS97: S | DT97: S | DU97: M | DV97: T | DW97: W | DX97: T | DY97: F | DZ97: S | EA97: S | EB97: M | EC97: T | ED97: W | EE97: T | EF97: F | EG97: S | EH97: S | EI97: M | EJ97: T | EK97: W | EL97: T | EM97: F | EN97: S | EO97: S | EP97: M
F98: Buyer | N98: (All) | T98: ▼ | W98: Prod. Depot | AF98: (All) | AL98: ▼ | AX98: 1 | AY98: =AX98+1 -> 2 | AZ98: =AY98+1 -> 3 | BA98: =AZ98+1 -> 4 | BB98: =BA98+1 -> 5 | BC98: =BB98+1 -> 6 | BD98: =BC98+1 -> 7 | BE98: =BD98+1 -> 8 | BF98: =BE98+1 -> 9 | ... CB98: =CA98+1 -> 31 | CC98: 1 | CD98: =CC98+1 -> 2 | CE98: =CD98+1 -> 3 | CF98: =CE98+1 -> 4 | CG98: =CF98+1 -> 5 | CH98: =CG98+1 -> 6 | CI98: =CH98+1 -> 7 | CJ98: =CI98+1 -> 8 | CK98: =CJ98+1 -> 9 | ... DE98: =DD98+1 -> 29 | DF98: 1 | DG98: =DF98+1 -> 2 | DH98: =DG98+1 -> 3 | DI98: =DH98+1 -> 4 | DJ98: =DI98+1 -> 5 | DK98: =DJ98+1 -> 6 | DL98: =DK98+1 -> 7 | DM98: =DL98+1 -> 8 | DN98: =DM98+1 -> 9 | ... EJ98: =EI98+1 -> 31 | EK98: 1 | EL98: =EK98+1 -> 2 | EM98: =EL98+1 -> 3 | EN98: =EM98+1 -> 4 | EO98: =EN98+1 -> 5 | EP98: =EO98+1 -> 6
AQ100: Line 1
F101: File no. | N101: (All) | AA101: Order Creat | AH101: Query
N104: □ incl.Del-order | W104: □ Update List | AF104: □ Line Blank
AQ105: Line 2
F107: UPDATE | L107: (F) OSHKOSH - TY20OK7030
L108: Line Schedule : 20.01.04 ~ 20.02.02 (L1)
L109: Order Qty : 19,724
L110: Style : 4 (1J6941 2J6941 3J6941 3J6942) | AQ110: Line 3
F112: UPDATE | L112: (F) OSHKOSH - TY20OK7030
L113: Line Schedule : 20.01.04 ~ 20.02.02 (L2)
L114: Order Qty : 19,724
L115: Style : 4 (1J6941 2J6941 3J6941 3J6942) | AQ115: Line 4
L117: (F) OSHKOSH - TY20OK7030
L118: Line Schedule : 20.01.04 ~ 20.02.02 (L3)
L119: Order Qty : 19,724
L120: Style : 4 (1J6941 2J6941 3J6941 3J6942) | AQ120: Line 5
L122: (NF) OSHKOSH - TY20OK7030
L123: Line Schedule : 20.01.04 ~ 20.02.02 (L1)
L124: Order Qty : 19,724
L125: Style : 4 (1J6941 2J6941 3J6941 3J6942) | AQ125: Line 6
L127: (NF) OSHKOSH - TY20OK7030
L128: Line Schedule : 20.01.04 ~ 20.02.02 (L1)
L129: Order Qty : 19,724
L130: Style : 4 (1J6941 2J6941 3J6941 3J6942) | AQ130: Line 7
L132: (F) OSHKOSH - TY20OK7030
L133: Line Schedule : 20.01.04 ~ 20.02.02 (L1)
L134: Order Qty : 19,724
L135: Style : 4 (1J6941 2J6941 3J6941 3J6942) | AQ135: Line 8
L137: (F) OSHKOSH - TY20OK7030
L138: Line Schedule : 20.01.04 ~ 20.02.02 (L1)
L139: Order Qty : 19,724
L140: Style : 4 (1J6941 2J6941 3J6941 3J6942) | AQ140: Line 9
L143: Line Blank (#000002)
L144: Line Schedule : 20.01.04 ~ 20.02.02 (L1)
AQ147: Line Status | AX147: =AX148+AX149+AX150 -> 9 | AY147: =AY148+AY149+AY150 -> 9 | AZ147: =AZ148+AZ149+AZ150 -> 9 | BA147: =BA148+BA149+BA150 -> 9 | BB147: =BB148+BB149+BB150 -> 9 | BC147: =BC148+BC149+BC150 -> 9 | BD147: =BD148+BD149+BD150 -> 9 | BE147: =BE148+BE149+BE150 -> 9 | ... EP147: =EP148+EP149+EP150 -> 9
AQ148: - OP | AX148: 0 | AY148: 0 | AZ148: 0 | BA148: 1 | BB148: 1 | BC148: 2 | BD148: 2 | BE148: 3 | BF148: 3 | BG148: 5 | BH148: 6 | BI148: 6 | BJ148: 6 | BK148: 6 | BL148: 7 | BM148: 7 | BN148: 7 | BO148: 7 | BP148: 7 | BQ148: 7 | BR148: 7 | BS148: 7 | BT148: 7 | BU148: 7 | BV148: 7 | BW148: 7 | BX148: 7 | BY148: 7 | BZ148: 8 | CA148: 8 | CB148: 8 | CC148: 9 | CD148: 9 | CE148: 9 | CF148: 9 | CG148: 9 | CH148: 8 | CI148: 8 | CJ148: 8 | CK148: 8 | CL148: 8 | CM148: 7 | CN148: 7 | CO148: 7 | CP148: 7 | CQ148: 7 | CR148: 7 | CS148: 7 | CT148: 7 | CU148: 7 | CV148: 7 | CW148: 7 | CX148: 7 | CY148: 7 | CZ148: 7 | DA148: 7 | DB148: 7 | DC148: 7 | DD148: 7 | DE148: 7 | DF148: 7 | DG148: 7 | DH148: 2 | DI148: 2 | DJ148: 1 | DK148: 1 | DL148: 1 | DM148: 1 | DN148: 1 | DO148: 1 | DP148: 1 | DQ148: 1 | DR148: 1 | DS148: 1 | DT148: 1 | DU148: 0 | DV148: 0 | DW148: 0 | DX148: 0 | DY148: 0 | DZ148: 0 | EA148: 0 | EB148: 0 | EC148: 0 | ED148: 0 | EE148: 0 | EF148: 0 | EG148: 0 | EH148: 0 | EI148: 0 | EJ148: 0 | EK148: 0 | EL148: 0 | EM148: 0 | EN148: 0 | EO148: 0 | EP148: 0
F149: 1 | 2 | 3 | 4 | 5 | AQ149: - LB | AX149: 0 | AY149: 0 | AZ149: 0 | BA149: 0 | BB149: 0 | BC149: 0 | BD149: 0 | BE149: 0 | BF149: 0 | BG149: 0 | BH149: 0 | BI149: 0 | BJ149: 0 | BK149: 0 | BL149: 0 | BM149: 0 | BN149: 0 | BO149: 0 | BP149: 0 | BQ149: 0 | BR149: 0 | BS149: 0 | BT149: 0 | BU149: 0 | BV149: 0 | BW149: 0 | BX149: 0 | BY149: 0 | BZ149: 0 | CA149: 0 | CB149: 0 | CC149: 0 | CD149: 0 | CE149: 0 | CF149: 0 | CG149: 0 | CH149: 1 | CI149: 1 | CJ149: 1 | CK149: 1 | CL149: 1 | CM149: 2 | CN149: 2 | CO149: 2 | CP149: 2 | CQ149: 2 | CR149: 2 | CS149: 2 | CT149: 2 | CU149: 2 | CV149: 2 | CW149: 2 | CX149: 2 | CY149: 2 | CZ149: 2 | DA149: 2 | DB149: 2 | DC149: 2 | DD149: 2 | DE149: 2 | DF149: 0 | DG149: 0 | DH149: 0 | DI149: 0 | DJ149: 0 | DK149: 0 | DL149: 0 | DM149: 0 | DN149: 0 | DO149: 0 | DP149: 0 | DQ149: 0 | DR149: 0 | DS149: 0 | DT149: 0 | DU149: 0 | DV149: 0 | DW149: 0 | DX149: 0 | DY149: 0 | DZ149: 0 | EA149: 0 | EB149: 0 | EC149: 0 | ED149: 0 | EE149: 0 | EF149: 0 | EG149: 0 | EH149: 0 | EI149: 0 | EJ149: 0 | EK149: 0 | EL149: 0 | EM149: 0 | EN149: 0 | EO149: 0 | EP149: 0
AQ150: - no Plan | AX150: 9 | AY150: 9 | AZ150: 9 | BA150: 8 | BB150: 8 | BC150: 7 | BD150: 7 | BE150: 6 | BF150: 6 | BG150: 4 | BH150: 3 | BI150: 3 | BJ150: 3 | BK150: 3 | BL150: 2 | BM150: 2 | BN150: 2 | BO150: 2 | BP150: 2 | BQ150: 2 | BR150: 2 | BS150: 2 | BT150: 2 | BU150: 2 | BV150: 2 | BW150: 2 | BX150: 2 | BY150: 2 | BZ150: 1 | CA150: 1 | CB150: 1 | CC150: 0 | CD150: 0 | CE150: 0 | CF150: 0 | CG150: 0 | CH150: 0 | CI150: 0 | CJ150: 0 | CK150: 0 | CL150: 0 | CM150: 0 | CN150: 0 | CO150: 0 | CP150: 0 | CQ150: 0 | CR150: 0 | CS150: 0 | CT150: 0 | CU150: 0 | CV150: 0 | CW150: 0 | CX150: 0 | CY150: 0 | CZ150: 0 | DA150: 0 | DB150: 0 | DC150: 0 | DD150: 0 | DE150: 0 | DF150: 2 | DG150: 2 | DH150: 7 | DI150: 7 | DJ150: 8 | DK150: 8 | DL150: 8 | DM150: 8 | DN150: 8 | DO150: 8 | DP150: 8 | DQ150: 8 | DR150: 8 | DS150: 8 | DT150: 8 | DU150: 9 | DV150: 9 | DW150: 9 | DX150: 9 | DY150: 9 | DZ150: 9 | EA150: 9 | EB150: 9 | EC150: 9 | ED150: 9 | EE150: 9 | EF150: 9 | EG150: 9 | EH150: 9 | EI150: 9 | EJ150: 9 | EK150: 9 | EL150: 9 | EM150: 9 | EN150: 9 | EO150: 9 | EP150: 9
E158: Schedule | R158: Schedule - Reg
DI159: Delete | DO159: Save
F161: Prod.D. | K161: SHWE LIN PAN | T161: ▼ | X161: Buyer | AC161: OSHKOSH | AL161: ▼
AU162: Production Schedule - Reg.
F164: File no. | K164: TY20OK0011 | T164: + | Z164: LB Creat | AG164: Query
AU165: Reg date | BC165: YYYY-MM-DD | BL165: ▤ | BO165: Prod.Depot | BU165: SHWE LIN PAN | CD165: ▼ | CG165: Cutting date | CO165: YYYY-MM-DD | CX165: ▤
AU168: Line Schedule reg. | BF168: Add | BJ168: Copy | BN168: Del | CG168: Reg no. | CO168: XXXXXXXXXX
M169: (NF) OSHKOSH - TY20OK7030
M170: Style : 4 ea (1J6941 2J6941 3J6941 3J6942)
M171: Order Qty : 19,724 | V171: Req.Schdule : 20.02.28 | AU171: ■ | AW171: SN | AZ171: Line | BH171: Style no. | BT171: Start | CD171: End | CN171: Days | CS171: @PCS | CY171: Gross Q'ty | DG171: Accu. Q'ty
AU173: □ | AW173: 1 | AZ173: Line 1 | BF173: ▼ | BH173: 1J056810 | BR173: ▼ | BT173: YYYY-MM-DD | CB173: ▤ | CD173: YYYY-MM-DD | CL173: ▤ | CN173: 10 | CS173: 600 | CY173: =CS173*CN173 -> 6000 | DG173: =CY173 -> 6000
M174: (NF) OSHKOSH - TY20OK7030
M175: Style : 4 ea (1J6941 2J6941 3J6941 3J6942) | AU175: □ | AW175: 2 | AZ175: Line 2 | BF175: ▼ | BH175: 2J056810 | BR175: ▼ | BT175: YYYY-MM-DD | CB175: ▤ | CD175: YYYY-MM-DD | CL175: ▤ | CN175: 10 | CS175: 600 | CY175: =CS175*CN175 -> 6000 | DG175: =CY175+DG173 -> 12000
M176: Order Qty : 19,724 | V176: Req.Schdule : 20.02.28
AU177: □ | AW177: 3 | AZ177: Line 3 | BF177: ▼ | BH177: 3J056810 | BR177: ▼ | BT177: YYYY-MM-DD | CB177: ▤ | CD177: YYYY-MM-DD | CL177: ▤ | CN177: 10 | CS177: 600 | CY177: =CS177*CN177 -> 6000 | DG177: =CY177+DG175 -> 18000
M179: (NF) OSHKOSH - TY20OK7030
M180: Style : 4 ea (1J6941 2J6941 3J6941 3J6942)
...

Sheet ESP2.Order Check List
D3: ※ [ESP2] Order Schedule Management
S6: Order -Reg.
G7: Order Status
E9: Buyer | K9: OSHKOSH | T9: + | W9: New Order | AD9: Initial reg. | AK9: YYYY-MM-DD | AS9: Last update | AZ9: YYYY-MM-DD | BW9: Delete | CC9: Save | CI9: Print
E12: Reg no. | K12: TOK-XXXXXXXX | W12: Factory | AB12: SHWE LIN PAN | AK12: + | AN12: Order Status | AW12: Fixed | BF12: ▼ | BI12: Person in charge | BT12: (Eng Name) | CE12: #(Phone Number)
E15: File no. | K15: TY20OK0011 | W15: PO no. | AB15: 193897 | AN15: FOB | AR15: @ PCS | AW15: 3.4
E19: Garment Sketch | R19: + | T19: - | W19: Style no. | AL19: Delivery / Order Q'ty | BI19: Prod. Schedule | BT19: - Request - | CE19: - Prod. Plan -
W22: (Style no.) | AH22: + | AL22: YYYY-MM-DD | AW22: (Order Q'ty) | BE22: + | BI22: Cutting | BT22: YYYY-MM-DD | CE22: YYYY-MM-DD
W25: 1J056810 | AH25: - | AL25: 43869 | AW25: 117 | BE25: - | BI25: Sewing | BT25: YYYY-MM-DD | CE25: YYYY-MM-DD
W27: 2J056810 | AH27: - | AL27: 43870 | AW27: 890 | BE27: -
W29: 3J056810 | AH29: - | AL29: 43871 | AW29: 13362 | BE29: -
AH31: - | AL31: 43875 | AW31: 12416 | BE31: -
AH33: - | AL33: 43876 | AW33: 8592 | BE33: -
AH35: - | AL35: 43877 | AW35: 23382 | BE35: -
AH37: - | AL37: 43880 | AW37: 10123 | BE37: -
E39: Garment Description | AH39: - | AL39: 43880 | AW39: 10123 | BE39: -
E41: Full Runnina Leqqings | AL41: Total | AW41: =AW27+AW29+AW31+AW33+AW35+AW37+AW39+AW39 -> 89011
E44: Remark
E55: * Person in charge (영업담당자) 의 경우, 현지화 대비 영문을 Default 로 등록 (한글사용 지양 필요 - 향후 ESP2 전반적인 수정 필요)
E56: * 기 등록된 오더를 Delete 할 경우, Order Status 에 Delete 로 표현될 뿐, 등록된 내역에 대한 삭제 불용
G60: Order Status
V61: Order - Reg.
E63: Date | K63: Initial Reg. date | T63: ▼ | W63: YYYY-MM-DD | AF63: ▤ | AH63: ~ | AJ63: YYYY-MM-DD | AS63: ▤ | AV63: □ | AX63: Excl. closing File | EB63: Query | EH63: Excel | EN63: Delete
E65: Buyer | K65: OSHKOSH | T65: + | W65: Factory | AC65: SHWE LIN PAN | AL65: + | AO65: File no. | AT65: XXXXXXXXXX | BC65: + | BF65: Reg no. | BK65: TOK-XXXXXXXX | BW65: Person in charge | CG65: (Eng Name) | CS65: Order Status | CZ65: Fixed | DG65: ▼
E67: Feedback | L67: Prod. Schedule | U67: □ | W67: Fixed | AA67: □ | AC67: not Fixed | AK67: Update Check | AT67: □ | AV67: check | AZ67: □ | BB67: uncheck
E69: ■ | G69: Reg no. | Q69: Sketch | V69: Person in charge | AE69: Reg Date & Feedback | BA69: Order Info | EB69: Prod. Plan
AE70: Initial | AN70: F | AP70: Last update | AY70: C | BA70: Buyer | BJ70: File no. | BS70: PO no. | CB70: Status | CI70: Order Q'ty | CR70: @FOB | DA70: Delivery (1st) | DJ70: Delivery (F) | DS70: Factory | EB70: Cutting | EK70: Sewing
E71: □ | G71: TOK-XXXXXXX1 | V71: Kevin | AE71: YYYY-MM-DD | AN71: V | AP71: YYYY-MM-DD | AY71: □ | BA71: OSHKOSH | BJ71: TY20OK0011 | BS71: 1J056810 | CB71: Fixed | CI71: 89011 | CR71: 3.4 | DA71: 43869 | DJ71: 43880 | DS71: SHWE LIN PAN | EB71: 43869 | EK71: 43880
E72: □ | G72: TOK-XXXXXXX2 | V72: Kevin | AE72: YYYY-MM-DD | AN72: V | AP72: - | AY72: □ | BA72: OSHKOSH | BJ72: TY20OK0012 | BS72: 1J056811 | CB72: Fixed | CI72: 89011 | CR72: 3.4 | DA72: 43869 | DJ72: 43880 | DS72: SHWE LIN PAN | EB72: 43869 | EK72: 43880
E73: □ | G73: TOK-XXXXXXX3 | V73: Kevin | AE73: YYYY-MM-DD | AN73: □ | AP73: - | AY73: □ | BA73: OSHKOSH | BJ73: TY20OK0013 | BS73: 1J056812 | CB73: Not fixed | CI73: 89011 | CR73: 3.4 | DA73: 43869 | DJ73: 43880 | DS73: SHWE LIN PAN | EB73: - | EK73: -
E74: □ | G74: TOK-XXXXXXX4 | V74: Kevin | AE74: YYYY-MM-DD | AN74: □ | AP74: - | AY74: □ | BA74: OSHKOSH | BJ74: - | BS74: 1J056813 | CB74: Delete | CI74: 89011 | CR74: 3.4 | DA74: 43869 | DJ74: 43880 | DS74: SHWE LIN PAN | EB74: - | EK74: -
E77: * File no. 생성전 오더등록 Case 및 File no. 생성후 Overwrite 위해 Reg no. 별도 관리 필요
E78: * Feedback 은 영업에서 등록한 오더에 대한 라인계획 수립 여부 및 오더정보 Update 시 해당 내역 인지하고 조정반영 했는지 여부 회신 관리용
E79: * 기 등록된 오더를 삭제시 (오더캔슬 또는 별도 신규등록 등 원인), Order Status 에 Delete 로 표현될 뿐, 등록된 오더내역 삭제 불용

Sheet 3-2.Monitoring
F2: 3-2-2. Production Status by line (Monitoring)
H5: Hourly Production Status (by Q'ty) | T5: Hourly Production Status (by Amt) | AD5: Chart
W6: ↑ Amt (생산액) 기준 화면은 하단에 공장계 (Prod.Depot) 가 있어야 함
H7: Prod. Date | O7: YYYY-MM-DD | U7: ▤ | AM7: ↓ 생산일수
H9: Prod. Depot | O9: MY1 - Sewing Line | U9: + | AR9: ↓ 목표대비 Color 환경설정 가능해야 함
O13: Today | AA13: Hourly | AM13: Prod. | AR13: Hourly Sewing performance
H14: Factory
O15: Target | S15: Actual | W15: Prog. % | AA15: H.Target | AE15: H.AVG | AI15: Achieve.% | AM15: Dur. | AR15: 1H | AT15: 2H | AV15: 3H | AX15: 4H | AZ15: 5H | BB15: 6H | BD15: 7H | BF15: 8H | BH15: 9H | BJ15: 10H | BL15: 11H | BN15: 12H
H17: Line 01 | O17: 100 | S17: =SUM(AR17:BN17) -> 76 | W17: =S17/O17 -> 0.76 | AA17: =O17/8 -> 12.5 | AE17: =IF(COUNTA(AR17,AT17,AV17,AX17,AZ17,BB17,BD17,BF17,BH17,BJ17,BL17,BN17)=0,0,S17/COUNTA(AR17,AT17,AV17,AX17,AZ17,BB17,BD17,BF17,BH17,BJ17,BL17,BN17)) -> 12.666667 | AI17: =AE17/AA17 -> 1.0133333 | AM17: 10 | AR17: 10 | AT17: 12 | AV17: 13 | AX17: 13 | AZ17: 14 | BB17: 14
H19: Line 02 | O19: 150 | S19: =SUM(AR19:BN19) -> 101 | W19: =S19/O19 -> 0.67333333 | AA19: =O19/8 -> 18.75 | AE19: =IF(COUNTA(AR19,AT19,AV19,AX19,AZ19,BB19,BD19,BF19,BH19,BJ19,BL19,BN19)=0,0,S19/COUNTA(AR19,AT19,AV19,AX19,AZ19,BB19,BD19,BF19,BH19,BJ19,BL19,BN19)) -> 16.833333 | AI19: =AE19/AA19 -> 0.89777778 | AM19: 3 | AR19: 8 | AT19: 15 | AV19: 16 | AX19: 18 | AZ19: 22 | BB19: 22
H21: Line 03 | O21: 200 | S21: =SUM(AR21:BN21) -> 123 | W21: =S21/O21 -> 0.615 | AA21: =O21/8 -> 25 | AE21: =IF(COUNTA(AR21,AT21,AV21,AX21,AZ21,BB21,BD21,BF21,BH21,BJ21,BL21,BN21)=0,0,S21/COUNTA(AR21,AT21,AV21,AX21,AZ21,BB21,BD21,BF21,BH21,BJ21,BL21,BN21)) -> 20.5 | AI21: =AE21/AA21 -> 0.82 | AM21: 1 | AR21: 15 | AT21: 21 | AV21: 20 | AX21: 23 | AZ21: 22 | BB21: 22
H23: Line 04 | O23: 100 | S23: =SUM(AR23:BN23) -> 67 | W23: =S23/O23 -> 0.67 | AA23: =O23/8 -> 12.5 | AE23: =IF(COUNTA(AR23,AT23,AV23,AX23,AZ23,BB23,BD23,BF23,BH23,BJ23,BL23,BN23)=0,0,S23/COUNTA(AR23,AT23,AV23,AX23,AZ23,BB23,BD23,BF23,BH23,BJ23,BL23,BN23)) -> 11.166667 | AI23: =AE23/AA23 -> 0.89333333 | AM23: 5 | AR23: 14 | AT23: 10 | AV23: 11 | AX23: 8 | AZ23: 12 | BB23: 12
H25: Line 05 | O25: 230 | S25: =SUM(AR25:BN25) -> 139 | W25: =S25/O25 -> 0.60434783 | AA25: =O25/8 -> 28.75 | AE25: =IF(COUNTA(AR25,AT25,AV25,AX25,AZ25,BB25,BD25,BF25,BH25,BJ25,BL25,BN25)=0,0,S25/COUNTA(AR25,AT25,AV25,AX25,AZ25,BB25,BD25,BF25,BH25,BJ25,BL25,BN25)) -> 23.166667 | AI25: =AE25/AA25 -> 0.8057971 | AM25: 5 | AR25: 20 | AT25: 18 | AV25: 22 | AX25: 25 | AZ25: 27 | BB25: 27
H27: Line 06 | O27: 150 | S27: =SUM(AR27:BN27) -> 88 | W27: =S27/O27 -> 0.58666667 | AA27: =O27/8 -> 18.75 | AE27: =IF(COUNTA(AR27,AT27,AV27,AX27,AZ27,BB27,BD27,BF27,BH27,BJ27,BL27,BN27)=0,0,S27/COUNTA(AR27,AT27,AV27,AX27,AZ27,BB27,BD27,BF27,BH27,BJ27,BL27,BN27)) -> 14.666667 | AI27: =AE27/AA27 -> 0.78222222 | AM27: 5 | AR27: 5 | AT27: 16 | AV27: 15 | AX27: 12 | AZ27: 20 | BB27: 20
H29: Line 07 | O29: 200 | S29: =SUM(AR29:BN29) -> 68 | W29: =S29/O29 -> 0.34 | AA29: =O29/8 -> 25 | AE29: =IF(COUNTA(AR29,AT29,AV29,AX29,AZ29,BB29,BD29,BF29,BH29,BJ29,BL29,BN29)=0,0,S29/COUNTA(AR29,AT29,AV29,AX29,AZ29,BB29,BD29,BF29,BH29,BJ29,BL29,BN29)) -> 11.333333 | AI29: =AE29/AA29 -> 0.45333333 | AM29: 3 | AR29: 10 | AT29: 11 | AV29: 12 | AX29: 9 | AZ29: 13 | BB29: 13
H31: Line 08 | O31: 100 | S31: =SUM(AR31:BN31) -> 89 | W31: =S31/O31 -> 0.89 | AA31: =O31/8 -> 12.5 | AE31: =IF(COUNTA(AR31,AT31,AV31,AX31,AZ31,BB31,BD31,BF31,BH31,BJ31,BL31,BN31)=0,0,S31/COUNTA(AR31,AT31,AV31,AX31,AZ31,BB31,BD31,BF31,BH31,BJ31,BL31,BN31)) -> 14.833333 | AI31: =AE31/AA31 -> 1.1866667 | AM31: 3 | AR31: 15 | AT31: 13 | AV31: 12 | AX31: 15 | AZ31: 18 | BB31: 16
H33: Line 09 | O33: 50 | S33: =SUM(AR33:BN33) -> 51 | W33: =S33/O33 -> 1.02 | AA33: =O33/8 -> 6.25 | AE33: =IF(COUNTA(AR33,AT33,AV33,AX33,AZ33,BB33,BD33,BF33,BH33,BJ33,BL33,BN33)=0,0,S33/COUNTA(AR33,AT33,AV33,AX33,AZ33,BB33,BD33,BF33,BH33,BJ33,BL33,BN33)) -> 8.5 | AI33: =AE33/AA33 -> 1.36 | AM33: 3 | AR33: 10 | AT33: 10 | AV33: 9 | AX33: 6 | AZ33: 8 | BB33: 8
H35: Line 10 | O35: 50 | S35: =SUM(AR35:BN35) -> 56 | W35: =S35/O35 -> 1.12 | AA35: =O35/8 -> 6.25 | AE35: =IF(COUNTA(AR35,AT35,AV35,AX35,AZ35,BB35,BD35,BF35,BH35,BJ35,BL35,BN35)=0,0,S35/COUNTA(AR35,AT35,AV35,AX35,AZ35,BB35,BD35,BF35,BH35,BJ35,BL35,BN35)) -> 9.3333333 | AI35: =AE35/AA35 -> 1.4933333 | AM35: 1 | AR35: 10 | AT35: 10 | AV35: 11 | AX35: 8 | AZ35: 8 | BB35: 9

Sheet 3-2-1
AU5: Chart
K6: Hourly Production Status (by Qty) | AC6: Hourly Production Status (by Amt)
K8: Query date | R8: YYYY-MM-DD | AA8: ▤ | AC8: ~ | AE8: YYYY-MM-DD | AN8: ▤
K11: Prod.Depot | R11: SHWE LIN PAN | AA11: ▼ | AD11: Prod. Line | AK11: 1111 | AQ11: MY1.Line_01 | AZ11: ▼
O14: ◎ by End-line Sewing record ○ by Net Production amount
K17: Prod. (Amt) | AX17: Accumulate
AY20: T | BA20: C | BC20: A | BE20: D
R40: 1 | T40: 2 | V40: 3 | X40: 4 | Z40: 5 | AB40: 6 | AD40: 7 | AF40: 8 | AH40: 9 | AJ40: 10
J42: * Accumulate : T (Target), C (End-line counting), A (Net Prod. - 불량제외), D (Defect)

Sheet 4.EXIM
E3: Ⅳ. Garment W/H
F5: ※ System Menu 구성
H7: ◆ Garment W/H | O7: ◆ Garment W/H IN-OUT | Y7: □ | Z7: G. W/H PKG - Reg. | AM7: : 완성품 Pakage 등록
O9: ◆ EXPORT | Y9: □ | Z9: Ex-factory - Reg. | AM9: : 완성품 출하(Ex-factory) 등록
F13: 4-1. EXPORT
G15: 4-1-1. Ex-factory - Reg.
I18: Ex-factory - Reg. | P18: Status
I20: Reg Date | M20: YYYY-MM-DD | Q20: ▤ | R20: □ | S20: Date Modify | AE20: Ex-factory Reg. no | AJ20: XXXXXXXXXX | BJ20: SAVE | BM20: Delete
I22: - Ex-factory Header Info.
I24: ■ | J24: Invoice no. | O24: Ex-fac. Date | T24: On Board Date | Y24: Final Inspection | AD24: Transport | AI24: Destination | AN24: Carrier | AS24: B/L no. | AX24: B/L Date | BC24: ETA | BH24: Order Q'ty | BL24: Ex-fac. Q'ty
I25: □ | J25: XXXXXXXXXXXXX | O25: YYYY-MM-DD | S25: + | T25: YYYY-MM-DD | X25: + | Y25: YYYY-MM-DD | AC25: + | AD25: VESSEL | AH25: ▼ | AI25: US | AM25: ▼ | AN25: XXXXXXX | AR25: + | AS25: XXXXXXXXXXXXX | AX25: YYYY-MM-DD | BB25: + | BC25: YYYY-MM-DD | BG25: + | BH25: 600 | BL25: 601
I28: - Ex-factory File Info. | P28: (+) ADD | S28: (+) COPY & ADD | W28: (-) DEL
I30: ■ | J30: Order | AJ30: Ex-factory | BG30: Remark
J31: File no. | O31: Style no. | R31: SEQ | T31: PO no. | W31: Style Color | AC31: Size | AF31: Order Q'ty | AJ31: Factory | AP31: Ex-fac. Q'ty | AT31: Ex-fac. KGS | AX31: Ex-fac. Amt | BB31: Export Permit no. | BO31: ▤
I32: □ | J32: TN18TK7043 | N32: + | O32: 241657 | R32: 11 | T32: QC81T | W32: BCVC13(PL106) | AC32: 18M | AF32: 1200 | AJ32: MASAYA1 | AO32: ▼ | AP32: 600 | AT32: 100 | AX32: =AP32*3 -> 1800 | BB32: XXXXXXXXXXXXX
I33: □ | J33: TN18TK7043 | N33: + | O33: 241657 | R33: 11 | T33: QC81T | W33: BCVC13(PL106) | AC33: 4T | AF33: 1200 | AJ33: MASAYA2 | AO33: ▼ | AP33: 599 | AT33: 100 | AX33: =AP33*3 -> 1797 | BB33: XXXXXXXXXXXXX
I34: □ | J34: TN18TK7043 | N34: + | O34: 241657 | R34: A1 | T34: QC81 | W34: BCVC13(PL106) | AC34: S | AF34: 600 | AJ34: TEXNICA | AO34: ▼ | AP34: 590 | AT34: 95 | AX34: =AP34*3 -> 1770 | BB34: XXXXXXXXXXXXX
AC37: Total | AF37: =AF34+AF33+AF32 -> 3000 | AP37: =AP34+AP33+AP32 -> 1789 | AT37: =AT34+AT33+AT32 -> 295 | AX37: =AX34+AX33+AX32 -> 5367
I40: ※ Summary (Shortage Info.) | P40: *** 해당 Summary 자료 필요한지 여부 점검
I42: ■ | J42: Order | AF42: Q'ty
J43: File no. | O43: Style no. | R43: SEQ | T43: PO no. | W43: Style Color | AC43: Size | AF43: Order Q'ty | AJ43: Ex-fac. Q'ty | AN43: Shortage | AR43: ▤
I44: □ | J44: TN18TK7043 | O44: Style no. | R44: 11 | T44: QC81T | W44: BCVC13(PL106) | AC44: 18M | AF44: 1200 | AJ44: =AP32+AP33 -> 1199 | AN44: =AJ44-AF44 -> -1
I45: □ | J45: TN18TK7043 | O45: Style no. | R45: A1 | T45: QC81 | W45: BCVC13(PL106) | AC45: 4T | AF45: 600 | AJ45: 590 | AN45: =AJ45-AF45 -> -10
AC48: Total | AF48: =AF44+AF45 -> 1800 | AJ48: =AJ44+AJ45 -> 1789 | AN48: =AJ48-AF48 -> -11
G53: 4-1-2. Ex-factory Status
H55: * 기간조회 기준 : Reg Date, Ex-factory Date, On Board Date
H56: * 하기 Status 외, 현황 Report 추가요청 가능성 高
I59: Ex-factory - Reg. | P59: Status
I61: Reg Date | N61: ▼ | P61: YYYY-MM-DD | T61: ▤ | U61: ~ | V61: YYYY-MM-DD | Z61: ▤ | AB61: Factory | AE61: MASAYA1 | AJ61: ▼ | BU61: Query | BX61: Excel
I63: Buyer | L63: XXXXXXXXXX | P63: + | R63: File no | U63: XXXXXXXXXX | Y63: + | Z63: Style no | AC63: XXXXXXXXXX | AG63: + | AI63: PO no | AL63: XXXXXXXXXX | AQ63: Ex-factory Reg. no | AV63: XXXXXXXXXX | BA63: Invoice no | BE63: XXXXXXXXXX
I65: ■ | J65: Reg. Date | N65: Ex-Factory Reg. no | S65: Invoice no | X65: Buyer | AC65: File no. | AG65: Style no. | AJ65: SEQ | AL65: PO no. | AO65: Style Color | AU65: Size | AX65: Factory | BC65: Final Inspection | BG65: Ex-fac. Date | BK65: Ex-fac. Q'ty | BO65: Ex-fac. Amt | BS65: On Board Date | BW65: Closing Date
I66: □ | J66: YYYY-MM-DD | N66: XXXXXXXXXX | S66: XXXXXXXXXX | X66: Buyer | AC66: TN18TK7043 | AG66: Style no. | AJ66: 11 | AL66: QC81T | AO66: BCVC13(PL106) | AU66: 18M | AX66: MASAYA1 | BC66: YYYY-MM-DD | BG66: YYYY-MM-DD | BK66: 601 | BO66: 1803 | BS66: YYYY-MM-DD
I67: □ | J67: YYYY-MM-DD | N67: XXXXXXXXXX | S67: XXXXXXXXXX | X67: Buyer | AC67: TN18TK7043 | AG67: Style no. | AJ67: A1 | AL67: QC81T | AO67: BCVC13(PL106) | AU67: 4T | AX67: MASAYA1 | BC67: YYYY-MM-DD | BG67: YYYY-MM-DD | BK67: 601 | BO67: 1803 | BS67: YYYY-MM-DD
I68: □ | J68: YYYY-MM-DD | N68: XXXXXXXXXX | S68: XXXXXXXXXX | X68: Buyer | AC68: TN18TK7043 | AG68: Style no. | AJ68: A1 | AL68: QC81T | AO68: BCVC13(PL106) | AU68: 4T | AX68: MASAYA1 | BC68: YYYY-MM-DD | BG68: YYYY-MM-DD | BK68: 601 | BO68: 1803 | BS68: YYYY-MM-DD
BG71: Total | BK71: =BK68+BK67+BK66 -> 1803 | BO71: =BO68+BO67+BO66 -> 5409
F77: 4-2. IMPORT
G79: 4-2-1. Import Material - Reg.
I81: : Local 수입서류 관리목적 - 생산관리시스템과 연동되는 Data 없이, 별도 Reg, Status 관리중 (각 법인의 Needs 에 따라 옵션으로 개발 진행)
G106: 4-2-2. Import Material Status
I108: : 5-1-1 내용 참조

Sheet 5.Garment Stock
E3: V. Garment Stock W/H
F5: 5-1. Garment Stock IN - Reg. | AD5: * 입고증 출력 버튼 없음
H8: Garment Stock IN - Reg. | O8: Status
H10: W/H IN Date | L10: YYYY-MM-DD | P10: ▤ | Q10: □ | R10: Date Modify | U10: Depot | X10: Garment Stock W/H | AD10: + | AK10: SAVE | AN10: Delete
H12: Source Depot | L12: MY1 - Sewing Line | R12: +
H14: W/H Location | L14: (L.Type) | O14: ▼ | P14: P01 | S14: ▼ | T14: L01-C01 | W14: ▼
H16: File/Style no | L16: XXXXXXXXXX | P16: XXXXXXXXXX | T16: + | U16: (+) ADD | X16: (+) COPY & ADD | AB16: (-) DEL | AH16: IN Reg. no | AL16: XXXXXXXXXX
H18: ■ | I18: Depot | N18: W/H Location | W18: Order | AJ18: SIZE | AM18: IN Q'ty (PCS)
N19: Type | Q19: Class 1 | T19: Class 2 | W19: File no. | AA19: Style no. | AD19: Style Color | AP19: ▤
H20: □ | I20: Garment Stock W/H | N20: (L.Type) | Q20: P01 | T20: L01-C01 | W20: TN18TK7043 | AA20: 241657 | AD20: BCVC13(PL106) | AI20: ▼ | AJ20: 18M | AL20: ▼ | AM20: 13
H21: □ | I21: Garment Stock W/H | N21: (L.Type) | Q21: P01 | T21: L01-C01 | W21: TN18TK7043 | AA21: 241657 | AD21: BCVC13(PL106) | AI21: ▼ | AJ21: 4T | AL21: ▼ | AM21: 13
H22: □ | I22: Garment Stock W/H | N22: (L.Type) | Q22: P01 | T22: L01-C01 | W22: TN18TK7043 | AA22: 241657 | AD22: BCVC13(PL106) | AI22: ▼ | AJ22: S | AL22: ▼ | AM22: 19
AJ25: PCS Q'ty | AM25: =AM22+AM21+AM20 -> 45
F30: 5-2. Garment Stock OUT - Reg.
H33: Garment Stock OUT - Reg. | O33: Status
H35: W/H OUT Date | L35: YYYY-MM-DD | P35: ▤ | Q35: □ | R35: Date Modify | U35: Depot | X35: Garment Stock W/H | AD35: + | AG35: Query | AJ35: SAVE | AM35: Delete
H37: [ Stock Query ]
H39: W/H Location | L39: (L.Type) | O39: ▼ | P39: P01 | S39: ▼ | T39: L01-C01 | W39: ▼
H41: File/Style no | L41: XXXXXXXXXX | P41: XXXXXXXXXX | T41: + | U41: (+) ADD | X41: (+) COPY & ADD | AB41: (-) DEL
H43: ■ | I43: Depot | O43: W/H Location | X43: Order | AJ43: SIZE | AL43: Q'ty
O44: Type | R44: Class 1 | U44: Class 2 | X44: File no. | AB44: Style no. | AE44: Style Color | AL44: (PCS) | AO44: ▤
H45: V | I45: MY1 - S.Bundle W/H | O45: (L.Type) | R45: P01 | U45: L01-C01 | X45: TN18TK7043 | AB45: 241657 | AE45: BCVC13(PL106) | AJ45: 18M | AL45: 14
H46: V | I46: MY1 - S.Bundle W/H | O46: (L.Type) | R46: P01 | U46: L01-C01 | X46: TN18TK7043 | AB46: 241657 | AE46: BCVC13(PL106) | AJ46: 4T | AL46: 14
H47: □ | I47: MY1 - S.Bundle W/H | O47: (L.Type) | R47: P01 | U47: L01-C01 | X47: TN18TK7043 | AB47: 241657 | AE47: BCVC13(PL106) | AJ47: 4T | AL47: 14
AH50: Chk. PCS Q'ty | AL50: =AL47+AL45 -> 28
H53: Target Depot / Transaction | O53: Sales | U53: + | V53: (▼) Add | Y53: ◎ | Z53: Select only | AC53: ○ | AD53: All
H56: [ Garment Stock OUT - Reg. ] | P56: (-)Del Row | AA56: OUT Reg. no | AE56: XXXXXXXXXX
H58: ■ | I58: W/H OUT Date | M58: Target Depot (Transaction) | R58: Order | AD58: SIZE | AF58: OUT Q'ty (PCS)
R59: File no. | V59: Style no. | Y59: Style Color | AI59: ▤
H60: □ | I60: YYYY-MM-DD | M60: Sales | R60: TN18TK7043 | V60: 241657 | Y60: BCVC13(PL106) | AD60: 18M | AF60: 14
H61: □ | I61: YYYY-MM-DD | M61: Sales | R61: TN18TK7043 | V61: 241657 | Y61: BCVC13(PL106) | AD61: 4T | AF61: 14
AC64: OUT Q'ty | AF64: =AF60+AF61 -> 28

Sheet 예제-본공장운영
B2: Appendix 1. 본공장 생산운영 현황 | I2: * 기본적으로 PMS 와 Global Accounting Data 를 통해 예제 Sheet 를 산출할 수 있어야 함 | AA2: [조업일수 미고려 Raw Data]
B4: 구 분 | H4: 당 월 | Q4: 연누계 | AA4: 당 월 | AJ4: 연누계
H5: 총 계 | I5: 니카라과 | L5: 베트남 | O5: 미얀마 | Q5: 총 계 | R5: 니카라과 | U5: 베트남 | X5: 미얀마 | AA5: 총 계 | AB5: 니카라과 | AE5: 베트남 | AH5: 미얀마 | AJ5: 총 계 | AK5: 니카라과 | AN5: 베트남 | AQ5: 미얀마
J6: ISTMO | K6: TEXNICA | M6: SSVN | N6: SSTSVN | S6: ISTMO | T6: TEXNICA | V6: SSVN | W6: SSTSVN | AC6: ISTMO | AD6: TEXNICA | AF6: SSVN | AG6: SSTSVN | AL6: ISTMO | AM6: TEXNICA | AO6: SSVN | AP6: SSTSVN
B8: Line수 (조업일당 평균) | J8: =AC8/$AC$9 -> 57.545455 | AC8: =[1]니카라과!$O$7 -> 1266
B9: 총 조업일수(Day) | J9: =AC9 -> 22 | AC9: =[1]니카라과!$O$6 -> 22
B10: 총 조업시간(Hour) - Factory 기준 | J10: =AC10 -> 677067.18 | AC10: =AC12+AC23 -> 677067.18
D11: 생산라인 조업시간 | J11: =J15+J26 -> 393274.31 | AC11: =AC15+AC26 -> 393274.31
C12: 정상 | J12: =AC12 -> 640771.18 | AC12: =AC13+AC14+AC15+AC18+AC19+AC20+AC21+AC22 -> 640771.18
D13: 자재창고 | J13: =AC13 -> 5734.67 | AC13: =[1]니카라과!$O$26 -> 5734.67
D14: 재단 | J14: =AC14 -> 39962.66 | AC14: =[1]니카라과!$O$27 -> 39962.66
D15: 생산라인 | J15: =AC15 -> 381586.81 | AC15: =AC16+AC17 -> 381586.81
F16: 미싱사+시다 | J16: =AC16 -> 360515.77 | AC16: =[1]니카라과!$O$28 -> 360515.77
F17: 매니저 | J17: =AC17 -> 21071.04 | AC17: =[1]니카라과!$O$32 -> 21071.04
D18: 완성반 | J18: =AC18 -> 90947.49 | AC18: =[1]니카라과!$O$29 -> 90947.49
D19: 공무 | J19: =AC19 -> 6357.62 | AC19: =[1]니카라과!$O$30 -> 6357.62
D20: QA/QC | J20: =AC20 -> 79471.72 | AC20: =[1]니카라과!$O$31 -> 79471.72
D21: Factory Office | J21: =AC21 -> 36710.21 | AC21: =[1]니카라과!$O$33 -> 36710.21
D22: 기타 | J22: =AC22 -> 0
C23: OT | J23: =AC23 -> 36296 | AC23: =AC24+AC25+AC26+AC29+AC30+AC31+AC32+AC33 -> 36296
D24: 자재창고 | J24: =AC24 -> 603 | AC24: =[1]니카라과!$O$39 -> 603
D25: 재단 | J25: =AC25 -> 2518 | AC25: =[1]니카라과!$O$40 -> 2518
D26: 생산라인 | J26: =AC26 -> 11687.5 | AC26: =AC27+AC28 -> 11687.5
F27: 미싱사+시다 | J27: =AC27 -> 8877.5 | AC27: =[1]니카라과!$O$41 -> 8877.5
F28: 매니저 | J28: =AC28 -> 2810 | AC28: =[1]니카라과!$O$45 -> 2810
D29: 완성반 | J29: =AC29 -> 10652.5 | AC29: =[1]니카라과!$O$42 -> 10652.5
D30: 공무 | J30: =AC30 -> 270 | AC30: =[1]니카라과!$O$43 -> 270
D31: QA/QC | J31: =AC31 -> 4700.5 | AC31: =[1]니카라과!$O$44 -> 4700.5
D32: Factory Office | J32: =AC32 -> 5864.5 | AC32: =[1]니카라과!$O$46 -> 5864.5
D33: 기타 | J33: =AC33 -> 0
B34: 총 투입기계 (조업일당 평균) | J34: =AC34/$AC$9 -> 1515.6364 | AC34: =[1]니카라과!$O$8 -> 33344
B35: 총인원(명) | J35: =AC35/$AC$9 -> 3824.5909 | AC35: =AC36+AC50 -> 84141
C36: Factory | J36: =AC36/$AC$9 -> 3777.7727 | AC36: =AC37+AC38+AC39 -> 83111
D37: 주재원
D38: 제3국인
D39: 현지인 | J39: =AC39/$AC$9 -> 3777.7727 | AC39: =AC40+AC41+AC42+AC45+AC46+AC47+AC48+AC49 -> 83111
E40: 자재창고 | J40: =AC40/$AC$9 -> 34.272727 | AC40: =[1]니카라과!$O$11 -> 754
E41: 재단 | J41: =AC41/$AC$9 -> 238.45455 | AC41: =[1]니카라과!$O$12 -> 5246
E42: 생산라인 | J42: =AC42/$AC$9 -> 2196.5455 | AC42: =AC43+AC44 -> 48324
F43: 미싱사+시다 | J43: =AC43/$AC$9 -> 2076.4091 | AC43: =[1]니카라과!$O$13 -> 45681
F44: 매니저 | J44: =AC44/$AC$9 -> 120.13636 | AC44: =[1]니카라과!$O$17 -> 2643
E45: 완성반 | J45: =AC45/$AC$9 -> 519.13636 | AC45: =[1]니카라과!$O$14 -> 11421
E46: 공무 | J46: =AC46/$AC$9 -> 37 | AC46: =[1]니카라과!$O$15 -> 814
E47: QA/QC | J47: =AC47/$AC$9 -> 474.09091 | AC47: =[1]니카라과!$O$16 -> 10430
E48: Factory Office | J48: =AC48/$AC$9 -> 278.27273 | AC48: =[1]니카라과!$O$18 -> 6122
E49: 기타 | J49: =AC49/$AC$9 -> 0
C50: Main Office | J50: =AC50/$AC$9 -> 46.818182 | AC50: =AC51+AC52+AC53 -> 1030
D51: 주재원
D52: 제3국인
D53: 현지인 | J53: =AC53/$AC$9 -> 46.818182 | AC53: =SUM(AC54:AC57) -> 1030
E54: 인사/총무 | J54: =AC54/$AC$9 -> 13 | AC54: =[1]니카라과!$O$19 -> 286
E55: 회계 | J55: =AC55/$AC$9 -> 0 | AC55: =[1]니카라과!$O$20 -> 0
E56: 수출입 | J56: =AC56/$AC$9 -> 5.9090909 | AC56: =[1]니카라과!$O$21 -> 130
E57: 기타 | J57: =AC57/$AC$9 -> 27.909091 | AC57: =[1]니카라과!$O$22 -> 614
B59: US대비 환율
B60: 법정최저임금

Sheet 예제-생산성지표
B2: Appendix 2. 본공장 관리지표 현황 - 생산성 지표
X3: (unit : USD)
B4: 구 분 | H4: 당 월 | Q4: 연누계
H5: 총 계 | I5: 니카라과 | L5: 베트남 | O5: 미얀마 | Q5: 총 계 | R5: 니카라과 | U5: 베트남 | X5: 미얀마
J6: ISTMO | K6: TEXNICA | M6: SSVN | N6: SSTSVN | S6: ISTMO | T6: TEXNICA | V6: SSVN | W6: SSTSVN
B8: ■ (선적)FOB대비 요율
C9: (선적)FOB대비 공임(CM+HC)% | J9: =('[1]해외-본공장손익'!M30+'[1]해외-본공장손익'!M35)/'[1]해외-본공장손익'!M28 -> 0.28224809
C10: (선적)FOB대비 Net CM% | J10: ='[1]해외-본공장손익'!M30/'[1]해외-본공장손익'!M28 -> 0.25227576
B12: ■ Capa (Net CM기준)
C13: * Max Capa (3년내 Max 월 생산Net CM)
C14: Max Capa 대비 조업율
B16: ■ 생산성 지표
C17: MH당 Net CM (①x②) (라인인원 기준) | J17: =J18*J19 -> 4.0016492
D18: ① PCS당 Net CM | J18: ='[1]해외-본공장손익'!M13/'[1]해외-본공장손익'!M11 -> 0.50026061 | K18: ='[1]해외-본공장손익'!N13/'[1]해외-본공장손익'!N11 -> 0.24
D19: ② MH당 PCS | J19: ='[1]해외-본공장손익'!M11/'예제-본공장운영'!J11 -> 7.9991292
C20: Line 관련지표
D21: Line당 평균 투입기계 | J21: ='예제-본공장운영'!J34/'예제-본공장운영'!J8 -> 26.338073
D22: 투입기계당 (생산) 월 Net CM (USD) | J22: ='[1]해외-본공장손익'!M13/'예제-본공장운영'!J34 -> 1038.34
D23: 투입기계당 총인원 (법인 총현지인) | J23: ='예제-본공장운영'!J35/'예제-본공장운영'!J34 -> 2.5234225
D24: 투입기계당 생산라인 인원 | J24: ='예제-본공장운영'!J42/'예제-본공장운영'!J34 -> 1.4492562
C25: 인원 관련지표(Ⅰ) 공장-현지인
D26: 인당 평균 (생산) 월 Net CM (USD) | J26: ='[1]해외-본공장손익'!M13/'예제-본공장운영'!J36 -> 416.58034
D27: 인당 평균 조업시간 (Hour) | J27: =J29+J30 -> 179.2239
E28: * 일평균 조업시간 (Hour) | J28: =J27/'예제-본공장운영'!J9 -> 8.1465411
F29: 정상 | J29: ='예제-본공장운영'!J12/'예제-본공장운영'!J36 -> 169.61613
F30: OT | J30: ='예제-본공장운영'!J23/'예제-본공장운영'!J36 -> 9.6077776
C31: 인원 관련지표(Ⅱ) 생산라인-현지인
D32: 인당 평균 (생산) 월 Net CM (USD) | J32: ='[1]해외-본공장손익'!M13/'예제-본공장운영'!J42 -> 716.46404
D33: 인당 평균 조업시간 (Hour) | J33: =J35+J36 -> 179.04219
E34: * 일평균 조업시간 (Hour) | J34: =J33/'예제-본공장운영'!J9 -> 8.1382814
F35: 정상 | J35: ='예제-본공장운영'!J15/'예제-본공장운영'!J42 -> 173.72134
F36: OT | J36: ='예제-본공장운영'!J26/'예제-본공장운영'!J42 -> 5.3208551

Sheet 예제-비용분석
B4: Appendix 3. 제조경비 및 일반관리비 현황
AF5: (unit : USD)
B6: 구 분 | H6: 당 월 | U6: 연누계
H7: 총 계 | J7: 니카라과 | N7: 베트남 | R7: 미얀마 | U7: 총 계 | W7: 니카라과 | AA7: 베트남 | AE7: 미얀마
L8: ISTMO | M8: TEXNICA | P8: SSVN | Q8: SSTSVN | Y8: ISTMO | Z8: TEXNICA | AC8: SSVN | AD8: SSTSVN
I9: % | K9: % | O9: % | S9: % | V9: % | X9: % | AB9: % | AF9: %
B10: * 생산 FOB
B11: 생산액 (CMPAS) | I11: =IF(H$10=0,0,H11/H$10) -> 0 | K11: =IF(J$10=0,0,J11/J$10) -> 0 | O11: =IF(N$10=0,0,N11/N$10) -> 0 | S11: =IF(R$10=0,0,R11/R$10) -> 0 | V11: =IF(U$10=0,0,U11/U$10) -> 0 | X11: =IF(W$10=0,0,W11/W$10) -> 0 | AB11: =IF(AA$10=0,0,AA11/AA$10) -> 0 | AF11: =IF(AE$10=0,0,AE11/AE$10) -> 0
C12: Net CM | I12: =IF(H$11=0,0,H12/H$11) -> 0 | K12: =IF(J$11=0,0,J12/J$11) -> 0 | O12: =IF(N$11=0,0,N12/N$11) -> 0 | S12: =IF(R$11=0,0,R12/R$11) -> 0 | V12: =IF(U$11=0,0,U12/U$11) -> 0 | X12: =IF(W$11=0,0,W12/W$11) -> 0 | AB12: =IF(AA$11=0,0,AA12/AA$11) -> 0 | AF12: =IF(AE$11=0,0,AE12/AE$11) -> 0
B13: COGM | I13: =IF(H$11=0,0,H13/H$11) -> 0 | K13: =IF(J$11=0,0,J13/J$11) -> 0 | O13: =IF(N$11=0,0,N13/N$11) -> 0 | S13: =IF(R$11=0,0,R13/R$11) -> 0 | V13: =IF(U$11=0,0,U13/U$11) -> 0 | X13: =IF(W$11=0,0,W13/W$11) -> 0 | AB13: =IF(AA$11=0,0,AA13/AA$11) -> 0 | AF13: =IF(AE$11=0,0,AE13/AE$11) -> 0
C14: 재료비 | I14: =IF(H$11=0,0,H14/H$11) -> 0 | K14: =IF(J$11=0,0,J14/J$11) -> 0 | O14: =IF(N$11=0,0,N14/N$11) -> 0 | S14: =IF(R$11=0,0,R14/R$11) -> 0 | V14: =IF(U$11=0,0,U14/U$11) -> 0 | X14: =IF(W$11=0,0,W14/W$11) -> 0 | AB14: =IF(AA$11=0,0,AA14/AA$11) -> 0 | AF14: =IF(AE$11=0,0,AE14/AE$11) -> 0
C15: 부속가공비 | I15: =IF(H$11=0,0,H15/H$11) -> 0 | K15: =IF(J$11=0,0,J15/J$11) -> 0 | O15: =IF(N$11=0,0,N15/N$11) -> 0 | S15: =IF(R$11=0,0,R15/R$11) -> 0 | V15: =IF(U$11=0,0,U15/U$11) -> 0 | X15: =IF(W$11=0,0,W15/W$11) -> 0 | AB15: =IF(AA$11=0,0,AA15/AA$11) -> 0 | AF15: =IF(AE$11=0,0,AE15/AE$11) -> 0
C16: 외주가공비 | I16: =IF(H$11=0,0,H16/H$11) -> 0 | K16: =IF(J$11=0,0,J16/J$11) -> 0 | O16: =IF(N$11=0,0,N16/N$11) -> 0 | S16: =IF(R$11=0,0,R16/R$11) -> 0 | V16: =IF(U$11=0,0,U16/U$11) -> 0 | X16: =IF(W$11=0,0,W16/W$11) -> 0 | AB16: =IF(AA$11=0,0,AA16/AA$11) -> 0 | AF16: =IF(AE$11=0,0,AE16/AE$11) -> 0
C17: 인건비 | I17: =IF(H$11=0,0,H17/H$11) -> 0 | K17: =IF(J$11=0,0,J17/J$11) -> 0 | O17: =IF(N$11=0,0,N17/N$11) -> 0 | S17: =IF(R$11=0,0,R17/R$11) -> 0 | V17: =IF(U$11=0,0,U17/U$11) -> 0 | X17: =IF(W$11=0,0,W17/W$11) -> 0 | AB17: =IF(AA$11=0,0,AA17/AA$11) -> 0 | AF17: =IF(AE$11=0,0,AE17/AE$11) -> 0
D18: 순수 인건비 | I18: =IF(H$11=0,0,H18/H$11) -> 0 | K18: =IF(J$11=0,0,J18/J$11) -> 0 | O18: =IF(N$11=0,0,N18/N$11) -> 0 | S18: =IF(R$11=0,0,R18/R$11) -> 0 | V18: =IF(U$11=0,0,U18/U$11) -> 0 | X18: =IF(W$11=0,0,W18/W$11) -> 0 | AB18: =IF(AA$11=0,0,AA18/AA$11) -> 0 | AF18: =IF(AE$11=0,0,AE18/AE$11) -> 0
E19: 일반 | I19: =IF(H$11=0,0,H19/H$11) -> 0 | K19: =IF(J$11=0,0,J19/J$11) -> 0 | O19: =IF(N$11=0,0,N19/N$11) -> 0 | S19: =IF(R$11=0,0,R19/R$11) -> 0 | V19: =IF(U$11=0,0,U19/U$11) -> 0 | X19: =IF(W$11=0,0,W19/W$11) -> 0 | AB19: =IF(AA$11=0,0,AA19/AA$11) -> 0 | AF19: =IF(AE$11=0,0,AE19/AE$11) -> 0
E20: OT수당 | I20: =IF(H$11=0,0,H20/H$11) -> 0 | K20: =IF(J$11=0,0,J20/J$11) -> 0 | O20: =IF(N$11=0,0,N20/N$11) -> 0 | S20: =IF(R$11=0,0,R20/R$11) -> 0 | V20: =IF(U$11=0,0,U20/U$11) -> 0 | X20: =IF(W$11=0,0,W20/W$11) -> 0 | AB20: =IF(AA$11=0,0,AA20/AA$11) -> 0 | AF20: =IF(AE$11=0,0,AE20/AE$11) -> 0
D21: 인건비성 경비 | I21: =IF(H$11=0,0,H21/H$11) -> 0 | K21: =IF(J$11=0,0,J21/J$11) -> 0 | O21: =IF(N$11=0,0,N21/N$11) -> 0 | S21: =IF(R$11=0,0,R21/R$11) -> 0 | V21: =IF(U$11=0,0,U21/U$11) -> 0 | X21: =IF(W$11=0,0,W21/W$11) -> 0 | AB21: =IF(AA$11=0,0,AA21/AA$11) -> 0 | AF21: =IF(AE$11=0,0,AE21/AE$11) -> 0
C22: 공장임차료 (건물/토지DA) | I22: =IF(H$11=0,0,H22/H$11) -> 0 | K22: =IF(J$11=0,0,J22/J$11) -> 0 | O22: =IF(N$11=0,0,N22/N$11) -> 0 | S22: =IF(R$11=0,0,R22/R$11) -> 0 | V22: =IF(U$11=0,0,U22/U$11) -> 0 | X22: =IF(W$11=0,0,W22/W$11) -> 0 | AB22: =IF(AA$11=0,0,AA22/AA$11) -> 0 | AF22: =IF(AE$11=0,0,AE22/AE$11) -> 0
C23: 기타 고정자산DA | I23: =IF(H$11=0,0,H23/H$11) -> 0 | K23: =IF(J$11=0,0,J23/J$11) -> 0 | O23: =IF(N$11=0,0,N23/N$11) -> 0 | S23: =IF(R$11=0,0,R23/R$11) -> 0 | V23: =IF(U$11=0,0,U23/U$11) -> 0 | X23: =IF(W$11=0,0,W23/W$11) -> 0 | AB23: =IF(AA$11=0,0,AA23/AA$11) -> 0 | AF23: =IF(AE$11=0,0,AE23/AE$11) -> 0
C24: 수선비 | I24: =IF(H$11=0,0,H24/H$11) -> 0 | K24: =IF(J$11=0,0,J24/J$11) -> 0 | O24: =IF(N$11=0,0,N24/N$11) -> 0 | S24: =IF(R$11=0,0,R24/R$11) -> 0 | V24: =IF(U$11=0,0,U24/U$11) -> 0 | X24: =IF(W$11=0,0,W24/W$11) -> 0 | AB24: =IF(AA$11=0,0,AA24/AA$11) -> 0 | AF24: =IF(AE$11=0,0,AE24/AE$11) -> 0
C25: 수도광열비 | I25: =IF(H$11=0,0,H25/H$11) -> 0 | K25: =IF(J$11=0,0,J25/J$11) -> 0 | O25: =IF(N$11=0,0,N25/N$11) -> 0 | S25: =IF(R$11=0,0,R25/R$11) -> 0 | V25: =IF(U$11=0,0,U25/U$11) -> 0 | X25: =IF(W$11=0,0,W25/W$11) -> 0 | AB25: =IF(AA$11=0,0,AA25/AA$11) -> 0 | AF25: =IF(AE$11=0,0,AE25/AE$11) -> 0
C26: 소모품비 | I26: =IF(H$11=0,0,H26/H$11) -> 0 | K26: =IF(J$11=0,0,J26/J$11) -> 0 | O26: =IF(N$11=0,0,N26/N$11) -> 0 | S26: =IF(R$11=0,0,R26/R$11) -> 0 | V26: =IF(U$11=0,0,U26/U$11) -> 0 | X26: =IF(W$11=0,0,W26/W$11) -> 0 | AB26: =IF(AA$11=0,0,AA26/AA$11) -> 0 | AF26: =IF(AE$11=0,0,AE26/AE$11) -> 0
C27: 기타 | I27: =IF(H$11=0,0,H27/H$11) -> 0 | K27: =IF(J$11=0,0,J27/J$11) -> 0 | O27: =IF(N$11=0,0,N27/N$11) -> 0 | S27: =IF(R$11=0,0,R27/R$11) -> 0 | V27: =IF(U$11=0,0,U27/U$11) -> 0 | X27: =IF(W$11=0,0,W27/W$11) -> 0 | AB27: =IF(AA$11=0,0,AA27/AA$11) -> 0 | AF27: =IF(AE$11=0,0,AE27/AE$11) -> 0
B28: G&A | I28: =IF(H$11=0,0,H28/H$11) -> 0 | K28: =IF(J$11=0,0,J28/J$11) -> 0 | O28: =IF(N$11=0,0,N28/N$11) -> 0 | S28: =IF(R$11=0,0,R28/R$11) -> 0 | V28: =IF(U$11=0,0,U28/U$11) -> 0 | X28: =IF(W$11=0,0,W28/W$11) -> 0 | AB28: =IF(AA$11=0,0,AA28/AA$11) -> 0 | AF28: =IF(AE$11=0,0,AE28/AE$11) -> 0
C29: 인건비 | I29: =IF(H$11=0,0,H29/H$11) -> 0 | K29: =IF(J$11=0,0,J29/J$11) -> 0 | O29: =IF(N$11=0,0,N29/N$11) -> 0 | S29: =IF(R$11=0,0,R29/R$11) -> 0 | V29: =IF(U$11=0,0,U29/U$11) -> 0 | X29: =IF(W$11=0,0,W29/W$11) -> 0 | AB29: =IF(AA$11=0,0,AA29/AA$11) -> 0 | AF29: =IF(AE$11=0,0,AE29/AE$11) -> 0
D30: 순수 인건비 | I30: =IF(H$11=0,0,H30/H$11) -> 0 | K30: =IF(J$11=0,0,J30/J$11) -> 0 | O30: =IF(N$11=0,0,N30/N$11) -> 0 | S30: =IF(R$11=0,0,R30/R$11) -> 0 | V30: =IF(U$11=0,0,U30/U$11) -> 0 | X30: =IF(W$11=0,0,W30/W$11) -> 0 | AB30: =IF(AA$11=0,0,AA30/AA$11) -> 0 | AF30: =IF(AE$11=0,0,AE30/AE$11) -> 0
E31: 일반 | I31: =IF(H$11=0,0,H31/H$11) -> 0 | K31: =IF(J$11=0,0,J31/J$11) -> 0 | O31: =IF(N$11=0,0,N31/N$11) -> 0 | S31: =IF(R$11=0,0,R31/R$11) -> 0 | V31: =IF(U$11=0,0,U31/U$11) -> 0 | X31: =IF(W$11=0,0,W31/W$11) -> 0 | AB31: =IF(AA$11=0,0,AA31/AA$11) -> 0 | AF31: =IF(AE$11=0,0,AE31/AE$11) -> 0
E32: OT수당 | I32: =IF(H$11=0,0,H32/H$11) -> 0 | K32: =IF(J$11=0,0,J32/J$11) -> 0 | O32: =IF(N$11=0,0,N32/N$11) -> 0 | S32: =IF(R$11=0,0,R32/R$11) -> 0 | V32: =IF(U$11=0,0,U32/U$11) -> 0 | X32: =IF(W$11=0,0,W32/W$11) -> 0 | AB32: =IF(AA$11=0,0,AA32/AA$11) -> 0 | AF32: =IF(AE$11=0,0,AE32/AE$11) -> 0
D33: 인건비성 경비 | I33: =IF(H$11=0,0,H33/H$11) -> 0 | K33: =IF(J$11=0,0,J33/J$11) -> 0 | O33: =IF(N$11=0,0,N33/N$11) -> 0 | S33: =IF(R$11=0,0,R33/R$11) -> 0 | V33: =IF(U$11=0,0,U33/U$11) -> 0 | X33: =IF(W$11=0,0,W33/W$11) -> 0 | AB33: =IF(AA$11=0,0,AA33/AA$11) -> 0 | AF33: =IF(AE$11=0,0,AE33/AE$11) -> 0
C34: 고정자산DA | I34: =IF(H$11=0,0,H34/H$11) -> 0 | K34: =IF(J$11=0,0,J34/J$11) -> 0 | O34: =IF(N$11=0,0,N34/N$11) -> 0 | S34: =IF(R$11=0,0,R34/R$11) -> 0 | V34: =IF(U$11=0,0,U34/U$11) -> 0 | X34: =IF(W$11=0,0,W34/W$11) -> 0 | AB34: =IF(AA$11=0,0,AA34/AA$11) -> 0 | AF34: =IF(AE$11=0,0,AE34/AE$11) -> 0
C35: 복리후생비 | I35: =IF(H$11=0,0,H35/H$11) -> 0 | K35: =IF(J$11=0,0,J35/J$11) -> 0 | O35: =IF(N$11=0,0,N35/N$11) -> 0 | S35: =IF(R$11=0,0,R35/R$11) -> 0 | V35: =IF(U$11=0,0,U35/U$11) -> 0 | X35: =IF(W$11=0,0,W35/W$11) -> 0 | AB35: =IF(AA$11=0,0,AA35/AA$11) -> 0 | AF35: =IF(AE$11=0,0,AE35/AE$11) -> 0
C36: 접대비 | I36: =IF(H$11=0,0,H36/H$11) -> 0 | K36: =IF(J$11=0,0,J36/J$11) -> 0 | O36: =IF(N$11=0,0,N36/N$11) -> 0 | S36: =IF(R$11=0,0,R36/R$11) -> 0 | V36: =IF(U$11=0,0,U36/U$11) -> 0 | X36: =IF(W$11=0,0,W36/W$11) -> 0 | AB36: =IF(AA$11=0,0,AA36/AA$11) -> 0 | AF36: =IF(AE$11=0,0,AE36/AE$11) -> 0
C37: 소모품비 | I37: =IF(H$11=0,0,H37/H$11) -> 0 | K37: =IF(J$11=0,0,J37/J$11) -> 0 | O37: =IF(N$11=0,0,N37/N$11) -> 0 | S37: =IF(R$11=0,0,R37/R$11) -> 0 | V37: =IF(U$11=0,0,U37/U$11) -> 0 | X37: =IF(W$11=0,0,W37/W$11) -> 0 | AB37: =IF(AA$11=0,0,AA37/AA$11) -> 0 | AF37: =IF(AE$11=0,0,AE37/AE$11) -> 0
C38: 수선비 | I38: =IF(H$11=0,0,H38/H$11) -> 0 | K38: =IF(J$11=0,0,J38/J$11) -> 0 | O38: =IF(N$11=0,0,N38/N$11) -> 0 | S38: =IF(R$11=0,0,R38/R$11) -> 0 | V38: =IF(U$11=0,0,U38/U$11) -> 0 | X38: =IF(W$11=0,0,W38/W$11) -> 0 | AB38: =IF(AA$11=0,0,AA38/AA$11) -> 0 | AF38: =IF(AE$11=0,0,AE38/AE$11) -> 0
C39: 기타 | I39: =IF(H$11=0,0,H39/H$11) -> 0 | K39: =IF(J$11=0,0,J39/J$11) -> 0 | O39: =IF(N$11=0,0,N39/N$11) -> 0 | S39: =IF(R$11=0,0,R39/R$11) -> 0 | V39: =IF(U$11=0,0,U39/U$11) -> 0 | X39: =IF(W$11=0,0,W39/W$11) -> 0 | AB39: =IF(AA$11=0,0,AA39/AA$11) -> 0 | AF39: =IF(AE$11=0,0,AE39/AE$11) -> 0

Sheet 예제-비용효율지표
B2: Appendix 4. 본공장 관리지표 현황 - 비용효율 지표
X3: (unit : USD)
B4: 구 분 | H4: 당 월 | Q4: 연누계
H5: 총 계 | I5: 니카라과 | L5: 베트남 | O5: 미얀마 | Q5: 총 계 | R5: 니카라과 | U5: 베트남 | X5: 미얀마
J6: ISTMO | K6: TEXNICA | M6: SSVN | N6: SSTSVN | S6: ISTMO | T6: TEXNICA | V6: SSVN | W6: SSTSVN
B8: ■ 인당 인건비
D9: 공장-현지인
F10: (순)인건비-일반
F11: (순)인건비-OT
F12: 인건비성 경비
D13: 자재창고-현지인
F14: (순)인건비-일반
F15: (순)인건비-OT
F16: 인건비성 경비
D17: 재단-현지인
F18: (순)인건비-일반
F19: (순)인건비-OT
F20: 인건비성 경비
D21: 생산라인-현지인
F22: (순)인건비-일반
F23: (순)인건비-OT
F24: 인건비성 경비
D25: 완성반-현지인
F26: (순)인건비-일반
F27: (순)인건비-OT
F28: 인건비성 경비
B30: ■ MH당 인건비(Ⅰ)
D31: 공장-현지인
F32: (순)인건비
F33: 인건비성 경비
D34: 자재창고-현지인
F35: (순)인건비
F36: 인건비성 경비
D37: 재단-현지인
F38: (순)인건비
F39: 인건비성 경비
D40: 생산라인-현지인
F41: (순)인건비
F42: 인건비성 경비
D43: 완성반-현지인
F44: (순)인건비
F45: 인건비성 경비
B46: ■ MH당 인건비(Ⅱ) - OT제외
D47: 공장-현지인
F48: (순)인건비-일반
F49: 인건비성 경비
D50: 자재창고-현지인
F51: (순)인건비-일반
F52: 인건비성 경비
D53: 재단-현지인
F54: (순)인건비-일반
F55: 인건비성 경비
D56: 생산라인-현지인
F57: (순)인건비-일반
F58: 인건비성 경비
D59: 완성반-현지인
F60: (순)인건비-일반
F61: 인건비성 경비
B63: ■ Net CM 대비 기타 제조경비%

Sheet 6.Local Purchasing(미대상)
E3: Ⅵ. Purchasing
F5: : Local 구입 Packing 자재 등에 대해 등록하는 자료이나, 회계관리시스템으로 관리해도 무방한 것으로 판단됨.
F6: 생산관리시스템에서는 Local 자재를 수입자재와 구분하지 않고 관리하므로 Transaction 관련 메뉴를 시스템에 탑재할 필요 없다고 판단됨.
F10: Local 부자재 (영업팀 자재단가) - (공장영업)구매의뢰, 발주, 입고 - 재고
F11: (구매 한도관리 목적)

Sheet 7.HR
E3: Ⅶ. H/R
F5: 7-1. New Personnel information - Reg.
I8: New Personnel info - Reg. | P8: List
I10: Info. Reg Date | N10: YYYY-MM-DD | R10: ▤ | S10: □ | T10: Date Modify | AS10: SAVE | AV10: Delete
I12: Employee no. | N12: YYMMDD-XXXXX | T12: Create
I14: [ Personal Information ]
P16: Name | U16: Andrea | AC16: Birth date | AF16: YYYY-MM-DD | AJ16: ▤
P18: Social Security no. | U18: 244-64387 | AA18: Resident reg. no. | AF18: 203-140-183-000R
P20: Phone no. (Home) | U20: 1588-1588 | AA20: Mobile Phone no. | AF20: 1588-2222 | AL20: E-mail | AO20: jokkagoo@naver.com
P22: Home Address | U22: GRANADA.DIRIOMO BO.17 DE JULIO DE DONDE FUE OFICINAS TELCOR 1 1/2C.SUR.
I24: Upload | L24: Del | P24: Remark | U24: XXXXXX
I26: [ Employment Information ]
I28: Employment Date | N28: YYYY-MM-DD | R28: ▤ | T28: Retirement Date | Y28: YYYY-MM-DD | AC28: ▤
I30: Update Date | N30: YYYY-MM-DD | R30: ▤
I32: Department | N32: MASAYA 1 | T32: + | V32: ← 현지 Local 조직 및 부서체계 따름
I34: Position | N34: (직책) | S34: + | V34: Title | X34: (직위/직급) | AB34: + | AD34: Functions | AG34: (직능) | AK34: + | AM34: ← 현지 Local 조직 및 부서체계 따름
I37: * | J37: Management classification | Q37: MY1 | U37: + | W37: Function | Z37: Line Manager | AD37: +
I39: ↑ 본사&해외법인간 인원 및 기능별 Data 분류 위한 Global Master - 재무 예산부서 Setting 에 맞춰 세팅 (인사 재배치 시마다 수정 진행 필요)
I41: Career History | N41: ← 구현방법은 고민요망
I42: ■ | J42: Update | R42: Info. | AQ42: Management classification
J43: From | N43: To | R43: Emplyment | V43: Retirement | Z43: Department | AE43: Position | AI43: Title | AM43: Functions | AQ43: Class | AU43: Function
I44: □ | J44: YYYY-MM-DD | N44: YYYY-MM-DD | R44: YYYY-MM-DD | AQ44: MY1 | AU44: Line Manager
I45: □ | J45: YYYY-MM-DD | N45: YYYY-MM-DD | R45: YYYY-MM-DD | AQ45: MY2 | AU45: Line Manager
I46: □ | J46: YYYY-MM-DD | N46: YYYY-MM-DD | R46: YYYY-MM-DD | V46: YYYY-MM-DD | AQ46: MY3 | AU46: Line Manager
F52: 7-2. Attendance Management - Reg.
H54: : 일자별/라인별/Function별 근무일, 근무시간 집계 필요
H59: 기존 UI작동 및 집계방식, Local 기존 현황 참조후 개발
F65: 7-3. Salary Management
H67: : 근무일수, 근무Hour, 소속조직 및 Function별 월간 근무시간, 급여 항목별 집계 요망 (급여 항목 중 종업원 공제분 외, 회사 지급&공제분 포함)
H72: CO별 인사급여 산출 기준 및 현황 참조후 개발 (표준화 여부 검토)

Sheet 8.Machine
E3: Ⅷ. Machine
G5: : EarthN 시스템 화면 기반해 적용 (단, 생산관리지표상 필요한 라인투입 Machine 대수와 유휴기계 현황 반드시 조회가능해야 함)

Sheet Sheet5

Sheet 2.Cutting (삭제대상)
E2: Ⅱ. Spreading & Cutting
F4: ※ System Menu 구성
H6: ◆ Spreading & Cutting | P6: ◆ Cutting Fabric W/H | X6: □ | Y6: C.Fabric W/H IN - Reg. | AO6: : 재단반 원단창고 입고 등록
P7: (C.Fabric W/H) | X7: □ | Y7: C.Fabric W/H - Trans Location Reg. | AO7: : 재단반 원단창고 Location 변경 등록
X8: □ | Y8: C.Fabric W/H - Trans SPEC Reg. | AO8: : 재단반 원단창고 자재 SPEC 변경 등록 (File/Style/Color/Yds Info.)
X9: □ | Y9: C.Fabric W/H - Trans Split Reg. | AO9: : 재단반 원단창고 자재 Split 등록
X10: □ | Y10: C.Fabric W/H OUT - Reg. | AO10: : 재단반 원단창고 출고 등록
X12: (R) | Y12: C.Fabric W/H - IN-OUT Ledger | AO12: : 월별 재단반 원단창고 입출고 현황 (for Accounting)
X13: (R) | Y13: C.Fabric W/H - IN-OUT Status | AO13: : 기간별/누적 재단반 원단창고 입출고 현황
X14: (R) | Y14: C.Fabric W/H - Stock Status (by Present) | AO14: : 현재기준 재단반 원단창고 재고현황 (재고수량 및 Location)
P16: ◆ Spreading & Cutting | X16: □ | Y16: Sub-processing Plan - Reg (by C. Part) | AO16: : File-Style 재단 부위별 부속가공 계획 등록
X17: □ | Y17: Size Ratio by Marker - Reg. | AO17: : Marker Spec 등록
X18: □ | Y18: Spreading & Cutting - Reg. | AO18: : 연단&재단 실적 등록 (Incl.연단실적)
X19: □ | Y19: Sewing Process - Reg. (for Process tag printing) | AO19: : 파일/스타일별 공정등록 (옵션항목)
X20: □ | Y20: Bundle PKG - Reg. | AO20: : Bundle PKG 코드생성
X21: □ | Y21: C. Bundle PKG Setting - Reg. (PKG & IN - Reg.) | AO21: : Bundle PKG 내 Bundle 구성 등록 (옵션항목 : 동시 C.Bundle W/H IN 가능)
X23: (R) | Y23: Cutting Report | AO23: : 기간별 오더대비 재단물 상세현황
P25: ◆ Cutting Bundle W/H | X25: ▶ | Y25: Cutting Bundle IN-OUT
P26: (C.Bundle W/H) | X26: □ | Y26: C.Bundle W/H IN - Reg. (from Cutting) | AK26: (Garment 기준) | AO26: : 재단물 창고 입고 등록 (from 재단반)
X27: □ | Y27: C.Bundle W/H IN - Reg. | AK27: (Garment 기준) | AO27: : 재단물 창고 입고 등록 (재단반 外)
X28: □ | Y28: C.Bundle W/H - Trans Location Reg. | AK28: (Garment 기준) | AO28: : 재단물 창고 Location 변경 등록
X29: □ | Y29: C.Bundle W/H - Trans SPEC Reg. | AK29: (Garment 기준) | AO29: : 재단물 창고 자재 SPEC 변경 등록 (File/Style/color/Qty Info.)
X30: □ | Y30: C.Bundle W/H - Trans Split Reg. | AK30: (Garment 기준) | AO30: : 재단물 창고 자재 Split 등록
X31: □ | Y31: C.Bundle W/H OUT - Reg. | AK31: (Garment 기준) | AO31: : 재단물 창고 출고 등록
X33: ▶ | Y33: Sub-processing IN-OUT
Y34: □ | Z34: C.Bundle W/H OUT - Reg. (Sub-p) | AK34: (Parts 기준) | AO34: : 재단물 부속가공 출고 등록
Y35: □ | Z35: C.Bundle W/H Return OUT - Reg. (Sub-p) | AK35: (Parts 기준) | AO35: : 재단물 부속가공 재출고 등록
Y36: □ | Z36: C.Bundle W/H IN - Reg. (Sub-p) | AK36: (Parts 기준) | AO36: : 재단물 부속가공 입고 등록
X38: (R) | Y38: C.Bundle W/H - IN-OUT Ledger | AO38: : 월별 재단물 창고 입출고 현황 (for Accounting)
X39: (R) | Y39: C.Bundle W/H - IN-OUT Status | AO39: : 기간별/누적 재단물 창고 입출고 현황
X40: (R) | Y40: C.Bundle W/H - Stock Status (by Present) | AO40: : 현재기준 재단물 창고 재고 현황 (수량 및 Location)
X41: (R) | Y41: C.Bundle W/H - Sub-processing IN-OUT Status | AO41: : 재단물 부속가공 입출고 현황
F44: 2-1. C.Fabric W/H (Cutting - Fabric Warehouse)
G46: 2-1-1. C.Fabric W/H IN - Reg.
J49: C.Fabric W/H IN - Reg. | Q49: Status
J51: W/H IN Date | N51: YYYY-MM-DD | R51: ▤ | S51: □ | T51: Date Modify | X51: Depot | AA51: C. Fabric W/H | AG51: + | AX51: Query | BA51: SAVE | BD51: Delete
J53: [ W/H IN - Request Search ]
J55: Req. Date | M55: YYYY-MM-DD | Q55: ▤ | R55: ~ | S55: YYYY-MM-DD | W55: ▤ | X55: □ | Y55: Excl. already processed 'IN' | AG55: Source Depot | AK55: Material W/H | AQ55: +
J57: Buyer | M57: XXXXXXXXXX | Q57: ▤ | R57: File no | U57: XXXXXXXXXX | Y57: + | Z57: Style no | AC57: XXXXXXXXXX | AG57: + | AH57: Lot no | AK57: XXXXXXXXXX | AP57: OUT Reg. no | AT57: XXXXXXXXXX | AY57: Barcode | BB57: XXXXXXXXXX
J59: ■ | K59: IN Y/N | M59: OUT Reg Date | Q59: OUT Reg. no | U59: Source Depot | Y59: Order | AJ59: Item | BB59: Bulk Info. | BQ59: Gross Qty | BY59: Barcode
Y60: File no. | AC60: Style no. | AG60: Part | AJ60: CODE | AM60: Name | AR60: Description | AY60: Color | BB60: Lot no | BE60: Roll no | BH60: Unit | BK60: Qty | BN60: Width | BQ60: UNIT | BS60: Length | BV60: Weight | CE60: ▤
J61: □ | K61: N | M61: YY-MM-DD | Q61: XXXXXXXX | U61: Material W/H | Y61: TN19GB8044 | AC61: 12345 | AG61: BODY | AJ61: XXXXXXXX | AM61: XXXXXXXX | AR61: XXXXXXXXXXXXXXXXX | AY61: BLK | BB61: XXX1 | BE61: 1 | BH61: Roll | BK61: 1 | BN61: 66 | BQ61: YDS | BS61: 15 | BV61: 0 | BY61: XXXXXXXXXXXXXXXXX
J62: □ | K62: N | M62: YY-MM-DD | Q62: XXXXXXXX | U62: Material W/H | Y62: TN19GB8044 | AC62: 12345 | AG62: BODY | AJ62: XXXXXXXX | AM62: XXXXXXXX | AR62: XXXXXXXXXXXXXXXXX | AY62: BLK | BB62: XXX1 | BE62: 2 | BH62: Roll | BK62: 1 | BN62: 66 | BQ62: YDS | BS62: 20 | BV62: 0 | BY62: XXXXXXXXXXXXXXXXX
BE65: Total : | BI65: Bulk | BK65: 2 | BP65: Gross YDS | BS65: =BS62+BS61 -> 35 | BV65: =BV62+BV61 -> 0
J68: W/H Location | N68: (L.Zone) | Q68: ▼ | R68: P01 | U68: ▼ | V68: L01-C01 | Y68: ▼ | Z68: Apply | AC68: ◎ | AD68: Selection only | AH68: ○ | AI68: All | AK68: Barcode | AN68: XXXXXXXXXXXXXXXXX
AN70: ↑ W/H IN - Request 테이블에 조회된 내용을 기준으로, 대상 바코드 스캔하여 Material W/H IN - Reg 테이블로 보낼 수 있도록 하기 위한 목적. 단, 사전 WH Location 입력 필수
J72: [ W/H IN - Reg ] | O72: (-)Del Row | T72: IN Reg. no | X72: XXXXXXXXXX
J74: ■ | K74: OUT Reg. no | O74: Source Depot | S74: W/H Location | AB74: Order | AM74: Item | BE74: Lot no | BH74: Roll no | BK74: Bulk IN | BT74: Gross Qty | CB74: Barcode
S75: Zone | V75: Class 1 | Y75: Class 2 | AB75: File no. | AF75: Style no. | AJ75: Part | AM75: CODE | AP75: Name | AU75: Description | BB75: Color | BK75: Unit | BN75: Qty | BQ75: Width | BT75: UNIT | BV75: Length | BY75: Weight
J76: □ | K76: XXXXXXXX | O76: Material W/H | S76: (L.Zone) | V76: P01 | Y76: L01-C01 | AB76: TN19GB8044 | AF76: 12345 | AJ76: BODY | AM76: XXXXXXXX | AP76: XXXXXXXX | AU76: XXXXXXXXXXXXXXXXX | BB76: BLK | BE76: XXX1 | BH76: XX | BK76: Roll | BN76: 1 | BQ76: 66 | BT76: YDS | BV76: 15 | BY76: 0 | CB76: XXXXXXXXXXXXXXXXX
J77: □ | K77: XXXXXXXX | O77: Material W/H | S77: (L.Zone) | V77: P01 | Y77: L01-C01 | AB77: TN19GB8044 | AF77: 12345 | AJ77: BODY | AM77: XXXXXXXX | AP77: XXXXXXXX | AU77: XXXXXXXXXXXXXXXXX | BB77: BLK | BE77: XXX1 | BH77: XX | BK77: Roll | BN77: 1 | BQ77: 66 | BT77: YDS | BV77: 20 | BY77: 0 | CB77: XXXXXXXXXXXXXXXXX
BI80: Total : | BL80: Bulk | BN80: =BN76+BN77 -> 2 | BS80: Gross YDS | BV80: =BV77+BV76 -> 35 | BY80: =BY77+BY76 -> 0
J86: C.Fabric W/H IN - Reg. | Q86: Status
J88: W/H IN Date | O88: YYYY-MM-DD | S88: ▤ | T88: ~ | U88: YYYY-MM-DD | Y88: ▤ | AA88: Depot | AD88: C. Fabric W/H | AJ88: ▼ | CK88: Query | CN88: Excel
J90: Source Depot / TR | O90: (Depot or Transaction) | U90: ▼ | W90: W/H Location | AA90: (L.Zone) | AD90: ▼ | AE90: P01 | AH90: ▼ | AI90: L01-C01 | AL90: ▼
J92: Buyer | O92: XXXXXXXXXX | T92: File no. | W92: XXXXXXXXXX | AB92: + | AC92: Style no. | AF92: XXXXXXXXXX | AJ92: + | AK92: Lot no. | AN92: XXXXXXXXXX | AS92: IN Reg No. | AV92: XXXXXXXXXX | BA92: OUT Reg No. | BE92: XXXXXXXXXX | BJ92: Barcode | BM92: XXXXXXXXXX
J94: ■ | K94: IN Reg. no | O94: W/H IN Date | S94: Source Depot (Transaction) | W94: Depot (Present) | AA94: W/H Location | AJ94: Order | AU94: Item | BL94: Lot no | BO94: Roll no | BR94: Bulk IN | CA94: Gross Qty | CI94: OUT Reg. no | CM94: Barcode
AA95: Zone | AD95: Class 1 | AG95: Class 2 | AJ95: File no. | AN95: Style no. | AR95: Part | AU95: CODE | AX95: Name | BC95: Description | BI95: Color | BR95: Unit | BU95: Qty | BX95: Width | CA95: UNIT | CC95: Length | CF95: Weight
J96: □ | K96: XXXXXXXX | O96: YYYY-MM-DD | S96: Material W/H | W96: C.Fabric W/H | AA96: (L.Zone) | AD96: P01 | AG96: L01-C01 | AJ96: TN19GB8044 | AN96: 12345 | AR96: BODY | AU96: XXXXXXXX | AX96: XXXXXXXX | BC96: XXXXXXXXXXXXXXX | BI96: BLK | BL96: XXX1 | BO96: XX | BR96: Roll | BU96: 1 | BX96: 66 | CA96: YDS | CC96: 15 | CF96: 0 | CI96: XXXXXXXX | CM96: XXXXXXXX
J97: □ | K97: XXXXXXXX | O97: YYYY-MM-DD | S97: Material W/H | W97: C.Fabric W/H | AA97: (L.Zone) | AD97: P01 | AG97: L01-C01 | AJ97: TN19GB8044 | AN97: 12345 | AR97: BODY | AU97: XXXXXXXX | AX97: XXXXXXXX | BC97: XXXXXXXXXXXXXXX | BI97: BLK | BL97: XXX1 | BO97: XX | BR97: Roll | BU97: 1 | BX97: 66 | CA97: YDS | CC97: 20 | CF97: 0 | CI97: XXXXXXXX | CM97: XXXXXXXX
J100: * Row 더블클릭시, C.Fabric W/H IN - Reg 화면으로 전환 (for INPUT 수정&삭제) | BP100: Total : | BS100: Bulk | BU100: =BU96+BU97 -> 2 | BZ100: Gross YDS | CC100: =CC97+CC96 -> 35 | CF100: =CF97+CF96 -> 0
G105: 2-1-2. C.Fabric W/H - Trans Location Reg.
J108: C.Fabric W/H - Trans Location Reg. | S108: Status
J110: Reg Date | M110: YYYY-MM-DD | R110: ▤ | S110: □ | T110: Date Modify | W110: Depot | AA110: C. Fabric W/H | AG110: + | AV110: Query | AY110: Save | BB110: Delete
J112: File no. | M112: XXXXXXXXXX | R112: + | S112: Style no. | V112: XXXXXXXXXX | AA112: + | AC112: W/H Location | AG112: (L.Zone) | AJ112: ▼ | AK112: P01 | AN112: ▼ | AO112: L01-C01 | AR112: ▼
J114: [ Query details ]
J116: ■ | K116: Depot | P116: W/H Location | AB116: Order | AM116: Item | BE116: Bulk Info. | BT116: Gross Qty | CB116: Barcode
P117: Zone | T117: Class 1 | X117: Class 2 | AB117: File no. | AF117: Style no. | AJ117: Part | AM117: CODE | AP117: Name | AU117: Description | BB117: Color | BE117: Lot no | BH117: Roll no | BK117: UNIT | BN117: Qty | BQ117: Width | BT117: UNIT | BV117: Length | BY117: Weight
J118: V | K118: C. Fabric W/H | P118: (L.Zone) | T118: P01 | X118: L01-C01 | AB118: TN19GB8044 | AF118: 12345 | AJ118: BODY | AM118: XXXXXXXX | AP118: XXXXXXXX | AU118: XXXXXXXXXXXXXXXXX | BB118: BLK | BE118: XXX1 | BH118: 1 | BK118: Roll | BN118: 1 | BQ118: 66 | BT118: YDS | BV118: 60 | BY118: - | CB118: XXXXXXXXXXXXXXXXX | CH118: ▤
J119: V | K119: C. Fabric W/H | P119: (L.Zone) | T119: P01 | X119: L01-C01 | AB119: TN19GB8044 | AF119: 12345 | AJ119: BODY | AM119: XXXXXXXX | AP119: XXXXXXXX | AU119: XXXXXXXXXXXXXXXXX | BB119: BLK | BE119: XXX2 | BH119: 2 | BK119: Roll | BN119: 1 | BQ119: 66 | BT119: YDS | BV119: 40 | BY119: - | CB119: XXXXXXXXXXXXXXXXX
J120: □ | K120: C. Fabric W/H | P120: (L.Zone) | T120: P01 | X120: L01-C01 | AB120: TN19GB8044 | AF120: 12345 | AJ120: BODY | AM120: XXXXXXXX | AP120: XXXXXXXX | AU120: XXXXXXXXXXXXXXXXX | BB120: BLK | BE120: XXX3 | BH120: 3 | BK120: Roll | BN120: 1 | BQ120: 66 | BT120: YDS | BV120: 100 | BY120: - | CB120: XXXXXXXXXXXXXXXXX
BL123: Total | BN123: =BN120+BN119+BN118 -> 3 | BV123: =BV120+BV119+BV118 -> 200 | BY123: -
J127: Trans Location | N127: (L.Zone) | Q127: ▼ | R127: P01 | U127: ▼ | V127: L01-C02 | Y127: ▼ | Z127: Add & Apply | AF127: Barcode | AI127: XXXXXXXXXXXXXXXXX
AI128: ↑ 조건 입력후 조회할 수도 있으나 변경대상 바코드 스캔하여 Trans Location - Reg 테이블로 보낼 수 있도록 하기 위한 목적. 단, 사전 Trans Location 입력 필수
J131: [ Trans Location - Reg. ] | P131: Del | U131: Reg No. | X131: XXXXXXXXXX
J133: ■ | K133: Depot | P133: W/H Location | AB133: Order | AM133: Item | BE133: Bulk Info. | BT133: Gross Qty | CB133: Barcode
P134: Zone | T134: Class 1 | X134: Class 2 | AB134: File no. | AF134: Style no. | AJ134: Part | AM134: CODE | AP134: Name | AU134: Description | BB134: Color | BE134: Lot no | BH134: Roll no | BK134: UNIT | BN134: Qty | BQ134: Width | BT134: UNIT | BV134: Length | BY134: Weight
J135: □ | K135: C. Fabric W/H | P135: (L.Zone) | T135: P01 | X135: L01-C02 | AB135: TN19GB8044 | AF135: 12345 | AJ135: BODY | AM135: XXXXXXXX | AP135: XXXXXXXX | AU135: XXXXXXXXXXXXXXXXX | BB135: BLK | BE135: XXX1 | BH135: 1 | BK135: Roll | BN135: 1 | BQ135: 66 | BT135: YDS | BV135: 60 | BY135: 0 | CB135: XXXXXXXXXXXXXXXXX | CH135: ▤
J136: □ | K136: C. Fabric W/H | P136: (L.Zone) | T136: P01 | X136: L01-C02 | AB136: TN19GB8044 | AF136: 12345 | AJ136: BODY | AM136: XXXXXXXX | AP136: XXXXXXXX | AU136: XXXXXXXXXXXXXXXXX | BB136: BLK | BE136: XXX1 | BH136: 1 | BK136: Roll | BN136: 1 | BQ136: 66 | BT136: YDS | BV136: 50 | BY136: 0 | CB136: XXXXXXXXXXXXXXXXX
BJ139: Total : | BN139: =BN135+BN136 -> 2 | BT139: YDS | BV139: =BV135+BV136 -> 110 | BY139: =BY135+BY136 -> 0
J145: C.Fabric W/H - Trans Location Reg. | T145: Status
J147: Reg Date | M147: YYYY-MM-DD | Q147: ▤ | R147: ~ | S147: YYYY-MM-DD | W147: ▤ | Y147: Depot | AB147: C. Fabric W/H | AH147: + | CO147: Query | CR147: Excel
J149: Buyer | M149: XXXXXXXXXX | S149: File no. | U149: XXXXXXXXXX | Z149: + | AA149: Style no. | AD149: XXXXXXXXXX | AH149: + | AI149: Lot no. | AL149: XXXXXXXXXX | AQ149: Barcode | AT149: XXXXXXXXXX | AY149: Reg no. | BB149: XXXXXXXXXX
J151: ■ | K151: Reg no. | O151: Reg Date | S151: Depot | Y151: Before | AH151: After | AQ151: Order | BB151: Item | BT151: Bulk Info. | CI151: Gross Qty | CQ151: Barcode
Y152: Zone | AB152: Class 1 | AE152: Class 2 | AH152: Zone | AK152: Class 1 | AN152: Class 2 | AQ152: File no. | AU152: Style no. | AY152: Part | BB152: CODE | BE152: Name | BJ152: Description | BQ152: Color | BT152: Lot no | BW152: Roll no | BZ152: UNIT | CC152: Qty | CF152: Width | CI152: UNIT | CK152: Length | CN152: Weight
J153: □ | K153: XXXXXXXX | O153: YYYY-MM-DD | S153: C. Fabric W/H | Y153: (L.Zone) | AB153: P01 | AE153: L01-C01 | AH153: (L.Zone) | AK153: P01 | AN153: L01-C02 | AQ153: TN19GB8044 | AU153: 12345 | AY153: BODY | BB153: XXXXXXXX | BE153: XXXXXXXX | BJ153: XXXXXXXXXXXXXXXXX | BQ153: BLK | BT153: XXX1 | BW153: 1 | BZ153: Roll | CC153: 1 | CF153: 66 | CI153: YDS | CK153: 60 | CN153: 0 | CQ153: XXXXXXXX
J154: □ | K154: XXXXXXXX | O154: YYYY-MM-DD | S154: C. Fabric W/H | Y154: (L.Zone) | AB154: P01 | AE154: L01-C01 | AH154: (L.Zone) | AK154: P01 | AN154: L01-C02 | AQ154: TN19GB8044 | AU154: 12345 | AY154: BODY | BB154: XXXXXXXX | BE154: XXXXXXXX | BJ154: XXXXXXXXXXXXXXXXX | BQ154: BLK | BT154: XXX1 | BW154: 1 | BZ154: Roll | CC154: 1 | CF154: 66 | CI154: YDS | CK154: 50 | CN154: 0 | CQ154: XXXXXXXX
BY157: Total : | CC157: =CC153+CC154 -> 2 | CI157: YDS | CK157: =CK153+CK154 -> 110 | CN157: =CN153+CN154 -> 0
J160: * Trans Location 정보는 입출고현황의 입출고 내역(수량)에 표현하지 않음
G163: 2-1-3. C.Fabric W/H - Trans SPEC Reg.
J166: C.Fabric W/H - Trans SPEC Reg. | T166: Status
J168: Reg Date | N168: YYYY-MM-DD | S168: ▤ | T168: □ | U168: Date Modify | X168: Depot | AB168: C. Fabric W/H | AH168: + | AJ168: Barcode | AM168: XXXXXXXXXXXXXXXXX | AW168: Query | AZ168: Save | BC168: Delete | BG168: Barcode Print
J170: W/H Location | N170: (L.Zone) | Q170: ▼ | R170: P01 | U170: ▼ | V170: L01-C01 | Y170: ▼ | AZ170: ↑ Save 시 바코드 신규생성
J172: File no. | N172: XXXXXXXXXX | S172: + | T172: Style no. | W172: XXXXXXXXXX | AB172: +
J174: [ Query details ]
J176: ■ | K176: Depot | P176: W/H Location | AB176: Order | AM176: Item | BE176: Bulk Info. | BT176: Gross Qty | CB176: Barcode
P177: Zone | T177: Class 1 | X177: Class 2 | AB177: File no. | AF177: Style no. | AJ177: Part | AM177: CODE | AP177: Name | AU177: Description | BB177: Color | BE177: Lot no | BH177: Roll no | BK177: UNIT | BN177: Qty | BQ177: Width | BT177: UNIT | BV177: Length | BY177: Weight
J178: V | K178: C. Fabric W/H | P178: (L.Zone) | T178: P01 | X178: L01-C01 | AB178: TN19GB8044 | AF178: 12345 | AJ178: BODY | AM178: XXXXXXXX | AP178: XXXXXXXX | AU178: XXXXXXXXXXXXXXXXX | BB178: BLK | BE178: XXX1 | BH178: 1 | BK178: Roll | BN178: 1 | BQ178: 66 | BT178: YDS | BV178: 60 | BY178: - | CB178: XXXXXXXXXXXXXXXXX | CH178: ▤
J179: V | K179: C. Fabric W/H | P179: (L.Zone) | T179: P01 | X179: L01-C01 | AB179: TN19GB8044 | AF179: 12345 | AJ179: BODY | AM179: XXXXXXXX | AP179: XXXXXXXX | AU179: XXXXXXXXXXXXXXXXX | BB179: BLK | BE179: XXX2 | BH179: 2 | BK179: Roll | BN179: 1 | BQ179: 66 | BT179: YDS | BV179: 40 | BY179: - | CB179: XXXXXXXXXXXXXXXXX
J180: □ | K180: C. Fabric W/H | P180: (L.Zone) | T180: P01 | X180: L01-C01 | AB180: TN19GB8044 | AF180: 12345 | AJ180: BODY | AM180: XXXXXXXX | AP180: XXXXXXXX | AU180: XXXXXXXXXXXXXXXXX | BB180: BLK | BE180: XXX3 | BH180: 3 | BK180: Roll | BN180: 1 | BQ180: 66 | BT180: YDS | BV180: 100 | BY180: - | CB180: XXXXXXXXXXXXXXXXX
...
